Workbook

Sheet README
A1: TMMIN Next-Level Kaizen: Case Model & Answer Kit
A2: Working file for the team. Every number traces to a case exhibit or a labeled assumption.
A4: Colour legend
A5: Blue text | B5: Hardcoded input (from the case or a team assumption)
A6: Black text | B6: Formula, do not overwrite
A7: Green text | B7: Link from another tab
A8: Yellow fill | B8: Key assumption the team must justify or change
A9: Red fill | B9: VERIFY against the original casebook PDF (text came through garbled)
A11: Tab map
A12: WBS | B12: Work breakdown: who does what, which day, done criteria, hours, daily Gantt. Start here.
A13: Answer_Guide | B13: How to answer each sub-question, deck storyline with action titles, Q&A prep
A14: Ideation | B14: 8 idea options with case gaps, TPS anchor, Toyota precedent, references, weighted scoring
A15: Simulation | B15: Idea tests run in Python: closed-loop quality sim, financial Monte Carlo, roadmap strategies, tornado
A16: Exhibits | B16: Clean re-typed case data (Exhibits 1, 3-9). Fix red cells first
A17: Assumptions | B17: All model inputs + benchmark evidence for each lever; pilot-light phasing
A18: Model | B18: Savings by lever, investment, running cost, NPV, IRR, payback for 3 scenarios (2026-2030)
A19: Dashboard | B19: Scenario summary and charts for the financial slide
A20: Breakeven | B20: How much saving pays back Rp40-120B, plus NPV sensitivity grid
A21: Capability | B21: Workforce model: engineer skill levels, improvement time, know-how, ramp-up to 2030
A22: KPIs | B22: KPI tree with baselines from exhibits and suggested pilot / 2030 targets
A23: Roadmap | B23: Phased 2026-2030 roadmap template across workstreams
... A25: QA_Bank | B25: 15 likely judge questions with answer outline, evidence and owner
A27: How to use
A28: 1. Day 1: type names in WBS, re-type every red cell in Exhibits from the PDF.
A29: 2. Day 2-3: re-score Ideation as a team, lock ONE integrated idea + one pilot area by end of Day 3.
A30: 3. Day 3-4: replace yellow assumptions with numbers you can defend (Assumptions column G shows benchmarks found so far).
A31: 4. Day 5: re-run run_tests.py so the Simulation tab matches your final assumptions.
A32: 5. Dashboard, Breakeven and Capability update automatically. Example values in yellow cells are placeholders, not facts.

Sheet WBS
A1: Work breakdown structure: 7 days, 3 members
A2: Type your names in the yellow cells. Owner = accountable (hours counted); Support = helps. Update Status daily in the stand-up. Daily load is red above 6.5 hours.
A4: Code | B4: Name | C4: Role & accountable for | D4: Hours owned | E4: Tasks owned | F4: Tasks done | J4: Load (h/day) | K4: D1 | L4: D2 | M4: D3 | N4: D4 | O4: D5 | P4: D6 | Q4: D7
A5: M1 | B5: [Name M1] | C5: Lead, storyline & people: Owns problem framing, vision, idea decision, mindset & knowledge mechanism, governance, risks, exec summary, speaking script, mocks, submission | D5: =SUMIF($D$13:$D$70,A5,$H$13:$H$70) | E5: =COUNTIF($D$13:$D$70,A5) | F5: =COUNTIFS($D$13:$D$70,A5,$J$13:$J$70,"Done") | J5: M1 | K5: =SUMPRODUCT(($D$13:$D$70=$A5)*($F$13:$F$70<=1)*($G$13:$G$70>=1),$H$13:$H$70/($G$13:$G$70-$F$13:$F$70+1)) | L5: =SUMPRODUCT(($D$13:$D$70=$A5)*($F$13:$F$70<=2)*($G$13:$G$70>=2),$H$13:$H$70/($G$13:$G$70-$F$13:$F$70+1)) | M5: =SUMPRODUCT(($D$13:$D$70=$A5)*($F$13:$F$70<=3)*($G$13:$G$70>=3),$H$13:$H$70/($G$13:$G$70-$F$13:$F$70+1)) | N5: =SUMPRODUCT(($D$13:$D$70=$A5)*($F$13:$F$70<=4)*($G$13:$G$70>=4),$H$13:$H$70/($G$13:$G$70-$F$13:$F$70+1)) | O5: =SUMPRODUCT(($D$13:$D$70=$A5)*($F$13:$F$70<=5)*($G$13:$G$70>=5),$H$13:$H$70/($G$13:$G$70-$F$13:$F$70+1)) | P5: =SUMPRODUCT(($D$13:$D$70=$A5)*($F$13:$F$70<=6)*($G$13:$G$70>=6),$H$13:$H$70/($G$13:$G$70-$F$13:$F$70+1)) | Q5: =SUMPRODUCT(($D$13:$D$70=$A5)*($F$13:$F$70<=7)*($G$13:$G$70>=7),$H$13:$H$70/($G$13:$G$70-$F$13:$F$70+1))
A6: M2 | B6: [Name M2] | C6: Operations, TPS & roadmap: Owns gap heat map, root cause, system diagram, day-in-the-life, build-vs-partner, TPS fit, roadmap, slide template and design polish | D6: =SUMIF($D$13:$D$70,A6,$H$13:$H$70) | E6: =COUNTIF($D$13:$D$70,A6) | F6: =COUNTIFS($D$13:$D$70,A6,$J$13:$J$70,"Done") | J6: M2 | K6: =SUMPRODUCT(($D$13:$D$70=$A6)*($F$13:$F$70<=1)*($G$13:$G$70>=1),$H$13:$H$70/($G$13:$G$70-$F$13:$F$70+1)) | L6: =SUMPRODUCT(($D$13:$D$70=$A6)*($F$13:$F$70<=2)*($G$13:$G$70>=2),$H$13:$H$70/($G$13:$G$70-$F$13:$F$70+1)) | M6: =SUMPRODUCT(($D$13:$D$70=$A6)*($F$13:$F$70<=3)*($G$13:$G$70>=3),$H$13:$H$70/($G$13:$G$70-$F$13:$F$70+1)) | N6: =SUMPRODUCT(($D$13:$D$70=$A6)*($F$13:$F$70<=4)*($G$13:$G$70>=4),$H$13:$H$70/($G$13:$G$70-$F$13:$F$70+1)) | O6: =SUMPRODUCT(($D$13:$D$70=$A6)*($F$13:$F$70<=5)*($G$13:$G$70>=5),$H$13:$H$70/($G$13:$G$70-$F$13:$F$70+1)) | P6: =SUMPRODUCT(($D$13:$D$70=$A6)*($F$13:$F$70<=6)*($G$13:$G$70>=6),$H$13:$H$70/($G$13:$G$70-$F$13:$F$70+1)) | Q6: =SUMPRODUCT(($D$13:$D$70=$A6)*($F$13:$F$70<=7)*($G$13:$G$70>=7),$H$13:$H$70/($G$13:$G$70-$F$13:$F$70+1))
A7: M3 | B7: [Name M3] | C7: Quant, finance & evidence: Owns exhibits data, benchmarks, assumptions, Model, simulation re-runs, capability model, KPIs, appendix, number tie-out, Q&A bank | D7: =SUMIF($D$13:$D$70,A7,$H$13:$H$70) | E7: =COUNTIF($D$13:$D$70,A7) | F7: =COUNTIFS($D$13:$D$70,A7,$J$13:$J$70,"Done") | J7: M3 | K7: =SUMPRODUCT(($D$13:$D$70=$A7)*($F$13:$F$70<=1)*($G$13:$G$70>=1),$H$13:$H$70/($G$13:$G$70-$F$13:$F$70+1)) | L7: =SUMPRODUCT(($D$13:$D$70=$A7)*($F$13:$F$70<=2)*($G$13:$G$70>=2),$H$13:$H$70/($G$13:$G$70-$F$13:$F$70+1)) | M7: =SUMPRODUCT(($D$13:$D$70=$A7)*($F$13:$F$70<=3)*($G$13:$G$70>=3),$H$13:$H$70/($G$13:$G$70-$F$13:$F$70+1)) | N7: =SUMPRODUCT(($D$13:$D$70=$A7)*($F$13:$F$70<=4)*($G$13:$G$70>=4),$H$13:$H$70/($G$13:$G$70-$F$13:$F$70+1)) | O7: =SUMPRODUCT(($D$13:$D$70=$A7)*($F$13:$F$70<=5)*($G$13:$G$70>=5),$H$13:$H$70/($G$13:$G$70-$F$13:$F$70+1)) | P7: =SUMPRODUCT(($D$13:$D$70=$A7)*($F$13:$F$70<=6)*($G$13:$G$70>=6),$H$13:$H$70/($G$13:$G$70-$F$13:$F$70+1)) | Q7: =SUMPRODUCT(($D$13:$D$70=$A7)*($F$13:$F$70<=7)*($G$13:$G$70>=7),$H$13:$H$70/($G$13:$G$70-$F$13:$F$70+1))
A8: Total | D8: =SUM(D5:D7) | E8: =SUM(E5:E7) | F8: =SUM(F5:F7) | J8: Team | K8: =SUM(K5:K7) | L8: =SUM(L5:L7) | M8: =SUM(M5:M7) | N8: =SUM(N5:N7) | O8: =SUM(O5:O7) | P8: =SUM(P5:P7) | Q8: =SUM(Q5:Q7)
C9: Owned hours are balanced within ~4 h. Each member also supports others' tasks (Support column).
A12: WBS | B12: Work package / task | C12: Deliverable & done criteria | D12: Owner | E12: Support | F12: Start day | G12: End day | H12: Hours | I12: Depends on | J12: Status | K12: D1 | L12: D2 | M12: D3 | N12: D4 | O12: D5 | P12: D6 | Q12: D7
A13: 1 | B13: PROJECT MANAGEMENT | F13: 0 | G13: 0
A14: 1.1 | B14: Kick-off: roles, deadline, shared drive, task tracker | C14: Roles agreed, folder + tracker live | D14: M1 | E14: All | F14: 1 | G14: 1 | H14: 2 | J14: Not started | K14: =IF(AND(1>=$F14,1<=$G14),$D14,"") | L14: =IF(AND(2>=$F14,2<=$G14),$D14,"") | M14: =IF(AND(3>=$F14,3<=$G14),$D14,"") | N14: =IF(AND(4>=$F14,4<=$G14),$D14,"") | O14: =IF(AND(5>=$F14,5<=$G14),$D14,"") | P14: =IF(AND(6>=$F14,6<=$G14),$D14,"") | Q14: =IF(AND(7>=$F14,7<=$G14),$D14,"")
A15: 1.2 | B15: Confirm rules in writing (slide limit, format, AI use, judging criteria) | C15: Written confirmation saved | D15: M1 | F15: 1 | G15: 1 | H15: 1 | J15: Not started | K15: =IF(AND(1>=$F15,1<=$G15),$D15,"") | L15: =IF(AND(2>=$F15,2<=$G15),$D15,"") | M15: =IF(AND(3>=$F15,3<=$G15),$D15,"") | N15: =IF(AND(4>=$F15,4<=$G15),$D15,"") | O15: =IF(AND(5>=$F15,5<=$G15),$D15,"") | P15: =IF(AND(6>=$F15,6<=$G15),$D15,"") | Q15: =IF(AND(7>=$F15,7<=$G15),$D15,"")
A16: 1.3 | B16: Daily 15-min stand-up + update this sheet | C16: Status column current every evening | D16: M1 | E16: All | F16: 1 | G16: 7 | H16: 2 | I16: 1.1 | J16: Not started | K16: =IF(AND(1>=$F16,1<=$G16),$D16,"") | L16: =IF(AND(2>=$F16,2<=$G16),$D16,"") | M16: =IF(AND(3>=$F16,3<=$G16),$D16,"") | N16: =IF(AND(4>=$F16,4<=$G16),$D16,"") | O16: =IF(AND(5>=$F16,5<=$G16),$D16,"") | P16: =IF(AND(6>=$F16,6<=$G16),$D16,"") | Q16: =IF(AND(7>=$F16,7<=$G16),$D16,"")
A17: 2 | B17: DIAGNOSE THE PROBLEM (SQ1) | F17: 0 | G17: 0
A18: 2.1 | B18: Re-type exhibits from PDF; clear all red cells | C18: Exhibits tab has zero VERIFY cells | D18: M3 | E18: M2 | F18: 1 | G18: 1 | H18: 2 | J18: Not started | K18: =IF(AND(1>=$F18,1<=$G18),$D18,"") | L18: =IF(AND(2>=$F18,2<=$G18),$D18,"") | M18: =IF(AND(3>=$F18,3<=$G18),$D18,"") | N18: =IF(AND(4>=$F18,4<=$G18),$D18,"") | O18: =IF(AND(5>=$F18,5<=$G18),$D18,"") | P18: =IF(AND(6>=$F18,6<=$G18),$D18,"") | Q18: =IF(AND(7>=$F18,7<=$G18),$D18,"")
A19: 2.2 | B19: Issue tree + problem statement | C19: 1-page issue tree, MECE, agreed by team | D19: M1 | E19: All | F19: 1 | G19: 1 | H19: 3 | I19: 2.1 | J19: Not started | K19: =IF(AND(1>=$F19,1<=$G19),$D19,"") | L19: =IF(AND(2>=$F19,2<=$G19),$D19,"") | M19: =IF(AND(3>=$F19,3<=$G19),$D19,"") | N19: =IF(AND(4>=$F19,4<=$G19),$D19,"") | O19: =IF(AND(5>=$F19,5<=$G19),$D19,"") | P19: =IF(AND(6>=$F19,6<=$G19),$D19,"") | Q19: =IF(AND(7>=$F19,7<=$G19),$D19,"")
A20: 2.3 | B20: Gap heat map: process x cost/quality impact | C20: Heat map slide using Exhibits 4-5 | D20: M2 | E20: M3 | F20: 1 | G20: 2 | H20: 4 | I20: 2.1 | J20: Not started | K20: =IF(AND(1>=$F20,1<=$G20),$D20,"") | L20: =IF(AND(2>=$F20,2<=$G20),$D20,"") | M20: =IF(AND(3>=$F20,3<=$G20),$D20,"") | N20: =IF(AND(4>=$F20,4<=$G20),$D20,"") | O20: =IF(AND(5>=$F20,5<=$G20),$D20,"") | P20: =IF(AND(6>=$F20,6<=$G20),$D20,"") | Q20: =IF(AND(7>=$F20,7<=$G20),$D20,"")
A21: 2.4 | B21: Root cause (5-whys / fishbone) on the 3 complications | C21: Root-cause slide: 'open loops' | D21: M2 | E21: M1 | F21: 2 | G21: 2 | H21: 3 | I21: 2.2 | J21: Not started | K21: =IF(AND(1>=$F21,1<=$G21),$D21,"") | L21: =IF(AND(2>=$F21,2<=$G21),$D21,"") | M21: =IF(AND(3>=$F21,3<=$G21),$D21,"") | N21: =IF(AND(4>=$F21,4<=$G21),$D21,"") | O21: =IF(AND(5>=$F21,5<=$G21),$D21,"") | P21: =IF(AND(6>=$F21,6<=$G21),$D21,"") | Q21: =IF(AND(7>=$F21,7<=$G21),$D21,"")
A22: 2.5 | B22: Benchmark research: Toyota precedents + lever benchmarks | C22: Ideation refs + Assumptions col G complete | D22: M3 | E22: M2 | F22: 2 | G22: 3 | H22: 4 | J22: Not started | K22: =IF(AND(1>=$F22,1<=$G22),$D22,"") | L22: =IF(AND(2>=$F22,2<=$G22),$D22,"") | M22: =IF(AND(3>=$F22,3<=$G22),$D22,"") | N22: =IF(AND(4>=$F22,4<=$G22),$D22,"") | O22: =IF(AND(5>=$F22,5<=$G22),$D22,"") | P22: =IF(AND(6>=$F22,6<=$G22),$D22,"") | Q22: =IF(AND(7>=$F22,7<=$G22),$D22,"")
A23: 2.6 | B23: 2030 vision + 'value beyond cost' statement | C23: Vision slide draft | D23: M1 | E23: M2 | F23: 2 | G23: 2 | H23: 2 | I23: 2.3 | J23: Not started | K23: =IF(AND(1>=$F23,1<=$G23),$D23,"") | L23: =IF(AND(2>=$F23,2<=$G23),$D23,"") | M23: =IF(AND(3>=$F23,3<=$G23),$D23,"") | N23: =IF(AND(4>=$F23,4<=$G23),$D23,"") | O23: =IF(AND(5>=$F23,5<=$G23),$D23,"") | P23: =IF(AND(6>=$F23,6<=$G23),$D23,"") | Q23: =IF(AND(7>=$F23,7<=$G23),$D23,"")
A24: 3 | B24: DESIGN THE IDEA (SQ2) | F24: 0 | G24: 0
A25: 3.1 | B25: Ideation session: re-score 8 options as a team | C25: Scoring matrix updated with team scores | D25: M1 | E25: All | F25: 3 | G25: 3 | H25: 2 | I25: 2.4 | J25: Not started | K25: =IF(AND(1>=$F25,1<=$G25),$D25,"") | L25: =IF(AND(2>=$F25,2<=$G25),$D25,"") | M25: =IF(AND(3>=$F25,3<=$G25),$D25,"") | N25: =IF(AND(4>=$F25,4<=$G25),$D25,"") | O25: =IF(AND(5>=$F25,5<=$G25),$D25,"") | P25: =IF(AND(6>=$F25,6<=$G25),$D25,"") | Q25: =IF(AND(7>=$F25,7<=$G25),$D25,"")
A26: 3.2 | B26: Decide integrated idea + pilot area (decision log) | C26: One-line decision + 3 reasons | D26: M1 | E26: All | F26: 3 | G26: 3 | H26: 1 | I26: 3.1 | J26: Not started | K26: =IF(AND(1>=$F26,1<=$G26),$D26,"") | L26: =IF(AND(2>=$F26,2<=$G26),$D26,"") | M26: =IF(AND(3>=$F26,3<=$G26),$D26,"") | N26: =IF(AND(4>=$F26,4<=$G26),$D26,"") | O26: =IF(AND(5>=$F26,5<=$G26),$D26,"") | P26: =IF(AND(6>=$F26,6<=$G26),$D26,"") | Q26: =IF(AND(7>=$F26,7<=$G26),$D26,"")
A27: 3.3 | B27: System diagram: three closed loops | C27: One clean diagram, reviewed by all | D27: M2 | E27: M1 | F27: 3 | G27: 3 | H27: 3 | I27: 3.2 | J27: Not started | K27: =IF(AND(1>=$F27,1<=$G27),$D27,"") | L27: =IF(AND(2>=$F27,2<=$G27),$D27,"") | M27: =IF(AND(3>=$F27,3<=$G27),$D27,"") | N27: =IF(AND(4>=$F27,4<=$G27),$D27,"") | O27: =IF(AND(5>=$F27,5<=$G27),$D27,"") | P27: =IF(AND(6>=$F27,6<=$G27),$D27,"") | Q27: =IF(AND(7>=$F27,7<=$G27),$D27,"")
A28: 3.4 | B28: Day-in-the-life before/after (operator, team leader, engineer) | C28: Before/after slide | D28: M2 | E28: M1 | F28: 4 | G28: 4 | H28: 3 | I28: 3.2 | J28: Not started | K28: =IF(AND(1>=$F28,1<=$G28),$D28,"") | L28: =IF(AND(2>=$F28,2<=$G28),$D28,"") | M28: =IF(AND(3>=$F28,3<=$G28),$D28,"") | N28: =IF(AND(4>=$F28,4<=$G28),$D28,"") | O28: =IF(AND(5>=$F28,5<=$G28),$D28,"") | P28: =IF(AND(6>=$F28,6<=$G28),$D28,"") | Q28: =IF(AND(7>=$F28,7<=$G28),$D28,"")
A29: 3.5 | B29: Mindset & knowledge mechanism (idea channel, capture, recognition) | C29: Mechanism slide tied to Exhibits 6A/6B | D29: M1 | E29: M2 | F29: 4 | G29: 4 | H29: 3 | I29: 3.2 | J29: Not started | K29: =IF(AND(1>=$F29,1<=$G29),$D29,"") | L29: =IF(AND(2>=$F29,2<=$G29),$D29,"") | M29: =IF(AND(3>=$F29,3<=$G29),$D29,"") | N29: =IF(AND(4>=$F29,4<=$G29),$D29,"") | O29: =IF(AND(5>=$F29,5<=$G29),$D29,"") | P29: =IF(AND(6>=$F29,6<=$G29),$D29,"") | Q29: =IF(AND(7>=$F29,7<=$G29),$D29,"")
A30: 3.6 | B30: Build vs partner logic per component | C30: 2x2 or table slide | D30: M2 | E30: M3 | F30: 4 | G30: 5 | H30: 2 | I30: 3.2 | J30: Not started | K30: =IF(AND(1>=$F30,1<=$G30),$D30,"") | L30: =IF(AND(2>=$F30,2<=$G30),$D30,"") | M30: =IF(AND(3>=$F30,3<=$G30),$D30,"") | N30: =IF(AND(4>=$F30,4<=$G30),$D30,"") | O30: =IF(AND(5>=$F30,5<=$G30),$D30,"") | P30: =IF(AND(6>=$F30,6<=$G30),$D30,"") | Q30: =IF(AND(7>=$F30,7<=$G30),$D30,"")
A31: 3.7 | B31: TPS principle mapping (jidoka, kaizen, standardized work, yokoten) | C31: Mapping table | D31: M2 | F31: 3 | G31: 3 | H31: 1 | I31: 3.3 | J31: Not started | K31: =IF(AND(1>=$F31,1<=$G31),$D31,"") | L31: =IF(AND(2>=$F31,2<=$G31),$D31,"") | M31: =IF(AND(3>=$F31,3<=$G31),$D31,"") | N31: =IF(AND(4>=$F31,4<=$G31),$D31,"") | O31: =IF(AND(5>=$F31,5<=$G31),$D31,"") | P31: =IF(AND(6>=$F31,6<=$G31),$D31,"") | Q31: =IF(AND(7>=$F31,7<=$G31),$D31,"")
A32: 4 | B32: ROADMAP & CAPABILITY (SQ3) | F32: 0 | G32: 0
A33: 4.1 | B33: Phased roadmap with gates (pilot-light) | C33: Roadmap slide with gate criteria | D33: M2 | E33: M3 | F33: 4 | G33: 5 | H33: 3 | I33: 3.2 | J33: Not started | K33: =IF(AND(1>=$F33,1<=$G33),$D33,"") | L33: =IF(AND(2>=$F33,2<=$G33),$D33,"") | M33: =IF(AND(3>=$F33,3<=$G33),$D33,"") | N33: =IF(AND(4>=$F33,4<=$G33),$D33,"") | O33: =IF(AND(5>=$F33,5<=$G33),$D33,"") | P33: =IF(AND(6>=$F33,6<=$G33),$D33,"") | Q33: =IF(AND(7>=$F33,7<=$G33),$D33,"")
A34: 4.2 | B34: Capability plan using Capability tab | C34: Academy design + L3+ targets consistent with KPIs | D34: M3 | E34: M1 | F34: 4 | G34: 5 | H34: 2 | I34: 3.2 | J34: Not started | K34: =IF(AND(1>=$F34,1<=$G34),$D34,"") | L34: =IF(AND(2>=$F34,2<=$G34),$D34,"") | M34: =IF(AND(3>=$F34,3<=$G34),$D34,"") | N34: =IF(AND(4>=$F34,4<=$G34),$D34,"") | O34: =IF(AND(5>=$F34,5<=$G34),$D34,"") | P34: =IF(AND(6>=$F34,6<=$G34),$D34,"") | Q34: =IF(AND(7>=$F34,7<=$G34),$D34,"")
A35: 4.3 | B35: Risk register + mitigations (quantify top risks with Simulation) | C35: Risks tab finalized, top 3 on slide | D35: M1 | E35: M3 | F35: 5 | G35: 5 | H35: 2 | I35: 4.1 | J35: Not started | K35: =IF(AND(1>=$F35,1<=$G35),$D35,"") | L35: =IF(AND(2>=$F35,2<=$G35),$D35,"") | M35: =IF(AND(3>=$F35,3<=$G35),$D35,"") | N35: =IF(AND(4>=$F35,4<=$G35),$D35,"") | O35: =IF(AND(5>=$F35,5<=$G35),$D35,"") | P35: =IF(AND(6>=$F35,6<=$G35),$D35,"") | Q35: =IF(AND(7>=$F35,7<=$G35),$D35,"")
A36: 4.4 | B36: Governance: owners, cadence, partner roles | C36: Governance box on roadmap slide | D36: M1 | E36: M2 | F36: 5 | G36: 5 | H36: 1 | I36: 4.1 | J36: Not started | K36: =IF(AND(1>=$F36,1<=$G36),$D36,"") | L36: =IF(AND(2>=$F36,2<=$G36),$D36,"") | M36: =IF(AND(3>=$F36,3<=$G36),$D36,"") | N36: =IF(AND(4>=$F36,4<=$G36),$D36,"") | O36: =IF(AND(5>=$F36,5<=$G36),$D36,"") | P36: =IF(AND(6>=$F36,6<=$G36),$D36,"") | Q36: =IF(AND(7>=$F36,7<=$G36),$D36,"")
A37: 5 | B37: IMPACT & FINANCIALS (SQ4) | F37: 0 | G37: 0
A38: 5.1 | B38: Defend every yellow assumption with a source or reason | C38: No yellow cell without a note | D38: M3 | E38: M2 | F38: 3 | G38: 4 | H38: 4 | I38: 2.5 | J38: Not started | K38: =IF(AND(1>=$F38,1<=$G38),$D38,"") | L38: =IF(AND(2>=$F38,2<=$G38),$D38,"") | M38: =IF(AND(3>=$F38,3<=$G38),$D38,"") | N38: =IF(AND(4>=$F38,4<=$G38),$D38,"") | O38: =IF(AND(5>=$F38,5<=$G38),$D38,"") | P38: =IF(AND(6>=$F38,6<=$G38),$D38,"") | Q38: =IF(AND(7>=$F38,7<=$G38),$D38,"")
A39: 5.2 | B39: Update Model, scenarios, Dashboard | C39: Dashboard final; numbers frozen | D39: M3 | F39: 4 | G39: 4 | H39: 3 | I39: 5.1 | J39: Not started | K39: =IF(AND(1>=$F39,1<=$G39),$D39,"") | L39: =IF(AND(2>=$F39,2<=$G39),$D39,"") | M39: =IF(AND(3>=$F39,3<=$G39),$D39,"") | N39: =IF(AND(4>=$F39,4<=$G39),$D39,"") | O39: =IF(AND(5>=$F39,5<=$G39),$D39,"") | P39: =IF(AND(6>=$F39,6<=$G39),$D39,"") | Q39: =IF(AND(7>=$F39,7<=$G39),$D39,"")
A40: 5.3 | B40: Re-run run_tests.py with final assumptions | C40: Simulation tab refreshed | D40: M3 | F40: 5 | G40: 5 | H40: 2 | I40: 5.2 | J40: Not started | K40: =IF(AND(1>=$F40,1<=$G40),$D40,"") | L40: =IF(AND(2>=$F40,2<=$G40),$D40,"") | M40: =IF(AND(3>=$F40,3<=$G40),$D40,"") | N40: =IF(AND(4>=$F40,4<=$G40),$D40,"") | O40: =IF(AND(5>=$F40,5<=$G40),$D40,"") | P40: =IF(AND(6>=$F40,6<=$G40),$D40,"") | Q40: =IF(AND(7>=$F40,7<=$G40),$D40,"")
A41: 5.4 | B41: Finalize KPI tree (outcome + driver KPIs) | C41: KPI slide | D41: M3 | E41: M2 | F41: 5 | G41: 6 | H41: 2 | I41: 5.2 | J41: Not started | K41: =IF(AND(1>=$F41,1<=$G41),$D41,"") | L41: =IF(AND(2>=$F41,2<=$G41),$D41,"") | M41: =IF(AND(3>=$F41,3<=$G41),$D41,"") | N41: =IF(AND(4>=$F41,4<=$G41),$D41,"") | O41: =IF(AND(5>=$F41,5<=$G41),$D41,"") | P41: =IF(AND(6>=$F41,6<=$G41),$D41,"") | Q41: =IF(AND(7>=$F41,7<=$G41),$D41,"")
A42: 5.5 | B42: Non-financial impact: time, flexibility, capability | C42: Impact summary slide | D42: M3 | E42: M1 | F42: 5 | G42: 6 | H42: 2 | I42: 4.2 | J42: Not started | K42: =IF(AND(1>=$F42,1<=$G42),$D42,"") | L42: =IF(AND(2>=$F42,2<=$G42),$D42,"") | M42: =IF(AND(3>=$F42,3<=$G42),$D42,"") | N42: =IF(AND(4>=$F42,4<=$G42),$D42,"") | O42: =IF(AND(5>=$F42,5<=$G42),$D42,"") | P42: =IF(AND(6>=$F42,6<=$G42),$D42,"") | Q42: =IF(AND(7>=$F42,7<=$G42),$D42,"")
A43: 6 | B43: DECK & STORY | F43: 0 | G43: 0
A44: 6.1 | B44: Storyline skeleton with action titles | C44: Titles alone tell the story | D44: M1 | E44: All | F44: 3 | G44: 3 | H44: 2 | I44: 3.2 | J44: Not started | K44: =IF(AND(1>=$F44,1<=$G44),$D44,"") | L44: =IF(AND(2>=$F44,2<=$G44),$D44,"") | M44: =IF(AND(3>=$F44,3<=$G44),$D44,"") | N44: =IF(AND(4>=$F44,4<=$G44),$D44,"") | O44: =IF(AND(5>=$F44,5<=$G44),$D44,"") | P44: =IF(AND(6>=$F44,6<=$G44),$D44,"") | Q44: =IF(AND(7>=$F44,7<=$G44),$D44,"")
A45: 6.2 | B45: Slide template + visual system | C45: Master template shared | D45: M2 | F45: 2 | G45: 3 | H45: 2 | J45: Not started | K45: =IF(AND(1>=$F45,1<=$G45),$D45,"") | L45: =IF(AND(2>=$F45,2<=$G45),$D45,"") | M45: =IF(AND(3>=$F45,3<=$G45),$D45,"") | N45: =IF(AND(4>=$F45,4<=$G45),$D45,"") | O45: =IF(AND(5>=$F45,5<=$G45),$D45,"") | P45: =IF(AND(6>=$F45,6<=$G45),$D45,"") | Q45: =IF(AND(7>=$F45,7<=$G45),$D45,"")
A46: 6.3 | B46: SQ1 slides (situation, root cause, vision, gap) | C46: Draft slides | D46: M1 | E46: M2 | F46: 4 | G46: 5 | H46: 3 | I46: 2.3 | J46: Not started | K46: =IF(AND(1>=$F46,1<=$G46),$D46,"") | L46: =IF(AND(2>=$F46,2<=$G46),$D46,"") | M46: =IF(AND(3>=$F46,3<=$G46),$D46,"") | N46: =IF(AND(4>=$F46,4<=$G46),$D46,"") | O46: =IF(AND(5>=$F46,5<=$G46),$D46,"") | P46: =IF(AND(6>=$F46,6<=$G46),$D46,"") | Q46: =IF(AND(7>=$F46,7<=$G46),$D46,"")
A47: 6.4 | B47: SQ2 slides (idea, mechanism, day-in-the-life) | C47: Draft slides | D47: M2 | E47: M1 | F47: 5 | G47: 6 | H47: 4 | I47: 3.3 | J47: Not started | K47: =IF(AND(1>=$F47,1<=$G47),$D47,"") | L47: =IF(AND(2>=$F47,2<=$G47),$D47,"") | M47: =IF(AND(3>=$F47,3<=$G47),$D47,"") | N47: =IF(AND(4>=$F47,4<=$G47),$D47,"") | O47: =IF(AND(5>=$F47,5<=$G47),$D47,"") | P47: =IF(AND(6>=$F47,6<=$G47),$D47,"") | Q47: =IF(AND(7>=$F47,7<=$G47),$D47,"")
A48: 6.5 | B48: SQ3 slides (roadmap, capability, risks) | C48: Draft slides | D48: M2 | E48: M3 | F48: 5 | G48: 6 | H48: 3 | I48: 4.1 | J48: Not started | K48: =IF(AND(1>=$F48,1<=$G48),$D48,"") | L48: =IF(AND(2>=$F48,2<=$G48),$D48,"") | M48: =IF(AND(3>=$F48,3<=$G48),$D48,"") | N48: =IF(AND(4>=$F48,4<=$G48),$D48,"") | O48: =IF(AND(5>=$F48,5<=$G48),$D48,"") | P48: =IF(AND(6>=$F48,6<=$G48),$D48,"") | Q48: =IF(AND(7>=$F48,7<=$G48),$D48,"")
A49: 6.6 | B49: SQ4 slides (financials, simulation, KPIs) | C49: Draft slides | D49: M3 | F49: 5 | G49: 6 | H49: 3 | I49: 5.2 | J49: Not started | K49: =IF(AND(1>=$F49,1<=$G49),$D49,"") | L49: =IF(AND(2>=$F49,2<=$G49),$D49,"") | M49: =IF(AND(3>=$F49,3<=$G49),$D49,"") | N49: =IF(AND(4>=$F49,4<=$G49),$D49,"") | O49: =IF(AND(5>=$F49,5<=$G49),$D49,"") | P49: =IF(AND(6>=$F49,6<=$G49),$D49,"") | Q49: =IF(AND(7>=$F49,7<=$G49),$D49,"")
A50: 6.7 | B50: Executive summary | C50: 1 slide, readable in 30 seconds | D50: M1 | E50: All | F50: 6 | G50: 6 | H50: 2 | I50: 6.3 | J50: Not started | K50: =IF(AND(1>=$F50,1<=$G50),$D50,"") | L50: =IF(AND(2>=$F50,2<=$G50),$D50,"") | M50: =IF(AND(3>=$F50,3<=$G50),$D50,"") | N50: =IF(AND(4>=$F50,4<=$G50),$D50,"") | O50: =IF(AND(5>=$F50,5<=$G50),$D50,"") | P50: =IF(AND(6>=$F50,6<=$G50),$D50,"") | Q50: =IF(AND(7>=$F50,7<=$G50),$D50,"")
A51: 6.8 | B51: Appendix: assumptions, simulation, alternatives, sources | C51: Appendix complete, same style | D51: M3 | E51: M2 | F51: 6 | G51: 6 | H51: 2 | I51: 5.3 | J51: Not started | K51: =IF(AND(1>=$F51,1<=$G51),$D51,"") | L51: =IF(AND(2>=$F51,2<=$G51),$D51,"") | M51: =IF(AND(3>=$F51,3<=$G51),$D51,"") | N51: =IF(AND(4>=$F51,4<=$G51),$D51,"") | O51: =IF(AND(5>=$F51,5<=$G51),$D51,"") | P51: =IF(AND(6>=$F51,6<=$G51),$D51,"") | Q51: =IF(AND(7>=$F51,7<=$G51),$D51,"")
A52: 6.9 | B52: Design polish + consistency pass | C52: One font, one color system, aligned charts | D52: M2 | F52: 6 | G52: 7 | H52: 3 | I52: 6.7 | J52: Not started | K52: =IF(AND(1>=$F52,1<=$G52),$D52,"") | L52: =IF(AND(2>=$F52,2<=$G52),$D52,"") | M52: =IF(AND(3>=$F52,3<=$G52),$D52,"") | N52: =IF(AND(4>=$F52,4<=$G52),$D52,"") | O52: =IF(AND(5>=$F52,5<=$G52),$D52,"") | P52: =IF(AND(6>=$F52,6<=$G52),$D52,"") | Q52: =IF(AND(7>=$F52,7<=$G52),$D52,"")
A53: 7 | B53: QUALITY & PRESENTATION | F53: 0 | G53: 0
A54: 7.1 | B54: Red-team review: each member attacks another's section | C54: Comment list closed | D54: M1 | E54: All | F54: 5 | G54: 6 | H54: 2 | I54: 6.3 | J54: Not started | K54: =IF(AND(1>=$F54,1<=$G54),$D54,"") | L54: =IF(AND(2>=$F54,2<=$G54),$D54,"") | M54: =IF(AND(3>=$F54,3<=$G54),$D54,"") | N54: =IF(AND(4>=$F54,4<=$G54),$D54,"") | O54: =IF(AND(5>=$F54,5<=$G54),$D54,"") | P54: =IF(AND(6>=$F54,6<=$G54),$D54,"") | Q54: =IF(AND(7>=$F54,7<=$G54),$D54,"")
A55: 7.2 | B55: Number tie-out: every number traced to tab/exhibit | C55: Checklist signed off | D55: M3 | E55: M1 | F55: 6 | G55: 7 | H55: 2 | I55: 6.8 | J55: Not started | K55: =IF(AND(1>=$F55,1<=$G55),$D55,"") | L55: =IF(AND(2>=$F55,2<=$G55),$D55,"") | M55: =IF(AND(3>=$F55,3<=$G55),$D55,"") | N55: =IF(AND(4>=$F55,4<=$G55),$D55,"") | O55: =IF(AND(5>=$F55,5<=$G55),$D55,"") | P55: =IF(AND(6>=$F55,6<=$G55),$D55,"") | Q55: =IF(AND(7>=$F55,7<=$G55),$D55,"")
A56: 7.3 | B56: Q&A bank: answers + owner per question (QA_Bank tab) | C56: Every question has an owner + data point | D56: M3 | E56: All | F56: 7 | G56: 7 | H56: 2 | I56: 7.1 | J56: Not started | K56: =IF(AND(1>=$F56,1<=$G56),$D56,"") | L56: =IF(AND(2>=$F56,2<=$G56),$D56,"") | M56: =IF(AND(3>=$F56,3<=$G56),$D56,"") | N56: =IF(AND(4>=$F56,4<=$G56),$D56,"") | O56: =IF(AND(5>=$F56,5<=$G56),$D56,"") | P56: =IF(AND(6>=$F56,6<=$G56),$D56,"") | Q56: =IF(AND(7>=$F56,7<=$G56),$D56,"")
A57: 7.4 | B57: Speaker split + script (see split below) | C57: Each speaker has a 1-page script and handover lines | D57: M1 | E57: All | F57: 6 | G57: 6 | H57: 2 | I57: 6.7 | J57: Not started | K57: =IF(AND(1>=$F57,1<=$G57),$D57,"") | L57: =IF(AND(2>=$F57,2<=$G57),$D57,"") | M57: =IF(AND(3>=$F57,3<=$G57),$D57,"") | N57: =IF(AND(4>=$F57,4<=$G57),$D57,"") | O57: =IF(AND(5>=$F57,5<=$G57),$D57,"") | P57: =IF(AND(6>=$F57,6<=$G57),$D57,"") | Q57: =IF(AND(7>=$F57,7<=$G57),$D57,"")
A58: 7.5 | B58: Two timed mock presentations + Q&A drill | C58: Within time limit, smooth handovers | D58: M1 | E58: All | F58: 7 | G58: 7 | H58: 3 | I58: 7.4 | J58: Not started | K58: =IF(AND(1>=$F58,1<=$G58),$D58,"") | L58: =IF(AND(2>=$F58,2<=$G58),$D58,"") | M58: =IF(AND(3>=$F58,3<=$G58),$D58,"") | N58: =IF(AND(4>=$F58,4<=$G58),$D58,"") | O58: =IF(AND(5>=$F58,5<=$G58),$D58,"") | P58: =IF(AND(6>=$F58,6<=$G58),$D58,"") | Q58: =IF(AND(7>=$F58,7<=$G58),$D58,"")
A59: 7.6 | B59: Final proofread, export, submit early | C59: Submitted before deadline | D59: M1 | E59: M2 | F59: 7 | G59: 7 | H59: 1 | I59: 7.5 | J59: Not started | K59: =IF(AND(1>=$F59,1<=$G59),$D59,"") | L59: =IF(AND(2>=$F59,2<=$G59),$D59,"") | M59: =IF(AND(3>=$F59,3<=$G59),$D59,"") | N59: =IF(AND(4>=$F59,4<=$G59),$D59,"") | O59: =IF(AND(5>=$F59,5<=$G59),$D59,"") | P59: =IF(AND(6>=$F59,6<=$G59),$D59,"") | Q59: =IF(AND(7>=$F59,7<=$G59),$D59,"")
A61: Daily checkpoints (end of day)
B62: D1: exhibits clean, issue tree agreed, rules confirmed
B63: D2: gap heat map, root cause, vision draft, benchmarks started
B64: D3: idea + pilot area LOCKED, system diagram, storyline skeleton
B65: D4: day-in-the-life, mechanism, model updated, roadmap draft
B66: D5: full draft deck, simulation re-run, red-team started
B67: D6: exec summary, appendix, speaker script, design pass
B68: D7: numbers tied out, Q&A drilled, two mocks, submit early
A70: Speaker split (adjust % to the official time limit)
B71: Section | C71: Speaker | D71: Share of time
B72: Opening, situation, root cause, 2030 vision (SQ1) | C72: M1 | D72: 0.25
B73: The idea, how it works, day in the life, mindset & knowledge (SQ2) | C73: M2 | D73: 0.3
B74: Roadmap, capability, risks (SQ3) | C74: M2 | D74: 0.1
B75: Financial impact, simulation proof, KPIs (SQ4) | C75: M3 | D75: 0.25
B76: Close and the decision we ask TMMIN to take | C76: M1 | D76: 0.1
B77: Check (must be 100%) | D77: =SUM(D72:D76)
B78: Q&A rule: the owner of the slide answers first; the lead routes questions and closes. Never two people talking at once.

Sheet Answer_Guide
A1: How to answer each sub-question
A3: Section | B3: What judges look for | C3: How to answer (steps) | D3: Data to use | E3: Model tab | F3: Traps to avoid
A4: Executive summary (1 slide) | B4: One clear answer in 30 seconds: the idea, why now, impact, investment, ask. | C4: Write it LAST but draft it on Day 3. Situation (cost index 106 vs 89, multi-pathway coming) -> Complication (open loops in quality, data, knowledge) -> Answer (your one system) -> Impact (NPV, index, months) -> Roadmap headline. | D4: Exhibit 3, Dashboard | E4: Dashboard | F4: Listing 5 ideas; burying the number; no single name for the idea.
A5: SQ1. Future manufacturing vision & biggest gaps | B5: A vivid 2030 picture that goes BEYOND lower cost, and a prioritized, evidence-based gap. | C5: 1) Write a 2030 vision statement (people + technology + flexibility). 2) Define 'new value' beyond cost: speed to launch variants, knowledge that compounds, engaged people. 3) Build a gap heat map: process (Exhibit 5) x impact on cost & quality (Exhibit 4). 4) Show the gap is BETWEEN processes (integration, data, feedback). 5) Pick 1-2 priority gaps. | D5: Exhibits 3, 4, 5, 8 | E5: Exhibits | F5: Vision that is just a list of technologies; ignoring that the case says the gap lies between processes.
A6: SQ2. Transformative idea | B6: How manufacturing itself changes; people stay at the center; mindset shift; know-how becomes shared knowledge. | C6: 1) Name the idea and show ONE system diagram. 2) Walk through a 'day in the life' of an operator and an engineer before vs after. 3) Explain the mindset shift (operate & maintain -> improve & transform) and the mechanism that drives it (time freed, idea channel, recognition). 4) Show how know-how is captured, validated, reused. 5) Explain in-house vs partner logic. 6) Anchor every element in a TPS principle. | D6: Exhibits 6A, 6B, 7; Ideation tab | E6: Ideation | F6: Recommending a product/device; AI replacing people; no answer to the 31% who override alerts.
A7: SQ3. Roadmap & capability building | B7: Credible phasing 2026-2030 with pilot, standardization, rollout, talent, partners, risks. | C7: 1) Phase 0 (Q4 2026): build on AI camera validation; choose pilot area; set data standard. 2) Pilot (2027) with go/no-go KPIs. 3) Standardize (2028). 4) Roll out (2029-30). 5) Talent: tiered academy moving engineers up Exhibit 7 levels, operator data training. 6) Partners only where they add distinctive value. 7) Risk register with mitigations. | D7: Exhibits 5, 6A, 7; Roadmap tab | E7: Roadmap, KPIs | F7: Everything starting in year 1; no gate criteria; no owner; ignoring training (18% trained).
A8: SQ4. Competitive & financial impact | B8: Impact on cost, quality, time, flexibility, capability; investment; KPIs. Numbers must be traceable. | C8: 1) Bottom-up savings by lever (Model tab). 2) Investment inside Rp40-120B. 3) NPV at 10%, payback, IRR, 3 scenarios. 4) Break-even framing (Breakeven tab). 5) Translate to cost index vs benchmark. 6) Non-financial impact: months per variant, ramp-up time, ideas, skills. 7) KPI tree with baselines and targets. | D8: Exhibit 9, 3, 4; Model, Dashboard, Breakeven, KPIs | E8: Model, Dashboard | F8: Claiming 100% of the gap; ignoring running and training cost; no sensitivity; unlabeled assumptions.
A9: Q&A preparation | B9: Calm, data-backed answers; shows the team owns the logic. | C9: Prepare answers for: Why this pilot area? What if operators resist? Why in-house, not buy? What if the AI camera fails validation? How do you avoid job losses? What happens in the aggressive BEV scenario? Which assumption hurts NPV most? How does this differ from what Toyota Japan already does? | D9: All | E9: Breakeven (sensitivity) | F9: One person answering everything; arguing with judges.
A12: Suggested deck storyline (fill [ ] with your numbers; titles must read as a story on their own)
A13: # | B13: Slide | C13: Example action title / content | D13: Owner
A14: 1 | B14: Title | C14: Idea name + one-line promise | D14: M1
A15: 2 | B15: Executive summary | C15: TMMIN can close [x]% of its cost gap and cut variant changeover from 9 to [x] months by making the plant learn from itself | D15: M1
A16: 3 | B16: Situation | C16: Market fell 7% while new players run [~19]% cheaper per unit | D16: M1
A17: 4 | B17: Complication | C17: Multi-pathway mix lifts electrified share to [55-70]% by 2030, but every variant still costs ~9 months of rework | D17: M1
A18: 5 | B18: Root cause | C18: The real gap sits between processes: quality, data and know-how loops are open | D18: M2
A19: 6 | B19: 2030 vision (SQ1) | C19: In 2030 TMMIN's advantage is a production system that learns, not one that is bought | D19: M1
A20: 7 | B20: Gap prioritization (SQ1) | C20: [Pilot area] is where the open loops cost the most | D20: M2
A21: 8 | B21: The idea (SQ2) | C21: [Idea name]: three closed loops with people at the center | D21: M2
A22: 9 | B22: How it works (SQ2) | C22: A day in the life: operator and engineer before vs after | D22: M2
A23: 10 | B23: Mindset & knowledge (SQ2) | C23: Engineers move from firefighting to improving, and know-how leaves the heads of a few experts | D23: M1
A24: 11 | B24: In-house vs partners (SQ2/3) | C24: Build what differentiates, partner where partners add distinctive value | D24: M2
... A31: App. | B31: Appendix | C31: Assumptions list, sensitivity, alternatives considered (Ideation), exhibit re-type, methodology | D31: M3

Sheet Ideation
A1: Idea options: generate, compare, then combine into ONE system
A2: Case rule: the answer must change HOW manufacturing works (process, ways of working, people, knowledge), not recommend a product or machine.
A4: # | B4: Idea | C4: How manufacturing changes | D4: Case gaps it closes | E4: TPS anchor | F4: Public Toyota precedent | G4: Strength | H4: Risk / weakness | I4: References & evidence (cite in deck)
A5: A | B5: Closed-Loop Jidoka ("Self-Healing Line") | C5: Every abnormality detected anywhere (AI inspection, sensors, operator) is routed automatically to the upstream process that caused it, with a clear stop / correct / escalate rule. Operators confirm and fix; the line learns. | D5: Inspection L1, sealer with no feedback, defects found late, scrap up, 31% override alerts | E5: Jidoka, andon, built-in quality | F5: Toyota Japan uses worker-built AI models for adhesive-application inspection | G5: Strong cost + quality story; uses the Oct 2026 AI camera as a building block | H5: Needs data integration first; alert fatigue if poorly designed | I5: Google Cloud (2024) Toyota AI Platform: https://cloud.google.com/blog/topics/hybrid-cloud/toyota-ai-platform-manufacturing-efficiency DigitalDefynd (2026) 10 ways Toyota uses AI: https://digitaldefynd.com/IQ/toyota-using-ai-case-study/ The Future Factory (2026) TPS in the age of AI: https://www.thefuturefactory.com/insights/toyota-production-system-age-of-ai Own test: Simulation tab (closed-loop quality sim + Monte Carlo)
A6: B | B6: Plug-and-Produce Plant Standard (in-house) | C6: TMMIN defines one common interface + data standard; every new or modified equipment plugs into it. In-house engineers build standard equipment and apps on top. Variant change becomes configuration, not rewiring. | D6: Point-to-point integration, 9-month modification, scattered data, costly closed external tech | E6: Standardized work applied to equipment; heijunka for mixed models | F6: Toyota insources equipment tech (self-propelled conveyance at Motomachi) | G6: Direct answer to multi-pathway flexibility and in-house capability | H6: Less emotional / people story on its own; standard-setting takes discipline | I6: Toyota (2023) Monozukuri tech, in-house self-propelled conveyance: https://global.toyota/en/newsroom/corporate/39758451.html Toyota (2023) BEV production process, halve prep lead time & investment: https://global.toyota/en/newsroom/corporate/39330500.html Case: point-to-point integration, 9-month modification (Exhibits 4, 5)
A7: C | B7: Citizen Kaizen AI Platform | C7: Team leaders and operators build simple AI / data tools themselves through a no-code platform, plus an easy idea channel with fast engineer support. Engineers become coaches and platform owners. | D7: Ideas down 3.1->2.4, implementation 35%->28%, 62% would contribute with an easy channel, 18% trained | E7: Kaizen, respect for people | F7: Toyota AI Platform: ~10,000 models built by factory staff, ~1,200 active users | G7: Most human-centered; scales kaizen; very Toyota | H7: Needs governance (model quality, safety); training load | I7: Google Cloud (2024) Toyota AI Platform: https://cloud.google.com/blog/topics/hybrid-cloud/toyota-ai-platform-manufacturing-efficiency Chief AI Officer (2025) 10,000 models / 10,000 hrs: https://chiefaiofficer.com/blog/how-toyota-gave-ai-tools-to-factory-workers-and-saved-10000-hours/ Case Exhibit 6B: 62% would contribute ideas with an easy channel
A8: D | B8: Shop-Floor O-Beya ("Digital Sensei") | C8: Capture senior experts' troubleshooting and process know-how into shared standards and an AI assistant that new engineers and team leaders consult. Experts validate content; it becomes living standard work. | D8: Know-how with 1-2 seniors, low documentation, 15-month ramp-up, engineers stuck firefighting | E8: Yokoten (horizontal deployment), standardized work, hansei | F8: Toyota O-Beya: 9 AI agents for ~800 powertrain engineers | G8: Cheap, fast to pilot, addresses knowledge and talent directly | H8: Weaker direct cost impact; content quality depends on seniors' time | I8: Microsoft Source Asia (2024) O-Beya: https://news.microsoft.com/source/asia/features/toyota-is-deploying-ai-agents-to-harness-the-collective-wisdom-of-engineers-and-innovate-faster/ ABI Research (2025) O-Beya knowledge mgmt: https://www.abiresearch.com/market-research/insight/7786905-toyotas-o-beya-provides-best-practices-for Aicadium (2026) Lean to AI, GAIA + 100-course academy: https://aicadium.ai/lean-to-ai-what-toyotas-transformation-looks-like-today/ Case Exhibit 6A: know-how with 1-2 seniors, 15-month ramp-up
A9: E | B9: Simulation-First Production Preparation | C9: Every new variant / pathway is designed, balanced and debugged in a digital model of the line before physical change. Engineers own the models. | D9: 9-month modification, multi-pathway mix uncertainty (Exhibit 8) | E9: Genchi genbutsu supported by virtual verification; PDCA | F9: Toyota digital process verification for next-gen BEV plants (aim: halve prep lead time) | G9: Strong flexibility + time-to-market story; fits IE skills | H9: Needs reliable data; model upkeep cost | I9: Toyota (2023) BEV production process, halve prep lead time & investment: https://global.toyota/en/newsroom/corporate/39330500.html Case Exhibit 8: electrified share 30% -> 55-70%
A10: F | B10: Conveyor-Light Flexible Line + Synchronized Intralogistics | C10: Redesign flow around mobile automation (AMR/AGV, self-propelled concepts) so layout and sequence adapt to the variant mix; material flow synced with production signals. | D10: Manual forklifts/dollies, flow not synchronized, NVA 22% | E10: JIT, kanban, heijunka | F10: Toyota self-propelled assembly line trials | G10: Big flexibility upside, visually impressive | H10: Capex heavy, risks reading as equipment recommendation | I10: Assembly Magazine (2023) self-propelled lines: https://www.assemblymag.com/articles/98199-toyota-outlines-future-production-processes Toyota (2023) Monozukuri tech, in-house self-propelled conveyance: https://global.toyota/en/newsroom/corporate/39758451.html
A11: G | B11: AI-Enabled Autonomous Maintenance (TPM 2.0) | C11: Operators and maintenance jointly own equipment health using condition data; predictive alerts with operator-led first response. | D11: Periodic preventive only, rising unplanned downtime | E11: TPM, jidoka | F11: Toyota AI Platform used for injection-moulding abnormality detection | G11: Clear downtime savings, practical | H11: Narrower scope; many competitors will propose it | I11: Google Cloud (2024) Toyota AI Platform: https://cloud.google.com/blog/topics/hybrid-cloud/toyota-ai-platform-manufacturing-efficiency Logistics Viewpoints (2025) People + AI: https://logisticsviewpoints.com/2025/06/05/people-ai-augmenting-the-supply-chain-workforce/
A12: H | B12: INTEGRATED: Closed-Loop Production System (A+B+C+D) | C12: One operating system with three loops: quality loop (A), data/equipment loop (B), people & knowledge loop (C+D). Piloted in one area, standardized, then rolled out plant-wide. | D12: Attacks all three complications at once | E12: Jidoka + kaizen + standardization, in the digital era | F12: Combines the Toyota precedents above | G12: Best answer to 'system not product'; one memorable idea | H12: Complex to explain: needs one clean diagram and one pilot | I12: Google Cloud (2024) Toyota AI Platform: https://cloud.google.com/blog/topics/hybrid-cloud/toyota-ai-platform-manufacturing-efficiency Microsoft Source Asia (2024) O-Beya: https://news.microsoft.com/source/asia/features/toyota-is-deploying-ai-agents-to-harness-the-collective-wisdom-of-engineers-and-innovate-faster/ Toyota (2023) Monozukuri tech, in-house self-propelled conveyance: https://global.toyota/en/newsroom/corporate/39758451.html Aicadium (2026) Lean to AI, GAIA + 100-course academy: https://aicadium.ai/lean-to-ai-what-toyotas-transformation-looks-like-today/ Own test: Simulation tab (closed-loop quality sim + Monte Carlo)
A15: Scoring matrix (scores 1-5 are suggestions: re-score as a team on Day 3)
A16: # | B16: Idea | C16: Cost & quality impact | D16: Multi-pathway flexibility | E16: People at the center / knowledge | F16: Hard to buy off the shelf (in-house value) | G16: Feasible in Rp40-120B by 2030 | H16: Fits case ask: system, not product | I16: Weighted score | J16: Rank
B17: Weight | C17: 0.25 | D17: 0.15 | E17: 0.2 | F17: 0.15 | G17: 0.15 | H17: 0.1 | I17: =SUM(C17:H17)
A18: A | B18: Closed-Loop Jidoka ("Self-Healing Line") | C18: 5 | D18: 3 | E18: 4 | F18: 4 | G18: 4 | H18: 5 | I18: =SUMPRODUCT($C$17:$H$17,C18:H18) | J18: =RANK(I18,$I$18:$I$25)
A19: B | B19: Plug-and-Produce Plant Standard (in-house) | C19: 3 | D19: 5 | E19: 3 | F19: 5 | G19: 3 | H19: 5 | I19: =SUMPRODUCT($C$17:$H$17,C19:H19) | J19: =RANK(I19,$I$18:$I$25)
A20: C | B20: Citizen Kaizen AI Platform | C20: 4 | D20: 3 | E20: 5 | F20: 5 | G20: 4 | H20: 4 | I20: =SUMPRODUCT($C$17:$H$17,C20:H20) | J20: =RANK(I20,$I$18:$I$25)
A21: D | B21: Shop-Floor O-Beya ("Digital Sensei") | C21: 2 | D21: 3 | E21: 5 | F21: 4 | G21: 5 | H21: 4 | I21: =SUMPRODUCT($C$17:$H$17,C21:H21) | J21: =RANK(I21,$I$18:$I$25)
A22: E | B22: Simulation-First Production Preparation | C22: 3 | D22: 5 | E22: 3 | F22: 4 | G22: 4 | H22: 4 | I22: =SUMPRODUCT($C$17:$H$17,C22:H22) | J22: =RANK(I22,$I$18:$I$25)
A23: F | B23: Conveyor-Light Flexible Line + Synchronized Intralogistics | C23: 3 | D23: 5 | E23: 2 | F23: 2 | G23: 2 | H23: 2 | I23: =SUMPRODUCT($C$17:$H$17,C23:H23) | J23: =RANK(I23,$I$18:$I$25)
A24: G | B24: AI-Enabled Autonomous Maintenance (TPM 2.0) | C24: 4 | D24: 2 | E24: 4 | F24: 3 | G24: 4 | H24: 3 | I24: =SUMPRODUCT($C$17:$H$17,C24:H24) | J24: =RANK(I24,$I$18:$I$25)
A25: H | B25: INTEGRATED: Closed-Loop Production System (A+B+C+D) | C25: 5 | D25: 4 | E25: 5 | F25: 5 | G25: 3 | H25: 5 | I25: =SUMPRODUCT($C$17:$H$17,C25:H25) | J25: =RANK(I25,$I$18:$I$25)
A27: Tip: the winning pitch is usually one integrated idea (like H) explained through one pilot. Use the lower-ranked options as 'considered and rejected' in the appendix to show rigor.

Sheet Simulation9
A1: Idea tests: simulation results (values produced by run_tests.py, not formulas)
A2: Re-run run_tests.py after changing assumptions. Process parameters below are illustrative assumptions, not TMMIN data: present them as a mechanism test, and show the sensitivity.
A4: TEST 1. Does closing the quality loop beat adding technology alone? (sealer drift -> inspection -> feedback, 1 year, 175,000 units, 300 runs)
A5: Scenario | B5: Defective units / yr | C5: Scrapped units / yr | D5: Escaped defects / yr | E5: Units built while drifting | F5: Scrap vs today | G5: Escapes vs today | H5: Scrap P5-P95
A6: 1. Today: visual at final inspection, manual feedback | B6: 4266.68 | C6: 1088.524 | D6: 638.26667 | E6: 15796.093 | F6: 0 | G6: 0 | H6: 835 - 1,365
A7: 2. Better camera at end-of-line only (tech, no loop) | B7: 4265.3233 | C7: 1215.776 | D7: 212.73667 | E7: 15793.257 | F7: 0.11690326 | G7: -0.66669626 | H7: 910 - 1,492
A8: 3. Closed loop at sealer, 31% of alerts dismissed (as today) | B8: 1652.95 | C8: 362.15367 | D8: 203.26 | E8: 5247.72 | F8: -0.66729841 | G8: -0.68154376 | H8: 216 - 543
A9: 4. Closed loop with people-centred design (10% dismissed) | B9: 908.32333 | C9: 166.86333 | D9: 88.006667 | E9: 2257.0067 | F9: -0.84670679 | G9: -0.86211615 | H9: 83 - 270
A11: What this shows
A12: - A better camera at end-of-line alone changes scrap by +12% while escapes fall 67%: it catches more bad units, but too late, so escapes turn into scrap. It does not prevent defects.
A13: - Closing the loop right after the sealer cuts scrap 85% and escapes 86%, because a drift is stopped within a few units instead of hundreds.
A14: - If operators dismiss alerts in 31% of drift episodes (today's override rate), scrap reduction falls to 67%. Trust, training and alert design are part of the value, not an add-on.
A15: - Plant-wide: if the pilot scope causes 40% of plant scrap (team assumption), the plant-wide scrap cut is about 34%. Compare with the 20% / 35% / 50% lever in Assumptions.
A16: - Deck message: value comes from redesigning the system (where the check sits, how fast the signal travels, who acts on it), not from buying the device. That is exactly the case ask.
A18: Process assumptions used (illustrative, change and re-run)
A19: Defect probability per unit, stable sealer | B19: 0.002
A20: Average units between drift events | B20: 5000
A21: Defect probability per unit while drifting | B21: 0.25
A22: Manual visual detection rate at final inspection | B22: 0.85
A23: Share of sealer defect modes the in-line AI camera can see | B23: 0.7
A24: Units between sealer and today's final inspection | B24: 300
A25: Units built before manual feedback reaches the sealer | B25: 150
A26: Share of late-found defects scrapped | B26: 0.3
A27: Share of early-found defects scrapped | B27: 0.05
A28: Share of plant scrap from the pilot scope (team assumption) | B28: 0.4
A29: In-line check: 5 units after sealer, automatic feedback within 10 units, 90% detection on visible defect modes (case: AI camera in validation to Oct 2026).
A31: Robustness: closed-loop (scenario 4) scrap reduction vs today when each assumption changes
A32: Assumption | B32: Low | C32: Reduction | D32: Base | E32: Reduction | F32: High | G32: Reduction
A33: AI camera coverage of defect modes | B33: 0.5 | C33: 0.8247043 | D33: 0.7 | E33: 0.84684226 | F33: 0.9 | G33: 0.86670882
A34: Drift defect rate | B34: 0.1 | C34: 0.8026018 | D34: 0.25 | E34: 0.84799063 | F34: 0.4 | G34: 0.86492434
A35: Units between drift events | B35: 2500 | C35: 0.86340745 | D35: 5000 | E35: 0.85825104 | F35: 10000 | G35: 0.83368165
A36: Late-found scrap share | B36: 0.15 | C36: 0.83146269 | D36: 0.3 | E36: 0.85387796 | F36: 0.5 | G36: 0.85017711
A37: Units from sealer to today's inspection | B37: 100 | C37: 0.81112305 | D37: 300 | E37: 0.8492534 | F37: 600 | G37: 0.87379761
A38: Lowest scrap reduction across all tested cases: 80%. The mechanism holds even with pessimistic process assumptions.
A40: People test: how much value is lost when operators dismiss alerts?
A41: Share of drift episodes where alerts are dismissed | B41: Scrap reduction vs today
A42: 0 | B42: 0.93929302
A43: 0.1 | B43: 0.84457608
A44: 0.2 | B44: 0.7497195
A45: 0.31 | B45: 0.64310602
A46: 0.5 | B46: 0.49641257
A47: Exhibit 6B says 31% of operators frequently override alerts today. This chart is the quantified case for the people part of the idea.
A49: TEST 2. Is the business case robust? Financial Monte Carlo (10,000 runs, mirrors the Model tab incl. pilot-light phasing)
A50: Metric | B50: Value | C50: Note
A51: Deterministic base NPV (check vs Model tab) | B51: 27.014039 | C51: Should match Dashboard base NPV
A52: Mean NPV | B52: 11.823608 | C52: Rp billion
A53: P5 NPV (bad case) | B53: -19.41291 | C53: 1-in-20 downside
A54: Median NPV | B54: 11.708447
A55: P95 NPV (good case) | B55: 43.103322
A56: Probability NPV > 0 | B56: 0.7311 | C56: Headline for the financial slide
A57: Median full run-rate savings (Rp B/yr) | B57: 49.084413
A58: Median run-rate as % of conversion cost | B58: 0.087650737 | C58: vs 16% gap to benchmark
A60: TEST 2b. How should the roadmap spend the money? Same 10,000 runs, five strategies (gate = stop scaling if 2027 pilot adoption < 80%; happens in 25% of runs)
A61: Strategy | B61: Mean NPV | C61: P5 NPV | D61: Median NPV | E61: P95 NPV | F61: P(NPV > 0)
A62: A. Front-loaded phasing, no gate | B62: -0.19133229 | C62: -32.832551 | D62: -0.37372173 | E62: 32.504416 | F62: 0.4925
A63: B. Front-loaded phasing + gate (65% already spent) | B63: -3.7996789 | C63: -39.745907 | D63: -2.96235 | E63: 32.401945 | F63: 0.4518
A64: C. Pilot-light phasing, no gate (as in Model tab) | B64: 11.823608 | C64: -19.41291 | D64: 11.708447 | E64: 43.103322 | F64: 0.7311
A65: D. Pilot-light phasing + gate | B65: 15.0509 | C65: -8.4116268 | D65: 13.320402 | E65: 43.067723 | F65: 0.8595
A66: E. D + remaining equipment life valued at book | B66: 36.010535 | C66: 6.4767775 | D66: 36.960852 | E66: 67.48369 | F66: 0.9938
A67: F. D but savings ramp one year slower (stress test) | B67: -7.5342336 | C67: -31.899408 | D67: -5.5425073 | E67: 12.325501 | F67: 0.3242
A68: G. F + remaining equipment life valued at book | B68: 13.425401 | C68: -3.7787791 | D68: 11.927164 | E68: 35.124142 | F68: 0.879
A69: Pilot-light phasing: 10% / 15% / 40% / 25% / 10% of capex in 2026-2030. Ramp-up kept the same to isolate the effect of phasing; if scaling later also delays savings, the gain is smaller.
A70: Reading: a gate only protects value if little money is spent before it. Gate after heavy spending (B) destroys value; pilot-light + gate (D) is the design to defend in SQ3. Valuing equipment life beyond 2030 (E) is legitimate but state it openly. Stress test (F): if savings arrive a year late, P(NPV>0) falls to 32% (88% if remaining equipment life is valued, G). Speed of the pilot is the make-or-break factor: quick wins in 2026-27 belong in the roadmap.
A71: Ranges used (triangular low / mode / high): scrap 20/35/50%, maintenance 5/10/15%, NVA 15/30/45%, energy 2/5/8%, variant cost 20/35/50%, investment 60/80/110, running 8/9/12%, training 2/2.5/3, variant projects 2/3/5, cost per project 5/10/15, cash realization 30/50/70%, adoption 60/100/100%, labor share 35/40/45%.
A73: NPV distribution (histogram)
A74: NPV bin from (Rp B) | B74: Runs
A75: -51.6 | B75: 11
A76: -41.6 | B76: 73
A77: -31.5 | B77: 294
A78: -21.5 | B78: 700
A79: -11.5 | B79: 1367
A80: -1.4 | B80: 1920
A81: 8.6 | B81: 2028
A82: 18.6 | B82: 1753
A83: 28.6 | B83: 1056
A84: 38.7 | B84: 560
A85: 48.7 | B85: 182
A86: 58.7 | B86: 43
... A90: 98.9 | B90: 1
A92: TEST 3. Which assumption matters most? Tornado (base case, one at a time)
A93: Driver | B93: Low input | C93: High input | D93: NPV at low | E93: NPV at high | F93: Swing
A94: Investment (Rp B) | B94: 110 | C94: 60 | D94: -1.4979109 | E94: 46.022005 | F94: 47.519916
A95: Adoption achieved | B95: 0.6 | C95: 1 | D95: -17.99511 | E95: 27.014039 | F95: 45.009149
A96: Scrap reduction | B96: 0.2 | C96: 0.5 | D96: 7.3765393 | E96: 46.651538 | F96: 39.274999
A97: Variant projects / yr | B97: 2 | C97: 5 | D97: 18.831747 | E97: 43.378622 | F97: 24.546874
A98: Cost per variant project | B98: 5 | C98: 15 | D98: 14.740602 | E98: 39.287476 | F98: 24.546874
A99: Variant cost reduction | B99: 0.2 | C99: 0.5 | D99: 16.49395 | E99: 37.534128 | F99: 21.040178
A100: Operator NVA eliminated | B100: 0.15 | C100: 0.45 | D100: 18.373539 | E100: 35.654538 | F100: 17.280999
A101: Maintenance reduction | B101: 0.05 | C101: 0.15 | D101: 18.504456 | E101: 35.523622 | F101: 17.019166
A102: Energy reduction | B102: 0.02 | C102: 0.08 | D102: 22.301039 | E102: 31.727039 | F102: 9.4259997
A103: Running cost % | B103: 0.12 | C103: 0.08 | D103: 23.779625 | E103: 30.248453 | F103: 6.4688279
A104: Use the top 2-3 drivers as the assumptions you defend hardest in Q&A, and as the KPIs you track first in the pilot.

Sheet Simulation8
A1: Idea tests: simulation results (values produced by run_tests.py, not formulas)
A2: Re-run run_tests.py after changing assumptions. Process parameters below are illustrative assumptions, not TMMIN data: present them as a mechanism test, and show the sensitivity.
A4: TEST 1. Does closing the quality loop beat adding technology alone? (sealer drift -> inspection -> feedback, 1 year, 175,000 units, 300 runs)
A5: Scenario | B5: Defective units / yr | C5: Scrapped units / yr | D5: Escaped defects / yr | E5: Units built while drifting | F5: Scrap vs today | G5: Escapes vs today | H5: Scrap P5-P95
A6: 1. Today: visual at final inspection, manual feedback | B6: 4266.68 | C6: 1088.524 | D6: 638.26667 | E6: 15796.093 | F6: 0 | G6: 0 | H6: 835 - 1,365
A7: 2. Better camera at end-of-line only (tech, no loop) | B7: 4265.3233 | C7: 1215.776 | D7: 212.73667 | E7: 15793.257 | F7: 0.11690326 | G7: -0.66669626 | H7: 910 - 1,492
A8: 3. Closed loop at sealer, 31% of alerts dismissed (as today) | B8: 1652.95 | C8: 362.15367 | D8: 203.26 | E8: 5247.72 | F8: -0.66729841 | G8: -0.68154376 | H8: 216 - 543
A9: 4. Closed loop with people-centred design (10% dismissed) | B9: 908.32333 | C9: 166.86333 | D9: 88.006667 | E9: 2257.0067 | F9: -0.84670679 | G9: -0.86211615 | H9: 83 - 270
A11: What this shows
A12: - A better camera at end-of-line alone changes scrap by +12% while escapes fall 67%: it catches more bad units, but too late, so escapes turn into scrap. It does not prevent defects.
A13: - Closing the loop right after the sealer cuts scrap 85% and escapes 86%, because a drift is stopped within a few units instead of hundreds.
A14: - If operators dismiss alerts in 31% of drift episodes (today's override rate), scrap reduction falls to 67%. Trust, training and alert design are part of the value, not an add-on.
A15: - Plant-wide: if the pilot scope causes 40% of plant scrap (team assumption), the plant-wide scrap cut is about 34%. Compare with the 20% / 35% / 50% lever in Assumptions.
A16: - Deck message: value comes from redesigning the system (where the check sits, how fast the signal travels, who acts on it), not from buying the device. That is exactly the case ask.
A18: Process assumptions used (illustrative, change and re-run)
A19: Defect probability per unit, stable sealer | B19: 0.002
A20: Average units between drift events | B20: 5000
A21: Defect probability per unit while drifting | B21: 0.25
A22: Manual visual detection rate at final inspection | B22: 0.85
A23: Share of sealer defect modes the in-line AI camera can see | B23: 0.7
A24: Units between sealer and today's final inspection | B24: 300
A25: Units built before manual feedback reaches the sealer | B25: 150
A26: Share of late-found defects scrapped | B26: 0.3
A27: Share of early-found defects scrapped | B27: 0.05
A28: Share of plant scrap from the pilot scope (team assumption) | B28: 0.4
A29: In-line check: 5 units after sealer, automatic feedback within 10 units, 90% detection on visible defect modes (case: AI camera in validation to Oct 2026).
A31: Robustness: closed-loop (scenario 4) scrap reduction vs today when each assumption changes
A32: Assumption | B32: Low | C32: Reduction | D32: Base | E32: Reduction | F32: High | G32: Reduction
A33: AI camera coverage of defect modes | B33: 0.5 | C33: 0.8247043 | D33: 0.7 | E33: 0.84684226 | F33: 0.9 | G33: 0.86670882
A34: Drift defect rate | B34: 0.1 | C34: 0.8026018 | D34: 0.25 | E34: 0.84799063 | F34: 0.4 | G34: 0.86492434
A35: Units between drift events | B35: 2500 | C35: 0.86340745 | D35: 5000 | E35: 0.85825104 | F35: 10000 | G35: 0.83368165
A36: Late-found scrap share | B36: 0.15 | C36: 0.83146269 | D36: 0.3 | E36: 0.85387796 | F36: 0.5 | G36: 0.85017711
A37: Units from sealer to today's inspection | B37: 100 | C37: 0.81112305 | D37: 300 | E37: 0.8492534 | F37: 600 | G37: 0.87379761
A38: Lowest scrap reduction across all tested cases: 80%. The mechanism holds even with pessimistic process assumptions.
A40: People test: how much value is lost when operators dismiss alerts?
A41: Share of drift episodes where alerts are dismissed | B41: Scrap reduction vs today
A42: 0 | B42: 0.93929302
A43: 0.1 | B43: 0.84457608
A44: 0.2 | B44: 0.7497195
A45: 0.31 | B45: 0.64310602
A46: 0.5 | B46: 0.49641257
A47: Exhibit 6B says 31% of operators frequently override alerts today. This chart is the quantified case for the people part of the idea.
A49: TEST 2. Is the business case robust? Financial Monte Carlo (10,000 runs, mirrors the Model tab incl. pilot-light phasing)
A50: Metric | B50: Value | C50: Note
A51: Deterministic base NPV (check vs Model tab) | B51: 27.014039 | C51: Should match Dashboard base NPV
A52: Mean NPV | B52: 11.823608 | C52: Rp billion
A53: P5 NPV (bad case) | B53: -19.41291 | C53: 1-in-20 downside
A54: Median NPV | B54: 11.708447
A55: P95 NPV (good case) | B55: 43.103322
A56: Probability NPV > 0 | B56: 0.7311 | C56: Headline for the financial slide
A57: Median full run-rate savings (Rp B/yr) | B57: 49.084413
A58: Median run-rate as % of conversion cost | B58: 0.087650737 | C58: vs 16% gap to benchmark
A60: TEST 2b. How should the roadmap spend the money? Same 10,000 runs, five strategies (gate = stop scaling if 2027 pilot adoption < 80%; happens in 25% of runs)
A61: Strategy | B61: Mean NPV | C61: P5 NPV | D61: Median NPV | E61: P95 NPV | F61: P(NPV > 0)
A62: A. Front-loaded phasing, no gate | B62: -0.19133229 | C62: -32.832551 | D62: -0.37372173 | E62: 32.504416 | F62: 0.4925
A63: B. Front-loaded phasing + gate (65% already spent) | B63: -3.7996789 | C63: -39.745907 | D63: -2.96235 | E63: 32.401945 | F63: 0.4518
A64: C. Pilot-light phasing, no gate (as in Model tab) | B64: 11.823608 | C64: -19.41291 | D64: 11.708447 | E64: 43.103322 | F64: 0.7311
A65: D. Pilot-light phasing + gate | B65: 15.0509 | C65: -8.4116268 | D65: 13.320402 | E65: 43.067723 | F65: 0.8595
A66: E. D + remaining equipment life valued at book | B66: 36.010535 | C66: 6.4767775 | D66: 36.960852 | E66: 67.48369 | F66: 0.9938
A67: F. D but savings ramp one year slower (stress test) | B67: -7.5342336 | C67: -31.899408 | D67: -5.5425073 | E67: 12.325501 | F67: 0.3242
A68: G. F + remaining equipment life valued at book | B68: 13.425401 | C68: -3.7787791 | D68: 11.927164 | E68: 35.124142 | F68: 0.879
A69: Pilot-light phasing: 10% / 15% / 40% / 25% / 10% of capex in 2026-2030. Ramp-up kept the same to isolate the effect of phasing; if scaling later also delays savings, the gain is smaller.
A70: Reading: a gate only protects value if little money is spent before it. Gate after heavy spending (B) destroys value; pilot-light + gate (D) is the design to defend in SQ3. Valuing equipment life beyond 2030 (E) is legitimate but state it openly. Stress test (F): if savings arrive a year late, P(NPV>0) falls to 32% (88% if remaining equipment life is valued, G). Speed of the pilot is the make-or-break factor: quick wins in 2026-27 belong in the roadmap.
A71: Ranges used (triangular low / mode / high): scrap 20/35/50%, maintenance 5/10/15%, NVA 15/30/45%, energy 2/5/8%, variant cost 20/35/50%, investment 60/80/110, running 8/9/12%, training 2/2.5/3, variant projects 2/3/5, cost per project 5/10/15, cash realization 30/50/70%, adoption 60/100/100%, labor share 35/40/45%.
A73: NPV distribution (histogram)
A74: NPV bin from (Rp B) | B74: Runs
A75: -51.6 | B75: 11
A76: -41.6 | B76: 73
A77: -31.5 | B77: 294
A78: -21.5 | B78: 700
A79: -11.5 | B79: 1367
A80: -1.4 | B80: 1920
A81: 8.6 | B81: 2028
A82: 18.6 | B82: 1753
A83: 28.6 | B83: 1056
A84: 38.7 | B84: 560
A85: 48.7 | B85: 182
A86: 58.7 | B86: 43
... A90: 98.9 | B90: 1
A92: TEST 3. Which assumption matters most? Tornado (base case, one at a time)
A93: Driver | B93: Low input | C93: High input | D93: NPV at low | E93: NPV at high | F93: Swing
A94: Investment (Rp B) | B94: 110 | C94: 60 | D94: -1.4979109 | E94: 46.022005 | F94: 47.519916
A95: Adoption achieved | B95: 0.6 | C95: 1 | D95: -17.99511 | E95: 27.014039 | F95: 45.009149
A96: Scrap reduction | B96: 0.2 | C96: 0.5 | D96: 7.3765393 | E96: 46.651538 | F96: 39.274999
A97: Variant projects / yr | B97: 2 | C97: 5 | D97: 18.831747 | E97: 43.378622 | F97: 24.546874
A98: Cost per variant project | B98: 5 | C98: 15 | D98: 14.740602 | E98: 39.287476 | F98: 24.546874
A99: Variant cost reduction | B99: 0.2 | C99: 0.5 | D99: 16.49395 | E99: 37.534128 | F99: 21.040178
A100: Operator NVA eliminated | B100: 0.15 | C100: 0.45 | D100: 18.373539 | E100: 35.654538 | F100: 17.280999
A101: Maintenance reduction | B101: 0.05 | C101: 0.15 | D101: 18.504456 | E101: 35.523622 | F101: 17.019166
A102: Energy reduction | B102: 0.02 | C102: 0.08 | D102: 22.301039 | E102: 31.727039 | F102: 9.4259997
A103: Running cost % | B103: 0.12 | C103: 0.08 | D103: 23.779625 | E103: 30.248453 | F103: 6.4688279
A104: Use the top 2-3 drivers as the assumptions you defend hardest in Q&A, and as the KPIs you track first in the pilot.

Sheet Simulation7
A1: Idea tests: simulation results (values produced by run_tests.py, not formulas)
A2: Re-run run_tests.py after changing assumptions. Process parameters below are illustrative assumptions, not TMMIN data: present them as a mechanism test, and show the sensitivity.
A4: TEST 1. Does closing the quality loop beat adding technology alone? (sealer drift -> inspection -> feedback, 1 year, 175,000 units, 300 runs)
A5: Scenario | B5: Defective units / yr | C5: Scrapped units / yr | D5: Escaped defects / yr | E5: Units built while drifting | F5: Scrap vs today | G5: Escapes vs today | H5: Scrap P5-P95
A6: 1. Today: visual at final inspection, manual feedback | B6: 4266.68 | C6: 1088.524 | D6: 638.26667 | E6: 15796.093 | F6: 0 | G6: 0 | H6: 835 - 1,365
A7: 2. Better camera at end-of-line only (tech, no loop) | B7: 4265.3233 | C7: 1215.776 | D7: 212.73667 | E7: 15793.257 | F7: 0.11690326 | G7: -0.66669626 | H7: 910 - 1,492
A8: 3. Closed loop at sealer, 31% of alerts dismissed (as today) | B8: 1652.95 | C8: 362.15367 | D8: 203.26 | E8: 5247.72 | F8: -0.66729841 | G8: -0.68154376 | H8: 216 - 543
A9: 4. Closed loop with people-centred design (10% dismissed) | B9: 908.32333 | C9: 166.86333 | D9: 88.006667 | E9: 2257.0067 | F9: -0.84670679 | G9: -0.86211615 | H9: 83 - 270
A11: What this shows
A12: - A better camera at end-of-line alone changes scrap by +12% while escapes fall 67%: it catches more bad units, but too late, so escapes turn into scrap. It does not prevent defects.
A13: - Closing the loop right after the sealer cuts scrap 85% and escapes 86%, because a drift is stopped within a few units instead of hundreds.
A14: - If operators dismiss alerts in 31% of drift episodes (today's override rate), scrap reduction falls to 67%. Trust, training and alert design are part of the value, not an add-on.
A15: - Plant-wide: if the pilot scope causes 40% of plant scrap (team assumption), the plant-wide scrap cut is about 34%. Compare with the 20% / 35% / 50% lever in Assumptions.
A16: - Deck message: value comes from redesigning the system (where the check sits, how fast the signal travels, who acts on it), not from buying the device. That is exactly the case ask.
A18: Process assumptions used (illustrative, change and re-run)
A19: Defect probability per unit, stable sealer | B19: 0.002
A20: Average units between drift events | B20: 5000
A21: Defect probability per unit while drifting | B21: 0.25
A22: Manual visual detection rate at final inspection | B22: 0.85
A23: Share of sealer defect modes the in-line AI camera can see | B23: 0.7
A24: Units between sealer and today's final inspection | B24: 300
A25: Units built before manual feedback reaches the sealer | B25: 150
A26: Share of late-found defects scrapped | B26: 0.3
A27: Share of early-found defects scrapped | B27: 0.05
A28: Share of plant scrap from the pilot scope (team assumption) | B28: 0.4
A29: In-line check: 5 units after sealer, automatic feedback within 10 units, 90% detection on visible defect modes (case: AI camera in validation to Oct 2026).
A31: Robustness: closed-loop (scenario 4) scrap reduction vs today when each assumption changes
A32: Assumption | B32: Low | C32: Reduction | D32: Base | E32: Reduction | F32: High | G32: Reduction
A33: AI camera coverage of defect modes | B33: 0.5 | C33: 0.8247043 | D33: 0.7 | E33: 0.84684226 | F33: 0.9 | G33: 0.86670882
A34: Drift defect rate | B34: 0.1 | C34: 0.8026018 | D34: 0.25 | E34: 0.84799063 | F34: 0.4 | G34: 0.86492434
A35: Units between drift events | B35: 2500 | C35: 0.86340745 | D35: 5000 | E35: 0.85825104 | F35: 10000 | G35: 0.83368165
A36: Late-found scrap share | B36: 0.15 | C36: 0.83146269 | D36: 0.3 | E36: 0.85387796 | F36: 0.5 | G36: 0.85017711
A37: Units from sealer to today's inspection | B37: 100 | C37: 0.81112305 | D37: 300 | E37: 0.8492534 | F37: 600 | G37: 0.87379761
A38: Lowest scrap reduction across all tested cases: 80%. The mechanism holds even with pessimistic process assumptions.
A40: People test: how much value is lost when operators dismiss alerts?
A41: Share of drift episodes where alerts are dismissed | B41: Scrap reduction vs today
A42: 0 | B42: 0.93929302
A43: 0.1 | B43: 0.84457608
A44: 0.2 | B44: 0.7497195
A45: 0.31 | B45: 0.64310602
A46: 0.5 | B46: 0.49641257
A47: Exhibit 6B says 31% of operators frequently override alerts today. This chart is the quantified case for the people part of the idea.
A49: TEST 2. Is the business case robust? Financial Monte Carlo (10,000 runs, mirrors the Model tab incl. pilot-light phasing)
A50: Metric | B50: Value | C50: Note
A51: Deterministic base NPV (check vs Model tab) | B51: 27.014039 | C51: Should match Dashboard base NPV
A52: Mean NPV | B52: 11.823608 | C52: Rp billion
A53: P5 NPV (bad case) | B53: -19.41291 | C53: 1-in-20 downside
A54: Median NPV | B54: 11.708447
A55: P95 NPV (good case) | B55: 43.103322
A56: Probability NPV > 0 | B56: 0.7311 | C56: Headline for the financial slide
A57: Median full run-rate savings (Rp B/yr) | B57: 49.084413
A58: Median run-rate as % of conversion cost | B58: 0.087650737 | C58: vs 16% gap to benchmark
A60: TEST 2b. How should the roadmap spend the money? Same 10,000 runs, five strategies (gate = stop scaling if 2027 pilot adoption < 80%; happens in 25% of runs)
A61: Strategy | B61: Mean NPV | C61: P5 NPV | D61: Median NPV | E61: P95 NPV | F61: P(NPV > 0)
A62: A. Front-loaded phasing, no gate | B62: -0.19133229 | C62: -32.832551 | D62: -0.37372173 | E62: 32.504416 | F62: 0.4925
A63: B. Front-loaded phasing + gate (65% already spent) | B63: -3.7996789 | C63: -39.745907 | D63: -2.96235 | E63: 32.401945 | F63: 0.4518
A64: C. Pilot-light phasing, no gate (as in Model tab) | B64: 11.823608 | C64: -19.41291 | D64: 11.708447 | E64: 43.103322 | F64: 0.7311
A65: D. Pilot-light phasing + gate | B65: 15.0509 | C65: -8.4116268 | D65: 13.320402 | E65: 43.067723 | F65: 0.8595
A66: E. D + remaining equipment life valued at book | B66: 36.010535 | C66: 6.4767775 | D66: 36.960852 | E66: 67.48369 | F66: 0.9938
A67: F. D but savings ramp one year slower (stress test) | B67: -7.5342336 | C67: -31.899408 | D67: -5.5425073 | E67: 12.325501 | F67: 0.3242
A68: G. F + remaining equipment life valued at book | B68: 13.425401 | C68: -3.7787791 | D68: 11.927164 | E68: 35.124142 | F68: 0.879
A69: Pilot-light phasing: 10% / 15% / 40% / 25% / 10% of capex in 2026-2030. Ramp-up kept the same to isolate the effect of phasing; if scaling later also delays savings, the gain is smaller.
A70: Reading: a gate only protects value if little money is spent before it. Gate after heavy spending (B) destroys value; pilot-light + gate (D) is the design to defend in SQ3. Valuing equipment life beyond 2030 (E) is legitimate but state it openly. Stress test (F): if savings arrive a year late, P(NPV>0) falls to 32% (88% if remaining equipment life is valued, G). Speed of the pilot is the make-or-break factor: quick wins in 2026-27 belong in the roadmap.
A71: Ranges used (triangular low / mode / high): scrap 20/35/50%, maintenance 5/10/15%, NVA 15/30/45%, energy 2/5/8%, variant cost 20/35/50%, investment 60/80/110, running 8/9/12%, training 2/2.5/3, variant projects 2/3/5, cost per project 5/10/15, cash realization 30/50/70%, adoption 60/100/100%, labor share 35/40/45%.
A73: NPV distribution (histogram)
A74: NPV bin from (Rp B) | B74: Runs
A75: -51.6 | B75: 11
A76: -41.6 | B76: 73
A77: -31.5 | B77: 294
A78: -21.5 | B78: 700
A79: -11.5 | B79: 1367
A80: -1.4 | B80: 1920
A81: 8.6 | B81: 2028
A82: 18.6 | B82: 1753
A83: 28.6 | B83: 1056
A84: 38.7 | B84: 560
A85: 48.7 | B85: 182
A86: 58.7 | B86: 43
... A90: 98.9 | B90: 1
A92: TEST 3. Which assumption matters most? Tornado (base case, one at a time)
A93: Driver | B93: Low input | C93: High input | D93: NPV at low | E93: NPV at high | F93: Swing
A94: Investment (Rp B) | B94: 110 | C94: 60 | D94: -1.4979109 | E94: 46.022005 | F94: 47.519916
A95: Adoption achieved | B95: 0.6 | C95: 1 | D95: -17.99511 | E95: 27.014039 | F95: 45.009149
A96: Scrap reduction | B96: 0.2 | C96: 0.5 | D96: 7.3765393 | E96: 46.651538 | F96: 39.274999
A97: Variant projects / yr | B97: 2 | C97: 5 | D97: 18.831747 | E97: 43.378622 | F97: 24.546874
A98: Cost per variant project | B98: 5 | C98: 15 | D98: 14.740602 | E98: 39.287476 | F98: 24.546874
A99: Variant cost reduction | B99: 0.2 | C99: 0.5 | D99: 16.49395 | E99: 37.534128 | F99: 21.040178
A100: Operator NVA eliminated | B100: 0.15 | C100: 0.45 | D100: 18.373539 | E100: 35.654538 | F100: 17.280999
A101: Maintenance reduction | B101: 0.05 | C101: 0.15 | D101: 18.504456 | E101: 35.523622 | F101: 17.019166
A102: Energy reduction | B102: 0.02 | C102: 0.08 | D102: 22.301039 | E102: 31.727039 | F102: 9.4259997
A103: Running cost % | B103: 0.12 | C103: 0.08 | D103: 23.779625 | E103: 30.248453 | F103: 6.4688279
A104: Use the top 2-3 drivers as the assumptions you defend hardest in Q&A, and as the KPIs you track first in the pilot.

Sheet Simulation6
A1: Idea tests: simulation results (values produced by run_tests.py, not formulas)
A2: Re-run run_tests.py after changing assumptions. Process parameters below are illustrative assumptions, not TMMIN data: present them as a mechanism test, and show the sensitivity.
A4: TEST 1. Does closing the quality loop beat adding technology alone? (sealer drift -> inspection -> feedback, 1 year, 175,000 units, 300 runs)
A5: Scenario | B5: Defective units / yr | C5: Scrapped units / yr | D5: Escaped defects / yr | E5: Units built while drifting | F5: Scrap vs today | G5: Escapes vs today | H5: Scrap P5-P95
A6: 1. Today: visual at final inspection, manual feedback | B6: 4266.68 | C6: 1088.524 | D6: 638.26667 | E6: 15796.093 | F6: 0 | G6: 0 | H6: 835 - 1,365
A7: 2. Better camera at end-of-line only (tech, no loop) | B7: 4265.3233 | C7: 1215.776 | D7: 212.73667 | E7: 15793.257 | F7: 0.11690326 | G7: -0.66669626 | H7: 910 - 1,492
A8: 3. Closed loop at sealer, 31% of alerts dismissed (as today) | B8: 1652.95 | C8: 362.15367 | D8: 203.26 | E8: 5247.72 | F8: -0.66729841 | G8: -0.68154376 | H8: 216 - 543
A9: 4. Closed loop with people-centred design (10% dismissed) | B9: 908.32333 | C9: 166.86333 | D9: 88.006667 | E9: 2257.0067 | F9: -0.84670679 | G9: -0.86211615 | H9: 83 - 270
A11: What this shows
A12: - A better camera at end-of-line alone changes scrap by +12% while escapes fall 67%: it catches more bad units, but too late, so escapes turn into scrap. It does not prevent defects.
A13: - Closing the loop right after the sealer cuts scrap 85% and escapes 86%, because a drift is stopped within a few units instead of hundreds.
A14: - If operators dismiss alerts in 31% of drift episodes (today's override rate), scrap reduction falls to 67%. Trust, training and alert design are part of the value, not an add-on.
A15: - Plant-wide: if the pilot scope causes 40% of plant scrap (team assumption), the plant-wide scrap cut is about 34%. Compare with the 20% / 35% / 50% lever in Assumptions.
A16: - Deck message: value comes from redesigning the system (where the check sits, how fast the signal travels, who acts on it), not from buying the device. That is exactly the case ask.
A18: Process assumptions used (illustrative, change and re-run)
A19: Defect probability per unit, stable sealer | B19: 0.002
A20: Average units between drift events | B20: 5000
A21: Defect probability per unit while drifting | B21: 0.25
A22: Manual visual detection rate at final inspection | B22: 0.85
A23: Share of sealer defect modes the in-line AI camera can see | B23: 0.7
A24: Units between sealer and today's final inspection | B24: 300
A25: Units built before manual feedback reaches the sealer | B25: 150
A26: Share of late-found defects scrapped | B26: 0.3
A27: Share of early-found defects scrapped | B27: 0.05
A28: Share of plant scrap from the pilot scope (team assumption) | B28: 0.4
A29: In-line check: 5 units after sealer, automatic feedback within 10 units, 90% detection on visible defect modes (case: AI camera in validation to Oct 2026).
A31: Robustness: closed-loop (scenario 4) scrap reduction vs today when each assumption changes
A32: Assumption | B32: Low | C32: Reduction | D32: Base | E32: Reduction | F32: High | G32: Reduction
A33: AI camera coverage of defect modes | B33: 0.5 | C33: 0.8247043 | D33: 0.7 | E33: 0.84684226 | F33: 0.9 | G33: 0.86670882
A34: Drift defect rate | B34: 0.1 | C34: 0.8026018 | D34: 0.25 | E34: 0.84799063 | F34: 0.4 | G34: 0.86492434
A35: Units between drift events | B35: 2500 | C35: 0.86340745 | D35: 5000 | E35: 0.85825104 | F35: 10000 | G35: 0.83368165
A36: Late-found scrap share | B36: 0.15 | C36: 0.83146269 | D36: 0.3 | E36: 0.85387796 | F36: 0.5 | G36: 0.85017711
A37: Units from sealer to today's inspection | B37: 100 | C37: 0.81112305 | D37: 300 | E37: 0.8492534 | F37: 600 | G37: 0.87379761
A38: Lowest scrap reduction across all tested cases: 80%. The mechanism holds even with pessimistic process assumptions.
A40: People test: how much value is lost when operators dismiss alerts?
A41: Share of drift episodes where alerts are dismissed | B41: Scrap reduction vs today
A42: 0 | B42: 0.93929302
A43: 0.1 | B43: 0.84457608
A44: 0.2 | B44: 0.7497195
A45: 0.31 | B45: 0.64310602
A46: 0.5 | B46: 0.49641257
A47: Exhibit 6B says 31% of operators frequently override alerts today. This chart is the quantified case for the people part of the idea.
A49: TEST 2. Is the business case robust? Financial Monte Carlo (10,000 runs, mirrors the Model tab incl. pilot-light phasing)
A50: Metric | B50: Value | C50: Note
A51: Deterministic base NPV (check vs Model tab) | B51: 27.014039 | C51: Should match Dashboard base NPV
A52: Mean NPV | B52: 11.823608 | C52: Rp billion
A53: P5 NPV (bad case) | B53: -19.41291 | C53: 1-in-20 downside
A54: Median NPV | B54: 11.708447
A55: P95 NPV (good case) | B55: 43.103322
A56: Probability NPV > 0 | B56: 0.7311 | C56: Headline for the financial slide
A57: Median full run-rate savings (Rp B/yr) | B57: 49.084413
A58: Median run-rate as % of conversion cost | B58: 0.087650737 | C58: vs 16% gap to benchmark
A60: TEST 2b. How should the roadmap spend the money? Same 10,000 runs, five strategies (gate = stop scaling if 2027 pilot adoption < 80%; happens in 25% of runs)
A61: Strategy | B61: Mean NPV | C61: P5 NPV | D61: Median NPV | E61: P95 NPV | F61: P(NPV > 0)
A62: A. Front-loaded phasing, no gate | B62: -0.19133229 | C62: -32.832551 | D62: -0.37372173 | E62: 32.504416 | F62: 0.4925
A63: B. Front-loaded phasing + gate (65% already spent) | B63: -3.7996789 | C63: -39.745907 | D63: -2.96235 | E63: 32.401945 | F63: 0.4518
A64: C. Pilot-light phasing, no gate (as in Model tab) | B64: 11.823608 | C64: -19.41291 | D64: 11.708447 | E64: 43.103322 | F64: 0.7311
A65: D. Pilot-light phasing + gate | B65: 15.0509 | C65: -8.4116268 | D65: 13.320402 | E65: 43.067723 | F65: 0.8595
A66: E. D + remaining equipment life valued at book | B66: 36.010535 | C66: 6.4767775 | D66: 36.960852 | E66: 67.48369 | F66: 0.9938
A67: F. D but savings ramp one year slower (stress test) | B67: -7.5342336 | C67: -31.899408 | D67: -5.5425073 | E67: 12.325501 | F67: 0.3242
A68: G. F + remaining equipment life valued at book | B68: 13.425401 | C68: -3.7787791 | D68: 11.927164 | E68: 35.124142 | F68: 0.879
A69: Pilot-light phasing: 10% / 15% / 40% / 25% / 10% of capex in 2026-2030. Ramp-up kept the same to isolate the effect of phasing; if scaling later also delays savings, the gain is smaller.
A70: Reading: a gate only protects value if little money is spent before it. Gate after heavy spending (B) destroys value; pilot-light + gate (D) is the design to defend in SQ3. Valuing equipment life beyond 2030 (E) is legitimate but state it openly. Stress test (F): if savings arrive a year late, P(NPV>0) falls to 32% (88% if remaining equipment life is valued, G). Speed of the pilot is the make-or-break factor: quick wins in 2026-27 belong in the roadmap.
A71: Ranges used (triangular low / mode / high): scrap 20/35/50%, maintenance 5/10/15%, NVA 15/30/45%, energy 2/5/8%, variant cost 20/35/50%, investment 60/80/110, running 8/9/12%, training 2/2.5/3, variant projects 2/3/5, cost per project 5/10/15, cash realization 30/50/70%, adoption 60/100/100%, labor share 35/40/45%.
A73: NPV distribution (histogram)
A74: NPV bin from (Rp B) | B74: Runs
A75: -51.6 | B75: 11
A76: -41.6 | B76: 73
A77: -31.5 | B77: 294
A78: -21.5 | B78: 700
A79: -11.5 | B79: 1367
A80: -1.4 | B80: 1920
A81: 8.6 | B81: 2028
A82: 18.6 | B82: 1753
A83: 28.6 | B83: 1056
A84: 38.7 | B84: 560
A85: 48.7 | B85: 182
A86: 58.7 | B86: 43
... A90: 98.9 | B90: 1
A92: TEST 3. Which assumption matters most? Tornado (base case, one at a time)
A93: Driver | B93: Low input | C93: High input | D93: NPV at low | E93: NPV at high | F93: Swing
A94: Investment (Rp B) | B94: 110 | C94: 60 | D94: -1.4979109 | E94: 46.022005 | F94: 47.519916
A95: Adoption achieved | B95: 0.6 | C95: 1 | D95: -17.99511 | E95: 27.014039 | F95: 45.009149
A96: Scrap reduction | B96: 0.2 | C96: 0.5 | D96: 7.3765393 | E96: 46.651538 | F96: 39.274999
A97: Variant projects / yr | B97: 2 | C97: 5 | D97: 18.831747 | E97: 43.378622 | F97: 24.546874
A98: Cost per variant project | B98: 5 | C98: 15 | D98: 14.740602 | E98: 39.287476 | F98: 24.546874
A99: Variant cost reduction | B99: 0.2 | C99: 0.5 | D99: 16.49395 | E99: 37.534128 | F99: 21.040178
A100: Operator NVA eliminated | B100: 0.15 | C100: 0.45 | D100: 18.373539 | E100: 35.654538 | F100: 17.280999
A101: Maintenance reduction | B101: 0.05 | C101: 0.15 | D101: 18.504456 | E101: 35.523622 | F101: 17.019166
A102: Energy reduction | B102: 0.02 | C102: 0.08 | D102: 22.301039 | E102: 31.727039 | F102: 9.4259997
A103: Running cost % | B103: 0.12 | C103: 0.08 | D103: 23.779625 | E103: 30.248453 | F103: 6.4688279
A104: Use the top 2-3 drivers as the assumptions you defend hardest in Q&A, and as the KPIs you track first in the pilot.

Sheet Simulation5
A1: Idea tests: simulation results (values produced by run_tests.py, not formulas)
A2: Re-run run_tests.py after changing assumptions. Process parameters below are illustrative assumptions, not TMMIN data: present them as a mechanism test, and show the sensitivity.
A4: TEST 1. Does closing the quality loop beat adding technology alone? (sealer drift -> inspection -> feedback, 1 year, 175,000 units, 300 runs)
A5: Scenario | B5: Defective units / yr | C5: Scrapped units / yr | D5: Escaped defects / yr | E5: Units built while drifting | F5: Scrap vs today | G5: Escapes vs today | H5: Scrap P5-P95
A6: 1. Today: visual at final inspection, manual feedback | B6: 4266.68 | C6: 1088.524 | D6: 638.26667 | E6: 15796.093 | F6: 0 | G6: 0 | H6: 835 - 1,365
A7: 2. Better camera at end-of-line only (tech, no loop) | B7: 4265.3233 | C7: 1215.776 | D7: 212.73667 | E7: 15793.257 | F7: 0.11690326 | G7: -0.66669626 | H7: 910 - 1,492
A8: 3. Closed loop at sealer, 31% of alerts dismissed (as today) | B8: 1652.95 | C8: 362.15367 | D8: 203.26 | E8: 5247.72 | F8: -0.66729841 | G8: -0.68154376 | H8: 216 - 543
A9: 4. Closed loop with people-centred design (10% dismissed) | B9: 908.32333 | C9: 166.86333 | D9: 88.006667 | E9: 2257.0067 | F9: -0.84670679 | G9: -0.86211615 | H9: 83 - 270
A11: What this shows
A12: - A better camera at end-of-line alone changes scrap by +12% while escapes fall 67%: it catches more bad units, but too late, so escapes turn into scrap. It does not prevent defects.
A13: - Closing the loop right after the sealer cuts scrap 85% and escapes 86%, because a drift is stopped within a few units instead of hundreds.
A14: - If operators dismiss alerts in 31% of drift episodes (today's override rate), scrap reduction falls to 67%. Trust, training and alert design are part of the value, not an add-on.
A15: - Plant-wide: if the pilot scope causes 40% of plant scrap (team assumption), the plant-wide scrap cut is about 34%. Compare with the 20% / 35% / 50% lever in Assumptions.
A16: - Deck message: value comes from redesigning the system (where the check sits, how fast the signal travels, who acts on it), not from buying the device. That is exactly the case ask.
A18: Process assumptions used (illustrative, change and re-run)
A19: Defect probability per unit, stable sealer | B19: 0.002
A20: Average units between drift events | B20: 5000
A21: Defect probability per unit while drifting | B21: 0.25
A22: Manual visual detection rate at final inspection | B22: 0.85
A23: Share of sealer defect modes the in-line AI camera can see | B23: 0.7
A24: Units between sealer and today's final inspection | B24: 300
A25: Units built before manual feedback reaches the sealer | B25: 150
A26: Share of late-found defects scrapped | B26: 0.3
A27: Share of early-found defects scrapped | B27: 0.05
A28: Share of plant scrap from the pilot scope (team assumption) | B28: 0.4
A29: In-line check: 5 units after sealer, automatic feedback within 10 units, 90% detection on visible defect modes (case: AI camera in validation to Oct 2026).
A31: Robustness: closed-loop (scenario 4) scrap reduction vs today when each assumption changes
A32: Assumption | B32: Low | C32: Reduction | D32: Base | E32: Reduction | F32: High | G32: Reduction
A33: AI camera coverage of defect modes | B33: 0.5 | C33: 0.8247043 | D33: 0.7 | E33: 0.84684226 | F33: 0.9 | G33: 0.86670882
A34: Drift defect rate | B34: 0.1 | C34: 0.8026018 | D34: 0.25 | E34: 0.84799063 | F34: 0.4 | G34: 0.86492434
A35: Units between drift events | B35: 2500 | C35: 0.86340745 | D35: 5000 | E35: 0.85825104 | F35: 10000 | G35: 0.83368165
A36: Late-found scrap share | B36: 0.15 | C36: 0.83146269 | D36: 0.3 | E36: 0.85387796 | F36: 0.5 | G36: 0.85017711
A37: Units from sealer to today's inspection | B37: 100 | C37: 0.81112305 | D37: 300 | E37: 0.8492534 | F37: 600 | G37: 0.87379761
A38: Lowest scrap reduction across all tested cases: 80%. The mechanism holds even with pessimistic process assumptions.
A40: People test: how much value is lost when operators dismiss alerts?
A41: Share of drift episodes where alerts are dismissed | B41: Scrap reduction vs today
A42: 0 | B42: 0.93929302
A43: 0.1 | B43: 0.84457608
A44: 0.2 | B44: 0.7497195
A45: 0.31 | B45: 0.64310602
A46: 0.5 | B46: 0.49641257
A47: Exhibit 6B says 31% of operators frequently override alerts today. This chart is the quantified case for the people part of the idea.
A49: TEST 2. Is the business case robust? Financial Monte Carlo (10,000 runs, mirrors the Model tab incl. pilot-light phasing)
A50: Metric | B50: Value | C50: Note
A51: Deterministic base NPV (check vs Model tab) | B51: 27.014039 | C51: Should match Dashboard base NPV
A52: Mean NPV | B52: 11.823608 | C52: Rp billion
A53: P5 NPV (bad case) | B53: -19.41291 | C53: 1-in-20 downside
A54: Median NPV | B54: 11.708447
A55: P95 NPV (good case) | B55: 43.103322
A56: Probability NPV > 0 | B56: 0.7311 | C56: Headline for the financial slide
A57: Median full run-rate savings (Rp B/yr) | B57: 49.084413
A58: Median run-rate as % of conversion cost | B58: 0.087650737 | C58: vs 16% gap to benchmark
A60: TEST 2b. How should the roadmap spend the money? Same 10,000 runs, five strategies (gate = stop scaling if 2027 pilot adoption < 80%; happens in 25% of runs)
A61: Strategy | B61: Mean NPV | C61: P5 NPV | D61: Median NPV | E61: P95 NPV | F61: P(NPV > 0)
A62: A. Front-loaded phasing, no gate | B62: -0.19133229 | C62: -32.832551 | D62: -0.37372173 | E62: 32.504416 | F62: 0.4925
A63: B. Front-loaded phasing + gate (65% already spent) | B63: -3.7996789 | C63: -39.745907 | D63: -2.96235 | E63: 32.401945 | F63: 0.4518
A64: C. Pilot-light phasing, no gate (as in Model tab) | B64: 11.823608 | C64: -19.41291 | D64: 11.708447 | E64: 43.103322 | F64: 0.7311
A65: D. Pilot-light phasing + gate | B65: 15.0509 | C65: -8.4116268 | D65: 13.320402 | E65: 43.067723 | F65: 0.8595
A66: E. D + remaining equipment life valued at book | B66: 36.010535 | C66: 6.4767775 | D66: 36.960852 | E66: 67.48369 | F66: 0.9938
A67: F. D but savings ramp one year slower (stress test) | B67: -7.5342336 | C67: -31.899408 | D67: -5.5425073 | E67: 12.325501 | F67: 0.3242
A68: G. F + remaining equipment life valued at book | B68: 13.425401 | C68: -3.7787791 | D68: 11.927164 | E68: 35.124142 | F68: 0.879
A69: Pilot-light phasing: 10% / 15% / 40% / 25% / 10% of capex in 2026-2030. Ramp-up kept the same to isolate the effect of phasing; if scaling later also delays savings, the gain is smaller.
A70: Reading: a gate only protects value if little money is spent before it. Gate after heavy spending (B) destroys value; pilot-light + gate (D) is the design to defend in SQ3. Valuing equipment life beyond 2030 (E) is legitimate but state it openly. Stress test (F): if savings arrive a year late, P(NPV>0) falls to 32% (88% if remaining equipment life is valued, G). Speed of the pilot is the make-or-break factor: quick wins in 2026-27 belong in the roadmap.
A71: Ranges used (triangular low / mode / high): scrap 20/35/50%, maintenance 5/10/15%, NVA 15/30/45%, energy 2/5/8%, variant cost 20/35/50%, investment 60/80/110, running 8/9/12%, training 2/2.5/3, variant projects 2/3/5, cost per project 5/10/15, cash realization 30/50/70%, adoption 60/100/100%, labor share 35/40/45%.
A73: NPV distribution (histogram)
A74: NPV bin from (Rp B) | B74: Runs
A75: -51.6 | B75: 11
A76: -41.6 | B76: 73
A77: -31.5 | B77: 294
A78: -21.5 | B78: 700
A79: -11.5 | B79: 1367
A80: -1.4 | B80: 1920
A81: 8.6 | B81: 2028
A82: 18.6 | B82: 1753
A83: 28.6 | B83: 1056
A84: 38.7 | B84: 560
A85: 48.7 | B85: 182
A86: 58.7 | B86: 43
... A90: 98.9 | B90: 1
A92: TEST 3. Which assumption matters most? Tornado (base case, one at a time)
A93: Driver | B93: Low input | C93: High input | D93: NPV at low | E93: NPV at high | F93: Swing
A94: Investment (Rp B) | B94: 110 | C94: 60 | D94: -1.4979109 | E94: 46.022005 | F94: 47.519916
A95: Adoption achieved | B95: 0.6 | C95: 1 | D95: -17.99511 | E95: 27.014039 | F95: 45.009149
A96: Scrap reduction | B96: 0.2 | C96: 0.5 | D96: 7.3765393 | E96: 46.651538 | F96: 39.274999
A97: Variant projects / yr | B97: 2 | C97: 5 | D97: 18.831747 | E97: 43.378622 | F97: 24.546874
A98: Cost per variant project | B98: 5 | C98: 15 | D98: 14.740602 | E98: 39.287476 | F98: 24.546874
A99: Variant cost reduction | B99: 0.2 | C99: 0.5 | D99: 16.49395 | E99: 37.534128 | F99: 21.040178
A100: Operator NVA eliminated | B100: 0.15 | C100: 0.45 | D100: 18.373539 | E100: 35.654538 | F100: 17.280999
A101: Maintenance reduction | B101: 0.05 | C101: 0.15 | D101: 18.504456 | E101: 35.523622 | F101: 17.019166
A102: Energy reduction | B102: 0.02 | C102: 0.08 | D102: 22.301039 | E102: 31.727039 | F102: 9.4259997
A103: Running cost % | B103: 0.12 | C103: 0.08 | D103: 23.779625 | E103: 30.248453 | F103: 6.4688279
A104: Use the top 2-3 drivers as the assumptions you defend hardest in Q&A, and as the KPIs you track first in the pilot.

Sheet Simulation4
A1: Idea tests: simulation results (values produced by run_tests.py, not formulas)
A2: Re-run run_tests.py after changing assumptions. Process parameters below are illustrative assumptions, not TMMIN data: present them as a mechanism test, and show the sensitivity.
A4: TEST 1. Does closing the quality loop beat adding technology alone? (sealer drift -> inspection -> feedback, 1 year, 175,000 units, 300 runs)
A5: Scenario | B5: Defective units / yr | C5: Scrapped units / yr | D5: Escaped defects / yr | E5: Units built while drifting | F5: Scrap vs today | G5: Escapes vs today | H5: Scrap P5-P95
A6: 1. Today: visual at final inspection, manual feedback | B6: 4266.68 | C6: 1088.524 | D6: 638.26667 | E6: 15796.093 | F6: 0 | G6: 0 | H6: 835 - 1,365
A7: 2. Better camera at end-of-line only (tech, no loop) | B7: 4265.3233 | C7: 1215.776 | D7: 212.73667 | E7: 15793.257 | F7: 0.11690326 | G7: -0.66669626 | H7: 910 - 1,492
A8: 3. Closed loop at sealer, 31% of alerts dismissed (as today) | B8: 1652.95 | C8: 362.15367 | D8: 203.26 | E8: 5247.72 | F8: -0.66729841 | G8: -0.68154376 | H8: 216 - 543
A9: 4. Closed loop with people-centred design (10% dismissed) | B9: 908.32333 | C9: 166.86333 | D9: 88.006667 | E9: 2257.0067 | F9: -0.84670679 | G9: -0.86211615 | H9: 83 - 270
A11: What this shows
A12: - A better camera at end-of-line alone changes scrap by +12% while escapes fall 67%: it catches more bad units, but too late, so escapes turn into scrap. It does not prevent defects.
A13: - Closing the loop right after the sealer cuts scrap 85% and escapes 86%, because a drift is stopped within a few units instead of hundreds.
A14: - If operators dismiss alerts in 31% of drift episodes (today's override rate), scrap reduction falls to 67%. Trust, training and alert design are part of the value, not an add-on.
A15: - Plant-wide: if the pilot scope causes 40% of plant scrap (team assumption), the plant-wide scrap cut is about 34%. Compare with the 20% / 35% / 50% lever in Assumptions.
A16: - Deck message: value comes from redesigning the system (where the check sits, how fast the signal travels, who acts on it), not from buying the device. That is exactly the case ask.
A18: Process assumptions used (illustrative, change and re-run)
A19: Defect probability per unit, stable sealer | B19: 0.002
A20: Average units between drift events | B20: 5000
A21: Defect probability per unit while drifting | B21: 0.25
A22: Manual visual detection rate at final inspection | B22: 0.85
A23: Share of sealer defect modes the in-line AI camera can see | B23: 0.7
A24: Units between sealer and today's final inspection | B24: 300
A25: Units built before manual feedback reaches the sealer | B25: 150
A26: Share of late-found defects scrapped | B26: 0.3
A27: Share of early-found defects scrapped | B27: 0.05
A28: Share of plant scrap from the pilot scope (team assumption) | B28: 0.4
A29: In-line check: 5 units after sealer, automatic feedback within 10 units, 90% detection on visible defect modes (case: AI camera in validation to Oct 2026).
A31: Robustness: closed-loop (scenario 4) scrap reduction vs today when each assumption changes
A32: Assumption | B32: Low | C32: Reduction | D32: Base | E32: Reduction | F32: High | G32: Reduction
A33: AI camera coverage of defect modes | B33: 0.5 | C33: 0.8247043 | D33: 0.7 | E33: 0.84684226 | F33: 0.9 | G33: 0.86670882
A34: Drift defect rate | B34: 0.1 | C34: 0.8026018 | D34: 0.25 | E34: 0.84799063 | F34: 0.4 | G34: 0.86492434
A35: Units between drift events | B35: 2500 | C35: 0.86340745 | D35: 5000 | E35: 0.85825104 | F35: 10000 | G35: 0.83368165
A36: Late-found scrap share | B36: 0.15 | C36: 0.83146269 | D36: 0.3 | E36: 0.85387796 | F36: 0.5 | G36: 0.85017711
A37: Units from sealer to today's inspection | B37: 100 | C37: 0.81112305 | D37: 300 | E37: 0.8492534 | F37: 600 | G37: 0.87379761
A38: Lowest scrap reduction across all tested cases: 80%. The mechanism holds even with pessimistic process assumptions.
A40: People test: how much value is lost when operators dismiss alerts?
A41: Share of drift episodes where alerts are dismissed | B41: Scrap reduction vs today
A42: 0 | B42: 0.93929302
A43: 0.1 | B43: 0.84457608
A44: 0.2 | B44: 0.7497195
A45: 0.31 | B45: 0.64310602
A46: 0.5 | B46: 0.49641257
A47: Exhibit 6B says 31% of operators frequently override alerts today. This chart is the quantified case for the people part of the idea.
A49: TEST 2. Is the business case robust? Financial Monte Carlo (10,000 runs, mirrors the Model tab incl. pilot-light phasing)
A50: Metric | B50: Value | C50: Note
A51: Deterministic base NPV (check vs Model tab) | B51: 27.014039 | C51: Should match Dashboard base NPV
A52: Mean NPV | B52: 11.823608 | C52: Rp billion
A53: P5 NPV (bad case) | B53: -19.41291 | C53: 1-in-20 downside
A54: Median NPV | B54: 11.708447
A55: P95 NPV (good case) | B55: 43.103322
A56: Probability NPV > 0 | B56: 0.7311 | C56: Headline for the financial slide
A57: Median full run-rate savings (Rp B/yr) | B57: 49.084413
A58: Median run-rate as % of conversion cost | B58: 0.087650737 | C58: vs 16% gap to benchmark
A60: TEST 2b. How should the roadmap spend the money? Same 10,000 runs, five strategies (gate = stop scaling if 2027 pilot adoption < 80%; happens in 25% of runs)
A61: Strategy | B61: Mean NPV | C61: P5 NPV | D61: Median NPV | E61: P95 NPV | F61: P(NPV > 0)
A62: A. Front-loaded phasing, no gate | B62: -0.19133229 | C62: -32.832551 | D62: -0.37372173 | E62: 32.504416 | F62: 0.4925
A63: B. Front-loaded phasing + gate (65% already spent) | B63: -3.7996789 | C63: -39.745907 | D63: -2.96235 | E63: 32.401945 | F63: 0.4518
A64: C. Pilot-light phasing, no gate (as in Model tab) | B64: 11.823608 | C64: -19.41291 | D64: 11.708447 | E64: 43.103322 | F64: 0.7311
A65: D. Pilot-light phasing + gate | B65: 15.0509 | C65: -8.4116268 | D65: 13.320402 | E65: 43.067723 | F65: 0.8595
A66: E. D + remaining equipment life valued at book | B66: 36.010535 | C66: 6.4767775 | D66: 36.960852 | E66: 67.48369 | F66: 0.9938
A67: F. D but savings ramp one year slower (stress test) | B67: -7.5342336 | C67: -31.899408 | D67: -5.5425073 | E67: 12.325501 | F67: 0.3242
A68: G. F + remaining equipment life valued at book | B68: 13.425401 | C68: -3.7787791 | D68: 11.927164 | E68: 35.124142 | F68: 0.879
A69: Pilot-light phasing: 10% / 15% / 40% / 25% / 10% of capex in 2026-2030. Ramp-up kept the same to isolate the effect of phasing; if scaling later also delays savings, the gain is smaller.
A70: Reading: a gate only protects value if little money is spent before it. Gate after heavy spending (B) destroys value; pilot-light + gate (D) is the design to defend in SQ3. Valuing equipment life beyond 2030 (E) is legitimate but state it openly. Stress test (F): if savings arrive a year late, P(NPV>0) falls to 32% (88% if remaining equipment life is valued, G). Speed of the pilot is the make-or-break factor: quick wins in 2026-27 belong in the roadmap.
A71: Ranges used (triangular low / mode / high): scrap 20/35/50%, maintenance 5/10/15%, NVA 15/30/45%, energy 2/5/8%, variant cost 20/35/50%, investment 60/80/110, running 8/9/12%, training 2/2.5/3, variant projects 2/3/5, cost per project 5/10/15, cash realization 30/50/70%, adoption 60/100/100%, labor share 35/40/45%.
A73: NPV distribution (histogram)
A74: NPV bin from (Rp B) | B74: Runs
A75: -51.6 | B75: 11
A76: -41.6 | B76: 73
A77: -31.5 | B77: 294
A78: -21.5 | B78: 700
A79: -11.5 | B79: 1367
A80: -1.4 | B80: 1920
A81: 8.6 | B81: 2028
A82: 18.6 | B82: 1753
A83: 28.6 | B83: 1056
A84: 38.7 | B84: 560
A85: 48.7 | B85: 182
A86: 58.7 | B86: 43
... A90: 98.9 | B90: 1
A92: TEST 3. Which assumption matters most? Tornado (base case, one at a time)
A93: Driver | B93: Low input | C93: High input | D93: NPV at low | E93: NPV at high | F93: Swing
A94: Investment (Rp B) | B94: 110 | C94: 60 | D94: -1.4979109 | E94: 46.022005 | F94: 47.519916
A95: Adoption achieved | B95: 0.6 | C95: 1 | D95: -17.99511 | E95: 27.014039 | F95: 45.009149
A96: Scrap reduction | B96: 0.2 | C96: 0.5 | D96: 7.3765393 | E96: 46.651538 | F96: 39.274999
A97: Variant projects / yr | B97: 2 | C97: 5 | D97: 18.831747 | E97: 43.378622 | F97: 24.546874
A98: Cost per variant project | B98: 5 | C98: 15 | D98: 14.740602 | E98: 39.287476 | F98: 24.546874
A99: Variant cost reduction | B99: 0.2 | C99: 0.5 | D99: 16.49395 | E99: 37.534128 | F99: 21.040178
A100: Operator NVA eliminated | B100: 0.15 | C100: 0.45 | D100: 18.373539 | E100: 35.654538 | F100: 17.280999
A101: Maintenance reduction | B101: 0.05 | C101: 0.15 | D101: 18.504456 | E101: 35.523622 | F101: 17.019166
A102: Energy reduction | B102: 0.02 | C102: 0.08 | D102: 22.301039 | E102: 31.727039 | F102: 9.4259997
A103: Running cost % | B103: 0.12 | C103: 0.08 | D103: 23.779625 | E103: 30.248453 | F103: 6.4688279
A104: Use the top 2-3 drivers as the assumptions you defend hardest in Q&A, and as the KPIs you track first in the pilot.

Sheet Simulation3
A1: Idea tests: simulation results (values produced by run_tests.py, not formulas)
A2: Re-run run_tests.py after changing assumptions. Process parameters below are illustrative assumptions, not TMMIN data: present them as a mechanism test, and show the sensitivity.
A4: TEST 1. Does closing the quality loop beat adding technology alone? (sealer drift -> inspection -> feedback, 1 year, 175,000 units, 300 runs)
A5: Scenario | B5: Defective units / yr | C5: Scrapped units / yr | D5: Escaped defects / yr | E5: Units built while drifting | F5: Scrap vs today | G5: Escapes vs today | H5: Scrap P5-P95
A6: 1. Today: visual at final inspection, manual feedback | B6: 4266.68 | C6: 1088.524 | D6: 638.26667 | E6: 15796.093 | F6: 0 | G6: 0 | H6: 835 - 1,365
A7: 2. Better camera at end-of-line only (tech, no loop) | B7: 4265.3233 | C7: 1215.776 | D7: 212.73667 | E7: 15793.257 | F7: 0.11690326 | G7: -0.66669626 | H7: 910 - 1,492
A8: 3. Closed loop at sealer, 31% of alerts dismissed (as today) | B8: 1652.95 | C8: 362.15367 | D8: 203.26 | E8: 5247.72 | F8: -0.66729841 | G8: -0.68154376 | H8: 216 - 543
A9: 4. Closed loop with people-centred design (10% dismissed) | B9: 908.32333 | C9: 166.86333 | D9: 88.006667 | E9: 2257.0067 | F9: -0.84670679 | G9: -0.86211615 | H9: 83 - 270
A11: What this shows
A12: - A better camera at end-of-line alone changes scrap by +12% while escapes fall 67%: it catches more bad units, but too late, so escapes turn into scrap. It does not prevent defects.
A13: - Closing the loop right after the sealer cuts scrap 85% and escapes 86%, because a drift is stopped within a few units instead of hundreds.
A14: - If operators dismiss alerts in 31% of drift episodes (today's override rate), scrap reduction falls to 67%. Trust, training and alert design are part of the value, not an add-on.
A15: - Plant-wide: if the pilot scope causes 40% of plant scrap (team assumption), the plant-wide scrap cut is about 34%. Compare with the 20% / 35% / 50% lever in Assumptions.
A16: - Deck message: value comes from redesigning the system (where the check sits, how fast the signal travels, who acts on it), not from buying the device. That is exactly the case ask.
A18: Process assumptions used (illustrative, change and re-run)
A19: Defect probability per unit, stable sealer | B19: 0.002
A20: Average units between drift events | B20: 5000
A21: Defect probability per unit while drifting | B21: 0.25
A22: Manual visual detection rate at final inspection | B22: 0.85
A23: Share of sealer defect modes the in-line AI camera can see | B23: 0.7
A24: Units between sealer and today's final inspection | B24: 300
A25: Units built before manual feedback reaches the sealer | B25: 150
A26: Share of late-found defects scrapped | B26: 0.3
A27: Share of early-found defects scrapped | B27: 0.05
A28: Share of plant scrap from the pilot scope (team assumption) | B28: 0.4
A29: In-line check: 5 units after sealer, automatic feedback within 10 units, 90% detection on visible defect modes (case: AI camera in validation to Oct 2026).
A31: Robustness: closed-loop (scenario 4) scrap reduction vs today when each assumption changes
A32: Assumption | B32: Low | C32: Reduction | D32: Base | E32: Reduction | F32: High | G32: Reduction
A33: AI camera coverage of defect modes | B33: 0.5 | C33: 0.8247043 | D33: 0.7 | E33: 0.84684226 | F33: 0.9 | G33: 0.86670882
A34: Drift defect rate | B34: 0.1 | C34: 0.8026018 | D34: 0.25 | E34: 0.84799063 | F34: 0.4 | G34: 0.86492434
A35: Units between drift events | B35: 2500 | C35: 0.86340745 | D35: 5000 | E35: 0.85825104 | F35: 10000 | G35: 0.83368165
A36: Late-found scrap share | B36: 0.15 | C36: 0.83146269 | D36: 0.3 | E36: 0.85387796 | F36: 0.5 | G36: 0.85017711
A37: Units from sealer to today's inspection | B37: 100 | C37: 0.81112305 | D37: 300 | E37: 0.8492534 | F37: 600 | G37: 0.87379761
A38: Lowest scrap reduction across all tested cases: 80%. The mechanism holds even with pessimistic process assumptions.
A40: People test: how much value is lost when operators dismiss alerts?
A41: Share of drift episodes where alerts are dismissed | B41: Scrap reduction vs today
A42: 0 | B42: 0.93929302
A43: 0.1 | B43: 0.84457608
A44: 0.2 | B44: 0.7497195
A45: 0.31 | B45: 0.64310602
A46: 0.5 | B46: 0.49641257
A47: Exhibit 6B says 31% of operators frequently override alerts today. This chart is the quantified case for the people part of the idea.
A49: TEST 2. Is the business case robust? Financial Monte Carlo (10,000 runs, mirrors the Model tab incl. pilot-light phasing)
A50: Metric | B50: Value | C50: Note
A51: Deterministic base NPV (check vs Model tab) | B51: 27.014039 | C51: Should match Dashboard base NPV
A52: Mean NPV | B52: 11.823608 | C52: Rp billion
A53: P5 NPV (bad case) | B53: -19.41291 | C53: 1-in-20 downside
A54: Median NPV | B54: 11.708447
A55: P95 NPV (good case) | B55: 43.103322
A56: Probability NPV > 0 | B56: 0.7311 | C56: Headline for the financial slide
A57: Median full run-rate savings (Rp B/yr) | B57: 49.084413
A58: Median run-rate as % of conversion cost | B58: 0.087650737 | C58: vs 16% gap to benchmark
A60: TEST 2b. How should the roadmap spend the money? Same 10,000 runs, five strategies (gate = stop scaling if 2027 pilot adoption < 80%; happens in 25% of runs)
A61: Strategy | B61: Mean NPV | C61: P5 NPV | D61: Median NPV | E61: P95 NPV | F61: P(NPV > 0)
A62: A. Front-loaded phasing, no gate | B62: -0.19133229 | C62: -32.832551 | D62: -0.37372173 | E62: 32.504416 | F62: 0.4925
A63: B. Front-loaded phasing + gate (65% already spent) | B63: -3.7996789 | C63: -39.745907 | D63: -2.96235 | E63: 32.401945 | F63: 0.4518
A64: C. Pilot-light phasing, no gate (as in Model tab) | B64: 11.823608 | C64: -19.41291 | D64: 11.708447 | E64: 43.103322 | F64: 0.7311
A65: D. Pilot-light phasing + gate | B65: 15.0509 | C65: -8.4116268 | D65: 13.320402 | E65: 43.067723 | F65: 0.8595
A66: E. D + remaining equipment life valued at book | B66: 36.010535 | C66: 6.4767775 | D66: 36.960852 | E66: 67.48369 | F66: 0.9938
A67: F. D but savings ramp one year slower (stress test) | B67: -7.5342336 | C67: -31.899408 | D67: -5.5425073 | E67: 12.325501 | F67: 0.3242
A68: G. F + remaining equipment life valued at book | B68: 13.425401 | C68: -3.7787791 | D68: 11.927164 | E68: 35.124142 | F68: 0.879
A69: Pilot-light phasing: 10% / 15% / 40% / 25% / 10% of capex in 2026-2030. Ramp-up kept the same to isolate the effect of phasing; if scaling later also delays savings, the gain is smaller.
A70: Reading: a gate only protects value if little money is spent before it. Gate after heavy spending (B) destroys value; pilot-light + gate (D) is the design to defend in SQ3. Valuing equipment life beyond 2030 (E) is legitimate but state it openly. Stress test (F): if savings arrive a year late, P(NPV>0) falls to 32% (88% if remaining equipment life is valued, G). Speed of the pilot is the make-or-break factor: quick wins in 2026-27 belong in the roadmap.
A71: Ranges used (triangular low / mode / high): scrap 20/35/50%, maintenance 5/10/15%, NVA 15/30/45%, energy 2/5/8%, variant cost 20/35/50%, investment 60/80/110, running 8/9/12%, training 2/2.5/3, variant projects 2/3/5, cost per project 5/10/15, cash realization 30/50/70%, adoption 60/100/100%, labor share 35/40/45%.
A73: NPV distribution (histogram)
A74: NPV bin from (Rp B) | B74: Runs
A75: -51.6 | B75: 11
A76: -41.6 | B76: 73
A77: -31.5 | B77: 294
A78: -21.5 | B78: 700
A79: -11.5 | B79: 1367
A80: -1.4 | B80: 1920
A81: 8.6 | B81: 2028
A82: 18.6 | B82: 1753
A83: 28.6 | B83: 1056
A84: 38.7 | B84: 560
A85: 48.7 | B85: 182
A86: 58.7 | B86: 43
... A90: 98.9 | B90: 1
A92: TEST 3. Which assumption matters most? Tornado (base case, one at a time)
A93: Driver | B93: Low input | C93: High input | D93: NPV at low | E93: NPV at high | F93: Swing
A94: Investment (Rp B) | B94: 110 | C94: 60 | D94: -1.4979109 | E94: 46.022005 | F94: 47.519916
A95: Adoption achieved | B95: 0.6 | C95: 1 | D95: -17.99511 | E95: 27.014039 | F95: 45.009149
A96: Scrap reduction | B96: 0.2 | C96: 0.5 | D96: 7.3765393 | E96: 46.651538 | F96: 39.274999
A97: Variant projects / yr | B97: 2 | C97: 5 | D97: 18.831747 | E97: 43.378622 | F97: 24.546874
A98: Cost per variant project | B98: 5 | C98: 15 | D98: 14.740602 | E98: 39.287476 | F98: 24.546874
A99: Variant cost reduction | B99: 0.2 | C99: 0.5 | D99: 16.49395 | E99: 37.534128 | F99: 21.040178
A100: Operator NVA eliminated | B100: 0.15 | C100: 0.45 | D100: 18.373539 | E100: 35.654538 | F100: 17.280999
A101: Maintenance reduction | B101: 0.05 | C101: 0.15 | D101: 18.504456 | E101: 35.523622 | F101: 17.019166
A102: Energy reduction | B102: 0.02 | C102: 0.08 | D102: 22.301039 | E102: 31.727039 | F102: 9.4259997
A103: Running cost % | B103: 0.12 | C103: 0.08 | D103: 23.779625 | E103: 30.248453 | F103: 6.4688279
A104: Use the top 2-3 drivers as the assumptions you defend hardest in Q&A, and as the KPIs you track first in the pilot.

Sheet Simulation2
A1: Idea tests: simulation results (values produced by run_tests.py, not formulas)
A2: Re-run run_tests.py after changing assumptions. Process parameters below are illustrative assumptions, not TMMIN data: present them as a mechanism test, and show the sensitivity.
A4: TEST 1. Does closing the quality loop beat adding technology alone? (sealer drift -> inspection -> feedback, 1 year, 175,000 units, 300 runs)
A5: Scenario | B5: Defective units / yr | C5: Scrapped units / yr | D5: Escaped defects / yr | E5: Units built while drifting | F5: Scrap vs today | G5: Escapes vs today | H5: Scrap P5-P95
A6: 1. Today: visual at final inspection, manual feedback | B6: 4266.68 | C6: 1088.524 | D6: 638.26667 | E6: 15796.093 | F6: 0 | G6: 0 | H6: 835 - 1,365
A7: 2. Better camera at end-of-line only (tech, no loop) | B7: 4265.3233 | C7: 1215.776 | D7: 212.73667 | E7: 15793.257 | F7: 0.11690326 | G7: -0.66669626 | H7: 910 - 1,492
A8: 3. Closed loop at sealer, 31% of alerts dismissed (as today) | B8: 1652.95 | C8: 362.15367 | D8: 203.26 | E8: 5247.72 | F8: -0.66729841 | G8: -0.68154376 | H8: 216 - 543
A9: 4. Closed loop with people-centred design (10% dismissed) | B9: 908.32333 | C9: 166.86333 | D9: 88.006667 | E9: 2257.0067 | F9: -0.84670679 | G9: -0.86211615 | H9: 83 - 270
A11: What this shows
A12: - A better camera at end-of-line alone changes scrap by +12% while escapes fall 67%: it catches more bad units, but too late, so escapes turn into scrap. It does not prevent defects.
A13: - Closing the loop right after the sealer cuts scrap 85% and escapes 86%, because a drift is stopped within a few units instead of hundreds.
A14: - If operators dismiss alerts in 31% of drift episodes (today's override rate), scrap reduction falls to 67%. Trust, training and alert design are part of the value, not an add-on.
A15: - Plant-wide: if the pilot scope causes 40% of plant scrap (team assumption), the plant-wide scrap cut is about 34%. Compare with the 20% / 35% / 50% lever in Assumptions.
A16: - Deck message: value comes from redesigning the system (where the check sits, how fast the signal travels, who acts on it), not from buying the device. That is exactly the case ask.
A18: Process assumptions used (illustrative, change and re-run)
A19: Defect probability per unit, stable sealer | B19: 0.002
A20: Average units between drift events | B20: 5000
A21: Defect probability per unit while drifting | B21: 0.25
A22: Manual visual detection rate at final inspection | B22: 0.85
A23: Share of sealer defect modes the in-line AI camera can see | B23: 0.7
A24: Units between sealer and today's final inspection | B24: 300
A25: Units built before manual feedback reaches the sealer | B25: 150
A26: Share of late-found defects scrapped | B26: 0.3
A27: Share of early-found defects scrapped | B27: 0.05
A28: Share of plant scrap from the pilot scope (team assumption) | B28: 0.4
A29: In-line check: 5 units after sealer, automatic feedback within 10 units, 90% detection on visible defect modes (case: AI camera in validation to Oct 2026).
A31: Robustness: closed-loop (scenario 4) scrap reduction vs today when each assumption changes
A32: Assumption | B32: Low | C32: Reduction | D32: Base | E32: Reduction | F32: High | G32: Reduction
A33: AI camera coverage of defect modes | B33: 0.5 | C33: 0.8247043 | D33: 0.7 | E33: 0.84684226 | F33: 0.9 | G33: 0.86670882
A34: Drift defect rate | B34: 0.1 | C34: 0.8026018 | D34: 0.25 | E34: 0.84799063 | F34: 0.4 | G34: 0.86492434
A35: Units between drift events | B35: 2500 | C35: 0.86340745 | D35: 5000 | E35: 0.85825104 | F35: 10000 | G35: 0.83368165
A36: Late-found scrap share | B36: 0.15 | C36: 0.83146269 | D36: 0.3 | E36: 0.85387796 | F36: 0.5 | G36: 0.85017711
A37: Units from sealer to today's inspection | B37: 100 | C37: 0.81112305 | D37: 300 | E37: 0.8492534 | F37: 600 | G37: 0.87379761
A38: Lowest scrap reduction across all tested cases: 80%. The mechanism holds even with pessimistic process assumptions.
A40: People test: how much value is lost when operators dismiss alerts?
A41: Share of drift episodes where alerts are dismissed | B41: Scrap reduction vs today
A42: 0 | B42: 0.93929302
A43: 0.1 | B43: 0.84457608
A44: 0.2 | B44: 0.7497195
A45: 0.31 | B45: 0.64310602
A46: 0.5 | B46: 0.49641257
A47: Exhibit 6B says 31% of operators frequently override alerts today. This chart is the quantified case for the people part of the idea.
A49: TEST 2. Is the business case robust? Financial Monte Carlo (10,000 runs, mirrors the Model tab incl. pilot-light phasing)
A50: Metric | B50: Value | C50: Note
A51: Deterministic base NPV (check vs Model tab) | B51: 27.014039 | C51: Should match Dashboard base NPV
A52: Mean NPV | B52: 11.823608 | C52: Rp billion
A53: P5 NPV (bad case) | B53: -19.41291 | C53: 1-in-20 downside
A54: Median NPV | B54: 11.708447
A55: P95 NPV (good case) | B55: 43.103322
A56: Probability NPV > 0 | B56: 0.7311 | C56: Headline for the financial slide
A57: Median full run-rate savings (Rp B/yr) | B57: 49.084413
A58: Median run-rate as % of conversion cost | B58: 0.087650737 | C58: vs 16% gap to benchmark
A60: TEST 2b. How should the roadmap spend the money? Same 10,000 runs, five strategies (gate = stop scaling if 2027 pilot adoption < 80%; happens in 25% of runs)
A61: Strategy | B61: Mean NPV | C61: P5 NPV | D61: Median NPV | E61: P95 NPV | F61: P(NPV > 0)
A62: A. Front-loaded phasing, no gate | B62: -0.19133229 | C62: -32.832551 | D62: -0.37372173 | E62: 32.504416 | F62: 0.4925
A63: B. Front-loaded phasing + gate (65% already spent) | B63: -3.7996789 | C63: -39.745907 | D63: -2.96235 | E63: 32.401945 | F63: 0.4518
A64: C. Pilot-light phasing, no gate (as in Model tab) | B64: 11.823608 | C64: -19.41291 | D64: 11.708447 | E64: 43.103322 | F64: 0.7311
A65: D. Pilot-light phasing + gate | B65: 15.0509 | C65: -8.4116268 | D65: 13.320402 | E65: 43.067723 | F65: 0.8595
A66: E. D + remaining equipment life valued at book | B66: 36.010535 | C66: 6.4767775 | D66: 36.960852 | E66: 67.48369 | F66: 0.9938
A67: F. D but savings ramp one year slower (stress test) | B67: -7.5342336 | C67: -31.899408 | D67: -5.5425073 | E67: 12.325501 | F67: 0.3242
A68: G. F + remaining equipment life valued at book | B68: 13.425401 | C68: -3.7787791 | D68: 11.927164 | E68: 35.124142 | F68: 0.879
A69: Pilot-light phasing: 10% / 15% / 40% / 25% / 10% of capex in 2026-2030. Ramp-up kept the same to isolate the effect of phasing; if scaling later also delays savings, the gain is smaller.
A70: Reading: a gate only protects value if little money is spent before it. Gate after heavy spending (B) destroys value; pilot-light + gate (D) is the design to defend in SQ3. Valuing equipment life beyond 2030 (E) is legitimate but state it openly. Stress test (F): if savings arrive a year late, P(NPV>0) falls to 32% (88% if remaining equipment life is valued, G). Speed of the pilot is the make-or-break factor: quick wins in 2026-27 belong in the roadmap.
A71: Ranges used (triangular low / mode / high): scrap 20/35/50%, maintenance 5/10/15%, NVA 15/30/45%, energy 2/5/8%, variant cost 20/35/50%, investment 60/80/110, running 8/9/12%, training 2/2.5/3, variant projects 2/3/5, cost per project 5/10/15, cash realization 30/50/70%, adoption 60/100/100%, labor share 35/40/45%.
A73: NPV distribution (histogram)
A74: NPV bin from (Rp B) | B74: Runs
A75: -51.6 | B75: 11
A76: -41.6 | B76: 73
A77: -31.5 | B77: 294
A78: -21.5 | B78: 700
A79: -11.5 | B79: 1367
A80: -1.4 | B80: 1920
A81: 8.6 | B81: 2028
A82: 18.6 | B82: 1753
A83: 28.6 | B83: 1056
A84: 38.7 | B84: 560
A85: 48.7 | B85: 182
A86: 58.7 | B86: 43
... A90: 98.9 | B90: 1
A92: TEST 3. Which assumption matters most? Tornado (base case, one at a time)
A93: Driver | B93: Low input | C93: High input | D93: NPV at low | E93: NPV at high | F93: Swing
A94: Investment (Rp B) | B94: 110 | C94: 60 | D94: -1.4979109 | E94: 46.022005 | F94: 47.519916
A95: Adoption achieved | B95: 0.6 | C95: 1 | D95: -17.99511 | E95: 27.014039 | F95: 45.009149
A96: Scrap reduction | B96: 0.2 | C96: 0.5 | D96: 7.3765393 | E96: 46.651538 | F96: 39.274999
A97: Variant projects / yr | B97: 2 | C97: 5 | D97: 18.831747 | E97: 43.378622 | F97: 24.546874
A98: Cost per variant project | B98: 5 | C98: 15 | D98: 14.740602 | E98: 39.287476 | F98: 24.546874
A99: Variant cost reduction | B99: 0.2 | C99: 0.5 | D99: 16.49395 | E99: 37.534128 | F99: 21.040178
A100: Operator NVA eliminated | B100: 0.15 | C100: 0.45 | D100: 18.373539 | E100: 35.654538 | F100: 17.280999
A101: Maintenance reduction | B101: 0.05 | C101: 0.15 | D101: 18.504456 | E101: 35.523622 | F101: 17.019166
A102: Energy reduction | B102: 0.02 | C102: 0.08 | D102: 22.301039 | E102: 31.727039 | F102: 9.4259997
A103: Running cost % | B103: 0.12 | C103: 0.08 | D103: 23.779625 | E103: 30.248453 | F103: 6.4688279
A104: Use the top 2-3 drivers as the assumptions you defend hardest in Q&A, and as the KPIs you track first in the pilot.

Sheet Simulation1
A1: Idea tests: simulation results (values produced by run_tests.py, not formulas)
A2: Re-run run_tests.py after changing assumptions. Process parameters below are illustrative assumptions, not TMMIN data: present them as a mechanism test, and show the sensitivity.
A4: TEST 1. Does closing the quality loop beat adding technology alone? (sealer drift -> inspection -> feedback, 1 year, 175,000 units, 300 runs)
A5: Scenario | B5: Defective units / yr | C5: Scrapped units / yr | D5: Escaped defects / yr | E5: Units built while drifting | F5: Scrap vs today | G5: Escapes vs today | H5: Scrap P5-P95
A6: 1. Today: visual at final inspection, manual feedback | B6: 4266.68 | C6: 1088.524 | D6: 638.26667 | E6: 15796.093 | F6: 0 | G6: 0 | H6: 835 - 1,365
A7: 2. Better camera at end-of-line only (tech, no loop) | B7: 4265.3233 | C7: 1215.776 | D7: 212.73667 | E7: 15793.257 | F7: 0.11690326 | G7: -0.66669626 | H7: 910 - 1,492
A8: 3. Closed loop at sealer, 31% of alerts dismissed (as today) | B8: 1652.95 | C8: 362.15367 | D8: 203.26 | E8: 5247.72 | F8: -0.66729841 | G8: -0.68154376 | H8: 216 - 543
A9: 4. Closed loop with people-centred design (10% dismissed) | B9: 908.32333 | C9: 166.86333 | D9: 88.006667 | E9: 2257.0067 | F9: -0.84670679 | G9: -0.86211615 | H9: 83 - 270
A11: What this shows
A12: - A better camera at end-of-line alone changes scrap by +12% while escapes fall 67%: it catches more bad units, but too late, so escapes turn into scrap. It does not prevent defects.
A13: - Closing the loop right after the sealer cuts scrap 85% and escapes 86%, because a drift is stopped within a few units instead of hundreds.
A14: - If operators dismiss alerts in 31% of drift episodes (today's override rate), scrap reduction falls to 67%. Trust, training and alert design are part of the value, not an add-on.
A15: - Plant-wide: if the pilot scope causes 40% of plant scrap (team assumption), the plant-wide scrap cut is about 34%. Compare with the 20% / 35% / 50% lever in Assumptions.
A16: - Deck message: value comes from redesigning the system (where the check sits, how fast the signal travels, who acts on it), not from buying the device. That is exactly the case ask.
A18: Process assumptions used (illustrative, change and re-run)
A19: Defect probability per unit, stable sealer | B19: 0.002
A20: Average units between drift events | B20: 5000
A21: Defect probability per unit while drifting | B21: 0.25
A22: Manual visual detection rate at final inspection | B22: 0.85
A23: Share of sealer defect modes the in-line AI camera can see | B23: 0.7
A24: Units between sealer and today's final inspection | B24: 300
A25: Units built before manual feedback reaches the sealer | B25: 150
A26: Share of late-found defects scrapped | B26: 0.3
A27: Share of early-found defects scrapped | B27: 0.05
A28: Share of plant scrap from the pilot scope (team assumption) | B28: 0.4
A29: In-line check: 5 units after sealer, automatic feedback within 10 units, 90% detection on visible defect modes (case: AI camera in validation to Oct 2026).
A31: Robustness: closed-loop (scenario 4) scrap reduction vs today when each assumption changes
A32: Assumption | B32: Low | C32: Reduction | D32: Base | E32: Reduction | F32: High | G32: Reduction
A33: AI camera coverage of defect modes | B33: 0.5 | C33: 0.8247043 | D33: 0.7 | E33: 0.84684226 | F33: 0.9 | G33: 0.86670882
A34: Drift defect rate | B34: 0.1 | C34: 0.8026018 | D34: 0.25 | E34: 0.84799063 | F34: 0.4 | G34: 0.86492434
A35: Units between drift events | B35: 2500 | C35: 0.86340745 | D35: 5000 | E35: 0.85825104 | F35: 10000 | G35: 0.83368165
A36: Late-found scrap share | B36: 0.15 | C36: 0.83146269 | D36: 0.3 | E36: 0.85387796 | F36: 0.5 | G36: 0.85017711
A37: Units from sealer to today's inspection | B37: 100 | C37: 0.81112305 | D37: 300 | E37: 0.8492534 | F37: 600 | G37: 0.87379761
A38: Lowest scrap reduction across all tested cases: 80%. The mechanism holds even with pessimistic process assumptions.
A40: People test: how much value is lost when operators dismiss alerts?
A41: Share of drift episodes where alerts are dismissed | B41: Scrap reduction vs today
A42: 0 | B42: 0.93929302
A43: 0.1 | B43: 0.84457608
A44: 0.2 | B44: 0.7497195
A45: 0.31 | B45: 0.64310602
A46: 0.5 | B46: 0.49641257
A47: Exhibit 6B says 31% of operators frequently override alerts today. This chart is the quantified case for the people part of the idea.
A49: TEST 2. Is the business case robust? Financial Monte Carlo (10,000 runs, mirrors the Model tab incl. pilot-light phasing)
A50: Metric | B50: Value | C50: Note
A51: Deterministic base NPV (check vs Model tab) | B51: 27.014039 | C51: Should match Dashboard base NPV
A52: Mean NPV | B52: 11.823608 | C52: Rp billion
A53: P5 NPV (bad case) | B53: -19.41291 | C53: 1-in-20 downside
A54: Median NPV | B54: 11.708447
A55: P95 NPV (good case) | B55: 43.103322
A56: Probability NPV > 0 | B56: 0.7311 | C56: Headline for the financial slide
A57: Median full run-rate savings (Rp B/yr) | B57: 49.084413
A58: Median run-rate as % of conversion cost | B58: 0.087650737 | C58: vs 16% gap to benchmark
A60: TEST 2b. How should the roadmap spend the money? Same 10,000 runs, five strategies (gate = stop scaling if 2027 pilot adoption < 80%; happens in 25% of runs)
A61: Strategy | B61: Mean NPV | C61: P5 NPV | D61: Median NPV | E61: P95 NPV | F61: P(NPV > 0)
A62: A. Front-loaded phasing, no gate | B62: -0.19133229 | C62: -32.832551 | D62: -0.37372173 | E62: 32.504416 | F62: 0.4925
A63: B. Front-loaded phasing + gate (65% already spent) | B63: -3.7996789 | C63: -39.745907 | D63: -2.96235 | E63: 32.401945 | F63: 0.4518
A64: C. Pilot-light phasing, no gate (as in Model tab) | B64: 11.823608 | C64: -19.41291 | D64: 11.708447 | E64: 43.103322 | F64: 0.7311
A65: D. Pilot-light phasing + gate | B65: 15.0509 | C65: -8.4116268 | D65: 13.320402 | E65: 43.067723 | F65: 0.8595
A66: E. D + remaining equipment life valued at book | B66: 36.010535 | C66: 6.4767775 | D66: 36.960852 | E66: 67.48369 | F66: 0.9938
A67: F. D but savings ramp one year slower (stress test) | B67: -7.5342336 | C67: -31.899408 | D67: -5.5425073 | E67: 12.325501 | F67: 0.3242
A68: G. F + remaining equipment life valued at book | B68: 13.425401 | C68: -3.7787791 | D68: 11.927164 | E68: 35.124142 | F68: 0.879
A69: Pilot-light phasing: 10% / 15% / 40% / 25% / 10% of capex in 2026-2030. Ramp-up kept the same to isolate the effect of phasing; if scaling later also delays savings, the gain is smaller.
A70: Reading: a gate only protects value if little money is spent before it. Gate after heavy spending (B) destroys value; pilot-light + gate (D) is the design to defend in SQ3. Valuing equipment life beyond 2030 (E) is legitimate but state it openly. Stress test (F): if savings arrive a year late, P(NPV>0) falls to 32% (88% if remaining equipment life is valued, G). Speed of the pilot is the make-or-break factor: quick wins in 2026-27 belong in the roadmap.
A71: Ranges used (triangular low / mode / high): scrap 20/35/50%, maintenance 5/10/15%, NVA 15/30/45%, energy 2/5/8%, variant cost 20/35/50%, investment 60/80/110, running 8/9/12%, training 2/2.5/3, variant projects 2/3/5, cost per project 5/10/15, cash realization 30/50/70%, adoption 60/100/100%, labor share 35/40/45%.
A73: NPV distribution (histogram)
A74: NPV bin from (Rp B) | B74: Runs
A75: -51.6 | B75: 11
A76: -41.6 | B76: 73
A77: -31.5 | B77: 294
A78: -21.5 | B78: 700
A79: -11.5 | B79: 1367
A80: -1.4 | B80: 1920
A81: 8.6 | B81: 2028
A82: 18.6 | B82: 1753
A83: 28.6 | B83: 1056
A84: 38.7 | B84: 560
A85: 48.7 | B85: 182
A86: 58.7 | B86: 43
... A90: 98.9 | B90: 1
A92: TEST 3. Which assumption matters most? Tornado (base case, one at a time)
A93: Driver | B93: Low input | C93: High input | D93: NPV at low | E93: NPV at high | F93: Swing
A94: Investment (Rp B) | B94: 110 | C94: 60 | D94: -1.4979109 | E94: 46.022005 | F94: 47.519916
A95: Adoption achieved | B95: 0.6 | C95: 1 | D95: -17.99511 | E95: 27.014039 | F95: 45.009149
A96: Scrap reduction | B96: 0.2 | C96: 0.5 | D96: 7.3765393 | E96: 46.651538 | F96: 39.274999
A97: Variant projects / yr | B97: 2 | C97: 5 | D97: 18.831747 | E97: 43.378622 | F97: 24.546874
A98: Cost per variant project | B98: 5 | C98: 15 | D98: 14.740602 | E98: 39.287476 | F98: 24.546874
A99: Variant cost reduction | B99: 0.2 | C99: 0.5 | D99: 16.49395 | E99: 37.534128 | F99: 21.040178
A100: Operator NVA eliminated | B100: 0.15 | C100: 0.45 | D100: 18.373539 | E100: 35.654538 | F100: 17.280999
A101: Maintenance reduction | B101: 0.05 | C101: 0.15 | D101: 18.504456 | E101: 35.523622 | F101: 17.019166
A102: Energy reduction | B102: 0.02 | C102: 0.08 | D102: 22.301039 | E102: 31.727039 | F102: 9.4259997
A103: Running cost % | B103: 0.12 | C103: 0.08 | D103: 23.779625 | E103: 30.248453 | F103: 6.4688279
A104: Use the top 2-3 drivers as the assumptions you defend hardest in Q&A, and as the KPIs you track first in the pilot.

Sheet Simulation
A1: Idea tests: simulation results (values produced by run_tests.py, not formulas)
A2: Re-run run_tests.py after changing assumptions. Process parameters below are illustrative assumptions, not TMMIN data: present them as a mechanism test, and show the sensitivity.
A4: TEST 1. Does closing the quality loop beat adding technology alone? (sealer drift -> inspection -> feedback, 1 year, 175,000 units, 300 runs)
A5: Scenario | B5: Defective units / yr | C5: Scrapped units / yr | D5: Escaped defects / yr | E5: Units built while drifting | F5: Scrap vs today | G5: Escapes vs today | H5: Scrap P5-P95
A6: 1. Today: visual at final inspection, manual feedback | B6: 4266.68 | C6: 1088.524 | D6: 638.26667 | E6: 15796.093 | F6: 0 | G6: 0 | H6: 835 - 1,365
A7: 2. Better camera at end-of-line only (tech, no loop) | B7: 4265.3233 | C7: 1215.776 | D7: 212.73667 | E7: 15793.257 | F7: 0.11690326 | G7: -0.66669626 | H7: 910 - 1,492
A8: 3. Closed loop at sealer, 31% of alerts dismissed (as today) | B8: 1652.95 | C8: 362.15367 | D8: 203.26 | E8: 5247.72 | F8: -0.66729841 | G8: -0.68154376 | H8: 216 - 543
A9: 4. Closed loop with people-centred design (10% dismissed) | B9: 908.32333 | C9: 166.86333 | D9: 88.006667 | E9: 2257.0067 | F9: -0.84670679 | G9: -0.86211615 | H9: 83 - 270
A11: What this shows
A12: - A better camera at end-of-line alone changes scrap by +12% while escapes fall 67%: it catches more bad units, but too late, so escapes turn into scrap. It does not prevent defects.
A13: - Closing the loop right after the sealer cuts scrap 85% and escapes 86%, because a drift is stopped within a few units instead of hundreds.
A14: - If operators dismiss alerts in 31% of drift episodes (today's override rate), scrap reduction falls to 67%. Trust, training and alert design are part of the value, not an add-on.
A15: - Plant-wide: if the pilot scope causes 40% of plant scrap (team assumption), the plant-wide scrap cut is about 34%. Compare with the 20% / 35% / 50% lever in Assumptions.
A16: - Deck message: value comes from redesigning the system (where the check sits, how fast the signal travels, who acts on it), not from buying the device. That is exactly the case ask.
A18: Process assumptions used (illustrative, change and re-run)
A19: Defect probability per unit, stable sealer | B19: 0.002
A20: Average units between drift events | B20: 5000
A21: Defect probability per unit while drifting | B21: 0.25
A22: Manual visual detection rate at final inspection | B22: 0.85
A23: Share of sealer defect modes the in-line AI camera can see | B23: 0.7
A24: Units between sealer and today's final inspection | B24: 300
A25: Units built before manual feedback reaches the sealer | B25: 150
A26: Share of late-found defects scrapped | B26: 0.3
A27: Share of early-found defects scrapped | B27: 0.05
A28: Share of plant scrap from the pilot scope (team assumption) | B28: 0.4
A29: In-line check: 5 units after sealer, automatic feedback within 10 units, 90% detection on visible defect modes (case: AI camera in validation to Oct 2026).
A31: Robustness: closed-loop (scenario 4) scrap reduction vs today when each assumption changes
A32: Assumption | B32: Low | C32: Reduction | D32: Base | E32: Reduction | F32: High | G32: Reduction
A33: AI camera coverage of defect modes | B33: 0.5 | C33: 0.8247043 | D33: 0.7 | E33: 0.84684226 | F33: 0.9 | G33: 0.86670882
A34: Drift defect rate | B34: 0.1 | C34: 0.8026018 | D34: 0.25 | E34: 0.84799063 | F34: 0.4 | G34: 0.86492434
A35: Units between drift events | B35: 2500 | C35: 0.86340745 | D35: 5000 | E35: 0.85825104 | F35: 10000 | G35: 0.83368165
A36: Late-found scrap share | B36: 0.15 | C36: 0.83146269 | D36: 0.3 | E36: 0.85387796 | F36: 0.5 | G36: 0.85017711
A37: Units from sealer to today's inspection | B37: 100 | C37: 0.81112305 | D37: 300 | E37: 0.8492534 | F37: 600 | G37: 0.87379761
A38: Lowest scrap reduction across all tested cases: 80%. The mechanism holds even with pessimistic process assumptions.
A40: People test: how much value is lost when operators dismiss alerts?
A41: Share of drift episodes where alerts are dismissed | B41: Scrap reduction vs today
A42: 0 | B42: 0.93929302
A43: 0.1 | B43: 0.84457608
A44: 0.2 | B44: 0.7497195
A45: 0.31 | B45: 0.64310602
A46: 0.5 | B46: 0.49641257
A47: Exhibit 6B says 31% of operators frequently override alerts today. This chart is the quantified case for the people part of the idea.
A49: TEST 2. Is the business case robust? Financial Monte Carlo (10,000 runs, mirrors the Model tab incl. pilot-light phasing)
A50: Metric | B50: Value | C50: Note
A51: Deterministic base NPV (check vs Model tab) | B51: 27.014039 | C51: Should match Dashboard base NPV
A52: Mean NPV | B52: 11.823608 | C52: Rp billion
A53: P5 NPV (bad case) | B53: -19.41291 | C53: 1-in-20 downside
A54: Median NPV | B54: 11.708447
A55: P95 NPV (good case) | B55: 43.103322
A56: Probability NPV > 0 | B56: 0.7311 | C56: Headline for the financial slide
A57: Median full run-rate savings (Rp B/yr) | B57: 49.084413
A58: Median run-rate as % of conversion cost | B58: 0.087650737 | C58: vs 16% gap to benchmark
A60: TEST 2b. How should the roadmap spend the money? Same 10,000 runs, five strategies (gate = stop scaling if 2027 pilot adoption < 80%; happens in 25% of runs)
A61: Strategy | B61: Mean NPV | C61: P5 NPV | D61: Median NPV | E61: P95 NPV | F61: P(NPV > 0)
A62: A. Front-loaded phasing, no gate | B62: -0.19133229 | C62: -32.832551 | D62: -0.37372173 | E62: 32.504416 | F62: 0.4925
A63: B. Front-loaded phasing + gate (65% already spent) | B63: -3.7996789 | C63: -39.745907 | D63: -2.96235 | E63: 32.401945 | F63: 0.4518
A64: C. Pilot-light phasing, no gate (as in Model tab) | B64: 11.823608 | C64: -19.41291 | D64: 11.708447 | E64: 43.103322 | F64: 0.7311
A65: D. Pilot-light phasing + gate | B65: 15.0509 | C65: -8.4116268 | D65: 13.320402 | E65: 43.067723 | F65: 0.8595
A66: E. D + remaining equipment life valued at book | B66: 36.010535 | C66: 6.4767775 | D66: 36.960852 | E66: 67.48369 | F66: 0.9938
A67: F. D but savings ramp one year slower (stress test) | B67: -7.5342336 | C67: -31.899408 | D67: -5.5425073 | E67: 12.325501 | F67: 0.3242
A68: G. F + remaining equipment life valued at book | B68: 13.425401 | C68: -3.7787791 | D68: 11.927164 | E68: 35.124142 | F68: 0.879
A69: Pilot-light phasing: 10% / 15% / 40% / 25% / 10% of capex in 2026-2030. Ramp-up kept the same to isolate the effect of phasing; if scaling later also delays savings, the gain is smaller.
A70: Reading: a gate only protects value if little money is spent before it. Gate after heavy spending (B) destroys value; pilot-light + gate (D) is the design to defend in SQ3. Valuing equipment life beyond 2030 (E) is legitimate but state it openly. Stress test (F): if savings arrive a year late, P(NPV>0) falls to 32% (88% if remaining equipment life is valued, G). Speed of the pilot is the make-or-break factor: quick wins in 2026-27 belong in the roadmap.
A71: Ranges used (triangular low / mode / high): scrap 20/35/50%, maintenance 5/10/15%, NVA 15/30/45%, energy 2/5/8%, variant cost 20/35/50%, investment 60/80/110, running 8/9/12%, training 2/2.5/3, variant projects 2/3/5, cost per project 5/10/15, cash realization 30/50/70%, adoption 60/100/100%, labor share 35/40/45%.
A73: NPV distribution (histogram)
A74: NPV bin from (Rp B) | B74: Runs
A75: -51.6 | B75: 11
A76: -41.6 | B76: 73
A77: -31.5 | B77: 294
A78: -21.5 | B78: 700
A79: -11.5 | B79: 1367
A80: -1.4 | B80: 1920
A81: 8.6 | B81: 2028
A82: 18.6 | B82: 1753
A83: 28.6 | B83: 1056
A84: 38.7 | B84: 560
A85: 48.7 | B85: 182
A86: 58.7 | B86: 43
... A90: 98.9 | B90: 1
A92: TEST 3. Which assumption matters most? Tornado (base case, one at a time)
A93: Driver | B93: Low input | C93: High input | D93: NPV at low | E93: NPV at high | F93: Swing
A94: Investment (Rp B) | B94: 110 | C94: 60 | D94: -1.4979109 | E94: 46.022005 | F94: 47.519916
A95: Adoption achieved | B95: 0.6 | C95: 1 | D95: -17.99511 | E95: 27.014039 | F95: 45.009149
A96: Scrap reduction | B96: 0.2 | C96: 0.5 | D96: 7.3765393 | E96: 46.651538 | F96: 39.274999
A97: Variant projects / yr | B97: 2 | C97: 5 | D97: 18.831747 | E97: 43.378622 | F97: 24.546874
A98: Cost per variant project | B98: 5 | C98: 15 | D98: 14.740602 | E98: 39.287476 | F98: 24.546874
A99: Variant cost reduction | B99: 0.2 | C99: 0.5 | D99: 16.49395 | E99: 37.534128 | F99: 21.040178
A100: Operator NVA eliminated | B100: 0.15 | C100: 0.45 | D100: 18.373539 | E100: 35.654538 | F100: 17.280999
A101: Maintenance reduction | B101: 0.05 | C101: 0.15 | D101: 18.504456 | E101: 35.523622 | F101: 17.019166
A102: Energy reduction | B102: 0.02 | C102: 0.08 | D102: 22.301039 | E102: 31.727039 | F102: 9.4259997
A103: Running cost % | B103: 0.12 | C103: 0.08 | D103: 23.779625 | E103: 30.248453 | F103: 6.4688279
A104: Use the top 2-3 drivers as the assumptions you defend hardest in Q&A, and as the KPIs you track first in the pilot.

Sheet Exhibits
A1: Case exhibits, re-typed (verify red cells against the PDF)
A3: Exhibit 1. National car sales (units)
A4: Metric | B4: 2024 | C4: 2025 | D4: Change
A5: Wholesales | B5: 865723 | C5: 803687 | D5: =C5/B5-1
A6: Retail sales | B6: 889680 | C6: 833692 | D6: =C6/B6-1
A8: Exhibit 3. Conversion cost index, Karawang (TMMIN 2023 = 100)
A9: Year | B9: TMMIN | C9: New-player benchmark | D9: TMMIN vs benchmark
A10: 2023 | B10: 100 | C10: 94 | D10: =B10/C10-1
A11: 2024 | B11: 103 | C11: 91 | D11: =B11/C11-1
A12: 2025 | B12: 106 | C12: 89 | D12: =B12/C12-1
A14: Exhibit 4. Quality & productivity baseline (index 2023 = 100 unless stated)
A15: Metric | B15: 2023 | C15: 2025 | D15: Note
A16: Scrap (index) | B16: 100 | C16: 108 | D16: Verified from casebook PDF
A17: Unplanned downtime (index) | B17: 100 | C17: 111 | D17: Verified from casebook PDF
A18: Defects escaping to downstream (index) | B18: 100 | C18: 103 | D18: Verified from casebook PDF
A19: Operator non-value-added time (% hours) | B19: 0.2 | C19: 0.22 | D19: Verified from casebook PDF
A20: Equipment modification time, new variant (months) | B20: 8 | C20: 9 | D20: Verified from casebook PDF
A22: Exhibit 5. Automation maturity (1 manual, 2 semi-auto, 3 auto+integrated, 4 autonomous)
A23: Process | B23: Level | C23: Gap to L4 | D23: Key condition
A24: Press shop | B24: 3 | C24: =4-B24 | D24: Die changes and panel quality checks rely on operators
A25: Casting | B25: 2 | C25: =4-B25 | D25: Finishing, handling, inspection partly manual
A26: Machining & engine assembly | B26: 3 | C26: =4-B26 | D26: Assembly and inspection partly manual
A27: Body welding: spot welding | B27: 3 | C27: =4-B27 | D27: Programmed robots integrated in line
A28: Body welding: sealer application | B28: 2 | C28: =4-B28 | D28: Manual/semi-auto; no automatic quality feedback
A29: Painting | B29: 3 | C29: =4-B29 | D29: Quality check and defect repair manual visual
A30: Final assembly | B30: 2 | C30: =4-B30 | D30: Manual with tools; high variant mix handled by operators
A31: Quality inspection | B31: 1 | C31: =4-B31 | D31: Manual visual; in-house AI camera (from CCTV) in validation to Oct 2026
A32: Intralogistics | B32: 2 | C32: =4-B32 | D32: Manual forklifts/dollies; AGV/AMR pilots
A33: Maintenance | B33: 2 | C33: =4-B33 | D33: Periodic preventive, not predictive
A34: Equipment & system integration | B34: 2 | C34: =4-B34 | D34: Point-to-point; no common interface standard
A35: Data integration | B35: 1 | C35: =4-B35 | D35: Data scattered; equipment, quality, logistics not connected
A37: Exhibit 6A. Engineering time, knowledge & improvement (production engineering)
A38: Metric | B38: 2023 | C38: 2025 | D38: Note
A39: Engineer time on routine support & troubleshooting (%) | B39: 0.62 | C39: 0.65 | D39: Verified; the remaining ~10% is other work
A40: Engineer time on improvement & new development (%) | B40: 0.28 | C40: 0.25
A41: Critical know-how documented in shared form (%) | B41: 0.35 | C41: 0.33
A42: Critical processes whose know-how rests with 1-2 seniors (%) | B42: 0.45 | C42: 0.48
A43: Months for new engineer to work independently | B43: 14 | C43: 15
A44: Improvement ideas per engineer per year | B44: 3.1 | C44: 2.4
A45: Ideas implemented (% of submitted) | B45: 0.35 | C45: 0.28
A47: Exhibit 6B. Operator & team-leader perception, pilot area (2025, N = 120)
A48: Indicator | B48: Share | D48: So what
A49: Say new tech helps rather than replaces their work | B49: 0.54 | D49: 46% are not convinced: change management is a real risk
A50: Have received training on data-driven tools | B50: 0.18 | D50: Training gap is the biggest adoption blocker
A51: Frequently override or ignore automated alerts | B51: 0.31 | D51: Tech without trust = no value; design alerts with operators
A52: Know-how shared mainly via informal on-the-job coaching | B52: 0.71 | D52: Supports knowledge-capture idea
A53: Would contribute ideas if an easy channel existed | B53: 0.62 | D53: Latent kaizen energy: biggest people opportunity
A55: Exhibit 7. Engineering competence (members per level, N = 30 per field)
A56: Field | B56: L1 basic | C56: L2 intermediate | D56: L3 proficient | E56: L4 expert | F56: Total | G56: % at L3+
A57: Mechanical | B57: 3 | C57: 8 | D57: 14 | E57: 5 | F57: =SUM(B57:E57) | G57: =(D57+E57)/F57
A58: Electrical | B58: 5 | C58: 10 | D58: 11 | E58: 4 | F58: =SUM(B58:E58) | G58: =(D58+E58)/F58
A59: PLC | B59: 7 | C59: 11 | D59: 9 | E59: 3 | F59: =SUM(B59:E59) | G59: =(D59+E59)/F59
A60: Programming | B60: 14 | C60: 10 | D60: 5 | E60: 1 | F60: =SUM(B60:E60) | G60: =(D60+E60)/F60
A61: Software & AI | B61: 20 | C61: 8 | D61: 2 | E61: 0 | F61: =SUM(B61:E61) | G61: =(D61+E61)/F61
A62: Verified from casebook PDF
A64: Exhibit 8. Volume share by pathway (indicative)
A65: Pathway | B65: 2026 | C65: 2030 moderate | D65: 2030 aggressive
A66: Conventional (ICE) | B66: 0.7 | C66: 0.45 | D66: 0.3
A67: HEV | B67: 0.25 | C67: 0.38 | D67: 0.4
A68: PHEV | B68: 0.03 | C68: 0.07 | D68: 0.1
A69: BEV | B69: 0.02 | C69: 0.1 | D69: 0.2
A70: Electrified share (HEV+PHEV+BEV) | B70: =SUM(B67:B69) | C70: =SUM(C67:C69) | D70: =SUM(D67:D69)
A72: Exhibit 9 parameters are in the Assumptions tab (rows 4-15).

Sheet Assumptions
A1: Model inputs
A3: Case parameter (Exhibit 9 / text) | B3: Value | C3: Unit | D3: Source / note
A4: Installed capacity, Karawang I + II | B4: 250000 | C4: units/yr | D4: Exhibit 9
A5: Capacity utilization 2025 | B5: 0.7 | C5: % | D5: Exhibit 9
A6: Production volume | B6: =B4*B5 | C6: units/yr | D6: Formula (case: ~175,000)
A7: Conversion cost per unit 2025 | B7: 3.2 | C7: Rp million | D7: Exhibit 9 (labor, energy, maintenance, depreciation, scrap)
A8: Total annual conversion cost | B8: =B6*B7/1000 | C8: Rp billion | D8: Formula (case: ~Rp560B)
A9: Discount rate | B9: 0.1 | C9: %/yr | D9: Exhibit 9
A10: Labor & energy cost escalation | B10: 0.04 | C10: %/yr | D10: Exhibit 9, applied to savings
A11: Technology economic life | B11: 5 | C11: years | D11: Exhibit 9
A12: TMMIN conversion cost index 2025 | B12: 106 | C12: index | D12: Exhibit 3
A13: New-player benchmark index 2025 | B13: 89 | C13: index | D13: Exhibit 3
A14: Operator non-value-added time | B14: 0.22 | C14: % hours | D14: Exhibit 4 / text
A15: Equipment modification time per new variant | B15: 9 | C15: months | D15: Exhibit 4 / text
A17: Conversion cost split (TEAM ASSUMPTION, case gives components only) | B17: Share | C17: Rp billion | D17: Justify with
A18: Labor | B18: 0.4 | C18: =B18*$B$8 | D18: No public source splits conversion cost. Stated team assumption; Monte Carlo tests labor share 35-45% (Simulation tab). Ask organizers in clarification if allowed.
A19: Energy | B19: 0.12 | C19: =B19*$B$8 | D19: No public source splits conversion cost. Stated team assumption; Monte Carlo tests labor share 35-45% (Simulation tab). Ask organizers in clarification if allowed.
A20: Maintenance | B20: 0.13 | C20: =B20*$B$8 | D20: No public source splits conversion cost. Stated team assumption; Monte Carlo tests labor share 35-45% (Simulation tab). Ask organizers in clarification if allowed.
A21: Depreciation | B21: 0.25 | C21: =B21*$B$8 | D21: No public source splits conversion cost. Stated team assumption; Monte Carlo tests labor share 35-45% (Simulation tab). Ask organizers in clarification if allowed.
A22: Scrap | B22: 0.1 | C22: =B22*$B$8 | D22: No public source splits conversion cost. Stated team assumption; Monte Carlo tests labor share 35-45% (Simulation tab). Ask organizers in clarification if allowed.
A23: Check (must be 100%) | B23: =SUM(B18:B22) | C23: =SUM(C18:C22)
A25: Other team assumptions | B25: Value | C25: Unit | D25: Note
A26: New variant / model-change projects per year | B26: 3 | C26: projects/yr | D26: Rises with multi-pathway mix (Exhibit 8)
A27: Average cost per equipment modification project | B27: 10 | C27: Rp billion | D27: Team assumption, no public source. Tornado shows its NPV swing (Simulation Test 3); state it openly.
A28: Share of freed operator time converted to cash | B28: 0.5 | C28: % | D28: Rest is redeployed to kaizen / absorbs volume (no layoffs)
A31: Lever assumptions by scenario | B31: Conservative | C31: Base | D31: Optimistic | E31: What drives it / how to defend | G31: Benchmark evidence (cite in appendix)
A32: Scrap cost reduction | B32: 0.2 | C32: 0.35 | D32: 0.5 | E32: Closed-loop feedback catches sealer/inspection lapses upstream (Exhibit 4/5) | G32: Own simulation (Simulation tab): closed loop cuts in-scope scrap ~85%; x 40% scope share = ~34% plant-wide. Base 35% sits on that result.
A33: Maintenance cost reduction | B33: 0.05 | C33: 0.1 | D33: 0.15 | E33: Predictive maintenance + fewer unplanned stops | G33: McKinsey (2020, via IIoT World): maintenance cost -18 to 25%, unplanned downtime up to -50%. Our range is deliberately below. https://www.iiot-world.com/predictive-analytics/predictive-maintenance/predictive-maintenance-cost-savings/
A34: Operator NVA time eliminated (% of the 22%) | B34: 0.15 | C34: 0.3 | D34: 0.45 | E34: Intralogistics sync, digital standard work, less searching/waiting | G34: Toyota AI Platform: >10,000 man-hours/yr saved by worker-built tools (Google Cloud 2024). Omron/MPA AMR case: up to 15 km/day of operator walking and all manual crate runs eliminated (no % published). Validate with a time study in the pilot. https://robotics.omron.com/case-studies/amr-automation-intralogistics-mpa-omron/
A35: Energy cost reduction | B35: 0.02 | C35: 0.05 | D35: 0.08 | E35: Data-driven idle/standby control | G35: Nissan US plants, energy management system (ISO 50001 / SEP): 13.8% energy performance gain over 3 years, 8-21% by site. Our 2-8% is deliberately below. https://www.cleanenergyministerial.org/content/uploads/2022/03/cem-em-casestudy-nissan-usa.pdf
A36: Variant modification cost reduction | B36: 0.2 | C36: 0.35 | D36: 0.5 | E36: Common interface standard + in-house equipment + virtual verification | G36: Siemens / Wipro PARI: virtual commissioning cut on-site commissioning 70% on a 17-variant engine line. Kalypso: up to 40%. Toyota BEV plan targets halving prep lead time. https://resources.sw.siemens.com/en-US/case-study-wipro-pari/
A37: Total program investment | B37: 110 | C37: 80 | D37: 60 | E37: Must sit inside case range Rp40-120B | G37: Case Exhibit 9
A38: Annual running cost (% of cumulative investment) | B38: 0.1 | C38: 0.1 | D38: 0.08 | E38: Licences, cloud/compute, upkeep | G38: Team assumption
A39: Training & change management opex | B39: 3 | C39: 2.5 | D39: 2 | E39: Rp billion/yr: academy, coaches, kaizen time | G39: Team assumption; cross-check with Capability tab
A40: Implied variant modification time (months) | B40: =$B$15*(1-B36) | C40: =$B$15*(1-C36) | D40: =$B$15*(1-D36) | E40: Show this on the flexibility slide (vs 9 months today)
A42: Timing | B42: 2026 | C42: 2027 | D42: 2028 | E42: 2029 | F42: 2030 | G42: Sum / note
A43: Adoption ramp-up (% of full run-rate) | B43: 0.1 | C43: 0.35 | D43: 0.65 | E43: 0.9 | F43: 1 | G43: Pilot -> standardize -> rollout
A44: Investment phasing (% of total): PILOT-LIGHT | B44: 0.1 | C44: 0.15 | D44: 0.4 | E44: 0.25 | F44: 0.1 | G44: =SUM(B44:F44)
A45: Year index (t) | B45: 1 | C45: 2 | D45: 3 | E45: 4 | F45: 5 | G45: End-of-year discounting
A46: Reference only: original front-loaded phasing | B46: 0.3 | C46: 0.35 | D46: 0.25 | E46: 0.1 | F46: 0
A47: Why pilot-light: Simulation tab Test 2b. Spending little before the end-2027 gate raised P(NPV>0) from ~49% to ~85% across 10,000 runs.

Sheet Model
A1: Savings, investment and NPV by scenario (Rp billion)
A2: Program window 2026-2030 = 5-year economic life. No terminal value (conservative).
A4: Scenario: Conservative
A5: Line item | B5: Unit | C5: 2026 | D5: 2027 | E5: 2028 | F5: 2029 | G5: 2030 | H5: Total
A6: Adoption ramp-up | B6: % | C6: =Assumptions!B$43 | D6: =Assumptions!C$43 | E6: =Assumptions!D$43 | F6: =Assumptions!E$43 | G6: =Assumptions!F$43
A7: Escalation factor | B7: x | C7: =(1+Assumptions!$B$10)^(Assumptions!B$45-1) | D7: =(1+Assumptions!$B$10)^(Assumptions!C$45-1) | E7: =(1+Assumptions!$B$10)^(Assumptions!D$45-1) | F7: =(1+Assumptions!$B$10)^(Assumptions!E$45-1) | G7: =(1+Assumptions!$B$10)^(Assumptions!F$45-1)
A8: Saving: scrap | B8: Rp B | C8: =Assumptions!$B$8*Assumptions!$B$22*Assumptions!$B$32*C6*C7 | D8: =Assumptions!$B$8*Assumptions!$B$22*Assumptions!$B$32*D6*D7 | E8: =Assumptions!$B$8*Assumptions!$B$22*Assumptions!$B$32*E6*E7 | F8: =Assumptions!$B$8*Assumptions!$B$22*Assumptions!$B$32*F6*F7 | G8: =Assumptions!$B$8*Assumptions!$B$22*Assumptions!$B$32*G6*G7 | H8: =SUM(C8:G8)
A9: Saving: maintenance / downtime | B9: Rp B | C9: =Assumptions!$B$8*Assumptions!$B$20*Assumptions!$B$33*C6*C7 | D9: =Assumptions!$B$8*Assumptions!$B$20*Assumptions!$B$33*D6*D7 | E9: =Assumptions!$B$8*Assumptions!$B$20*Assumptions!$B$33*E6*E7 | F9: =Assumptions!$B$8*Assumptions!$B$20*Assumptions!$B$33*F6*F7 | G9: =Assumptions!$B$8*Assumptions!$B$20*Assumptions!$B$33*G6*G7 | H9: =SUM(C9:G9)
A10: Saving: operator NVA time | B10: Rp B | C10: =Assumptions!$B$8*Assumptions!$B$18*Assumptions!$B$14*Assumptions!$B$34*Assumptions!$B$28*C6*C7 | D10: =Assumptions!$B$8*Assumptions!$B$18*Assumptions!$B$14*Assumptions!$B$34*Assumptions!$B$28*D6*D7 | E10: =Assumptions!$B$8*Assumptions!$B$18*Assumptions!$B$14*Assumptions!$B$34*Assumptions!$B$28*E6*E7 | F10: =Assumptions!$B$8*Assumptions!$B$18*Assumptions!$B$14*Assumptions!$B$34*Assumptions!$B$28*F6*F7 | G10: =Assumptions!$B$8*Assumptions!$B$18*Assumptions!$B$14*Assumptions!$B$34*Assumptions!$B$28*G6*G7 | H10: =SUM(C10:G10)
A11: Saving: energy | B11: Rp B | C11: =Assumptions!$B$8*Assumptions!$B$19*Assumptions!$B$35*C6*C7 | D11: =Assumptions!$B$8*Assumptions!$B$19*Assumptions!$B$35*D6*D7 | E11: =Assumptions!$B$8*Assumptions!$B$19*Assumptions!$B$35*E6*E7 | F11: =Assumptions!$B$8*Assumptions!$B$19*Assumptions!$B$35*F6*F7 | G11: =Assumptions!$B$8*Assumptions!$B$19*Assumptions!$B$35*G6*G7 | H11: =SUM(C11:G11)
A12: Saving: variant modification | B12: Rp B | C12: =Assumptions!$B$26*Assumptions!$B$27*Assumptions!$B$36*C6*C7 | D12: =Assumptions!$B$26*Assumptions!$B$27*Assumptions!$B$36*D6*D7 | E12: =Assumptions!$B$26*Assumptions!$B$27*Assumptions!$B$36*E6*E7 | F12: =Assumptions!$B$26*Assumptions!$B$27*Assumptions!$B$36*F6*F7 | G12: =Assumptions!$B$26*Assumptions!$B$27*Assumptions!$B$36*G6*G7 | H12: =SUM(C12:G12)
A13: Total gross savings | B13: Rp B | C13: =SUM(C8:C12) | D13: =SUM(D8:D12) | E13: =SUM(E8:E12) | F13: =SUM(F8:F12) | G13: =SUM(G8:G12) | H13: =SUM(C13:G13)
A14: Investment (capex) | B14: Rp B | C14: =Assumptions!$B$37*Assumptions!B$44 | D14: =Assumptions!$B$37*Assumptions!C$44 | E14: =Assumptions!$B$37*Assumptions!D$44 | F14: =Assumptions!$B$37*Assumptions!E$44 | G14: =Assumptions!$B$37*Assumptions!F$44 | H14: =SUM(C14:G14)
A15: Cumulative investment | B15: Rp B | C15: =SUM($C14:C14) | D15: =SUM($C14:D14) | E15: =SUM($C14:E14) | F15: =SUM($C14:F14) | G15: =SUM($C14:G14)
A16: Running + training cost | B16: Rp B | C16: =C15*Assumptions!$B$38+Assumptions!$B$39 | D16: =D15*Assumptions!$B$38+Assumptions!$B$39 | E16: =E15*Assumptions!$B$38+Assumptions!$B$39 | F16: =F15*Assumptions!$B$38+Assumptions!$B$39 | G16: =G15*Assumptions!$B$38+Assumptions!$B$39 | H16: =SUM(C16:G16)
A17: Net cash flow | B17: Rp B | C17: =C13-C14-C16 | D17: =D13-D14-D16 | E17: =E13-E14-E16 | F17: =F13-F14-F16 | G17: =G13-G14-G16 | H17: =SUM(C17:G17)
A18: Discount factor | B18: x | C18: =1/(1+Assumptions!$B$9)^Assumptions!B$45 | D18: =1/(1+Assumptions!$B$9)^Assumptions!C$45 | E18: =1/(1+Assumptions!$B$9)^Assumptions!D$45 | F18: =1/(1+Assumptions!$B$9)^Assumptions!E$45 | G18: =1/(1+Assumptions!$B$9)^Assumptions!F$45
A19: Present value | B19: Rp B | C19: =C17*C18 | D19: =D17*D18 | E19: =E17*E18 | F19: =F17*F18 | G19: =G17*G18 | H19: =SUM(C19:G19)
A20: Cumulative net cash flow | B20: Rp B | C20: =SUM($C17:C17) | D20: =SUM($C17:D17) | E20: =SUM($C17:E17) | F20: =SUM($C17:F17) | G20: =SUM($C17:G17)
A22: Outputs
A23: NPV @ discount rate | B23: Rp B | C23: =SUM(C19:G19)
A24: IRR | B24: % | C24: =IFERROR(IRR(C17:G17),"n/a")
A25: Payback year (cumulative net turns positive) | B25: year | C25: =IF(G20<0,"Beyond 2030",2026+COUNTIF(C20:G20,"<0"))
A26: Full run-rate savings (2025 prices) | B26: Rp B/yr | C26: =Assumptions!$B$8*(Assumptions!$B$22*Assumptions!B32+Assumptions!$B$20*Assumptions!B33+Assumptions!$B$18*Assumptions!$B$14*Assumptions!B34*Assumptions!$B$28+Assumptions!$B$19*Assumptions!B35)+Assumptions!$B$26*Assumptions!$B$27*Assumptions!B36
A27: Run-rate savings as % of conversion cost | B27: % | C27: =C26/Assumptions!$B$8
A28: Implied conversion cost index | B28: index | C28: =Assumptions!$B$12*(1-C27)
A29: Share of gap to benchmark closed | B29: % | C29: =(Assumptions!$B$12-C28)/(Assumptions!$B$12-Assumptions!$B$13)
A30: NPV incl. remaining equipment value at end-2030 (book) | B30: Rp B | C30: =C23+SUMPRODUCT(C14:G14,(Assumptions!$B$45:$F$45-0.5)/Assumptions!$B$11)/(1+Assumptions!$B$9)^Assumptions!$B$11
A32: Scenario: Base
A33: Line item | B33: Unit | C33: 2026 | D33: 2027 | E33: 2028 | F33: 2029 | G33: 2030 | H33: Total
A34: Adoption ramp-up | B34: % | C34: =Assumptions!B$43 | D34: =Assumptions!C$43 | E34: =Assumptions!D$43 | F34: =Assumptions!E$43 | G34: =Assumptions!F$43
A35: Escalation factor | B35: x | C35: =(1+Assumptions!$B$10)^(Assumptions!B$45-1) | D35: =(1+Assumptions!$B$10)^(Assumptions!C$45-1) | E35: =(1+Assumptions!$B$10)^(Assumptions!D$45-1) | F35: =(1+Assumptions!$B$10)^(Assumptions!E$45-1) | G35: =(1+Assumptions!$B$10)^(Assumptions!F$45-1)
A36: Saving: scrap | B36: Rp B | C36: =Assumptions!$B$8*Assumptions!$B$22*Assumptions!$C$32*C34*C35 | D36: =Assumptions!$B$8*Assumptions!$B$22*Assumptions!$C$32*D34*D35 | E36: =Assumptions!$B$8*Assumptions!$B$22*Assumptions!$C$32*E34*E35 | F36: =Assumptions!$B$8*Assumptions!$B$22*Assumptions!$C$32*F34*F35 | G36: =Assumptions!$B$8*Assumptions!$B$22*Assumptions!$C$32*G34*G35 | H36: =SUM(C36:G36)
A37: Saving: maintenance / downtime | B37: Rp B | C37: =Assumptions!$B$8*Assumptions!$B$20*Assumptions!$C$33*C34*C35 | D37: =Assumptions!$B$8*Assumptions!$B$20*Assumptions!$C$33*D34*D35 | E37: =Assumptions!$B$8*Assumptions!$B$20*Assumptions!$C$33*E34*E35 | F37: =Assumptions!$B$8*Assumptions!$B$20*Assumptions!$C$33*F34*F35 | G37: =Assumptions!$B$8*Assumptions!$B$20*Assumptions!$C$33*G34*G35 | H37: =SUM(C37:G37)
A38: Saving: operator NVA time | B38: Rp B | C38: =Assumptions!$B$8*Assumptions!$B$18*Assumptions!$B$14*Assumptions!$C$34*Assumptions!$B$28*C34*C35 | D38: =Assumptions!$B$8*Assumptions!$B$18*Assumptions!$B$14*Assumptions!$C$34*Assumptions!$B$28*D34*D35 | E38: =Assumptions!$B$8*Assumptions!$B$18*Assumptions!$B$14*Assumptions!$C$34*Assumptions!$B$28*E34*E35 | F38: =Assumptions!$B$8*Assumptions!$B$18*Assumptions!$B$14*Assumptions!$C$34*Assumptions!$B$28*F34*F35 | G38: =Assumptions!$B$8*Assumptions!$B$18*Assumptions!$B$14*Assumptions!$C$34*Assumptions!$B$28*G34*G35 | H38: =SUM(C38:G38)
A39: Saving: energy | B39: Rp B | C39: =Assumptions!$B$8*Assumptions!$B$19*Assumptions!$C$35*C34*C35 | D39: =Assumptions!$B$8*Assumptions!$B$19*Assumptions!$C$35*D34*D35 | E39: =Assumptions!$B$8*Assumptions!$B$19*Assumptions!$C$35*E34*E35 | F39: =Assumptions!$B$8*Assumptions!$B$19*Assumptions!$C$35*F34*F35 | G39: =Assumptions!$B$8*Assumptions!$B$19*Assumptions!$C$35*G34*G35 | H39: =SUM(C39:G39)
A40: Saving: variant modification | B40: Rp B | C40: =Assumptions!$B$26*Assumptions!$B$27*Assumptions!$C$36*C34*C35 | D40: =Assumptions!$B$26*Assumptions!$B$27*Assumptions!$C$36*D34*D35 | E40: =Assumptions!$B$26*Assumptions!$B$27*Assumptions!$C$36*E34*E35 | F40: =Assumptions!$B$26*Assumptions!$B$27*Assumptions!$C$36*F34*F35 | G40: =Assumptions!$B$26*Assumptions!$B$27*Assumptions!$C$36*G34*G35 | H40: =SUM(C40:G40)
A41: Total gross savings | B41: Rp B | C41: =SUM(C36:C40) | D41: =SUM(D36:D40) | E41: =SUM(E36:E40) | F41: =SUM(F36:F40) | G41: =SUM(G36:G40) | H41: =SUM(C41:G41)
A42: Investment (capex) | B42: Rp B | C42: =Assumptions!$C$37*Assumptions!B$44 | D42: =Assumptions!$C$37*Assumptions!C$44 | E42: =Assumptions!$C$37*Assumptions!D$44 | F42: =Assumptions!$C$37*Assumptions!E$44 | G42: =Assumptions!$C$37*Assumptions!F$44 | H42: =SUM(C42:G42)
A43: Cumulative investment | B43: Rp B | C43: =SUM($C42:C42) | D43: =SUM($C42:D42) | E43: =SUM($C42:E42) | F43: =SUM($C42:F42) | G43: =SUM($C42:G42)
A44: Running + training cost | B44: Rp B | C44: =C43*Assumptions!$C$38+Assumptions!$C$39 | D44: =D43*Assumptions!$C$38+Assumptions!$C$39 | E44: =E43*Assumptions!$C$38+Assumptions!$C$39 | F44: =F43*Assumptions!$C$38+Assumptions!$C$39 | G44: =G43*Assumptions!$C$38+Assumptions!$C$39 | H44: =SUM(C44:G44)
A45: Net cash flow | B45: Rp B | C45: =C41-C42-C44 | D45: =D41-D42-D44 | E45: =E41-E42-E44 | F45: =F41-F42-F44 | G45: =G41-G42-G44 | H45: =SUM(C45:G45)
A46: Discount factor | B46: x | C46: =1/(1+Assumptions!$B$9)^Assumptions!B$45 | D46: =1/(1+Assumptions!$B$9)^Assumptions!C$45 | E46: =1/(1+Assumptions!$B$9)^Assumptions!D$45 | F46: =1/(1+Assumptions!$B$9)^Assumptions!E$45 | G46: =1/(1+Assumptions!$B$9)^Assumptions!F$45
A47: Present value | B47: Rp B | C47: =C45*C46 | D47: =D45*D46 | E47: =E45*E46 | F47: =F45*F46 | G47: =G45*G46 | H47: =SUM(C47:G47)
A48: Cumulative net cash flow | B48: Rp B | C48: =SUM($C45:C45) | D48: =SUM($C45:D45) | E48: =SUM($C45:E45) | F48: =SUM($C45:F45) | G48: =SUM($C45:G45)
A50: Outputs
A51: NPV @ discount rate | B51: Rp B | C51: =SUM(C47:G47)
A52: IRR | B52: % | C52: =IFERROR(IRR(C45:G45),"n/a")
A53: Payback year (cumulative net turns positive) | B53: year | C53: =IF(G48<0,"Beyond 2030",2026+COUNTIF(C48:G48,"<0"))
A54: Full run-rate savings (2025 prices) | B54: Rp B/yr | C54: =Assumptions!$B$8*(Assumptions!$B$22*Assumptions!C32+Assumptions!$B$20*Assumptions!C33+Assumptions!$B$18*Assumptions!$B$14*Assumptions!C34*Assumptions!$B$28+Assumptions!$B$19*Assumptions!C35)+Assumptions!$B$26*Assumptions!$B$27*Assumptions!C36
A55: Run-rate savings as % of conversion cost | B55: % | C55: =C54/Assumptions!$B$8
A56: Implied conversion cost index | B56: index | C56: =Assumptions!$B$12*(1-C55)
A57: Share of gap to benchmark closed | B57: % | C57: =(Assumptions!$B$12-C56)/(Assumptions!$B$12-Assumptions!$B$13)
A58: NPV incl. remaining equipment value at end-2030 (book) | B58: Rp B | C58: =C51+SUMPRODUCT(C42:G42,(Assumptions!$B$45:$F$45-0.5)/Assumptions!$B$11)/(1+Assumptions!$B$9)^Assumptions!$B$11
A60: Scenario: Optimistic
A61: Line item | B61: Unit | C61: 2026 | D61: 2027 | E61: 2028 | F61: 2029 | G61: 2030 | H61: Total
A62: Adoption ramp-up | B62: % | C62: =Assumptions!B$43 | D62: =Assumptions!C$43 | E62: =Assumptions!D$43 | F62: =Assumptions!E$43 | G62: =Assumptions!F$43
A63: Escalation factor | B63: x | C63: =(1+Assumptions!$B$10)^(Assumptions!B$45-1) | D63: =(1+Assumptions!$B$10)^(Assumptions!C$45-1) | E63: =(1+Assumptions!$B$10)^(Assumptions!D$45-1) | F63: =(1+Assumptions!$B$10)^(Assumptions!E$45-1) | G63: =(1+Assumptions!$B$10)^(Assumptions!F$45-1)
A64: Saving: scrap | B64: Rp B | C64: =Assumptions!$B$8*Assumptions!$B$22*Assumptions!$D$32*C62*C63 | D64: =Assumptions!$B$8*Assumptions!$B$22*Assumptions!$D$32*D62*D63 | E64: =Assumptions!$B$8*Assumptions!$B$22*Assumptions!$D$32*E62*E63 | F64: =Assumptions!$B$8*Assumptions!$B$22*Assumptions!$D$32*F62*F63 | G64: =Assumptions!$B$8*Assumptions!$B$22*Assumptions!$D$32*G62*G63 | H64: =SUM(C64:G64)
A65: Saving: maintenance / downtime | B65: Rp B | C65: =Assumptions!$B$8*Assumptions!$B$20*Assumptions!$D$33*C62*C63 | D65: =Assumptions!$B$8*Assumptions!$B$20*Assumptions!$D$33*D62*D63 | E65: =Assumptions!$B$8*Assumptions!$B$20*Assumptions!$D$33*E62*E63 | F65: =Assumptions!$B$8*Assumptions!$B$20*Assumptions!$D$33*F62*F63 | G65: =Assumptions!$B$8*Assumptions!$B$20*Assumptions!$D$33*G62*G63 | H65: =SUM(C65:G65)
A66: Saving: operator NVA time | B66: Rp B | C66: =Assumptions!$B$8*Assumptions!$B$18*Assumptions!$B$14*Assumptions!$D$34*Assumptions!$B$28*C62*C63 | D66: =Assumptions!$B$8*Assumptions!$B$18*Assumptions!$B$14*Assumptions!$D$34*Assumptions!$B$28*D62*D63 | E66: =Assumptions!$B$8*Assumptions!$B$18*Assumptions!$B$14*Assumptions!$D$34*Assumptions!$B$28*E62*E63 | F66: =Assumptions!$B$8*Assumptions!$B$18*Assumptions!$B$14*Assumptions!$D$34*Assumptions!$B$28*F62*F63 | G66: =Assumptions!$B$8*Assumptions!$B$18*Assumptions!$B$14*Assumptions!$D$34*Assumptions!$B$28*G62*G63 | H66: =SUM(C66:G66)
A67: Saving: energy | B67: Rp B | C67: =Assumptions!$B$8*Assumptions!$B$19*Assumptions!$D$35*C62*C63 | D67: =Assumptions!$B$8*Assumptions!$B$19*Assumptions!$D$35*D62*D63 | E67: =Assumptions!$B$8*Assumptions!$B$19*Assumptions!$D$35*E62*E63 | F67: =Assumptions!$B$8*Assumptions!$B$19*Assumptions!$D$35*F62*F63 | G67: =Assumptions!$B$8*Assumptions!$B$19*Assumptions!$D$35*G62*G63 | H67: =SUM(C67:G67)
A68: Saving: variant modification | B68: Rp B | C68: =Assumptions!$B$26*Assumptions!$B$27*Assumptions!$D$36*C62*C63 | D68: =Assumptions!$B$26*Assumptions!$B$27*Assumptions!$D$36*D62*D63 | E68: =Assumptions!$B$26*Assumptions!$B$27*Assumptions!$D$36*E62*E63 | F68: =Assumptions!$B$26*Assumptions!$B$27*Assumptions!$D$36*F62*F63 | G68: =Assumptions!$B$26*Assumptions!$B$27*Assumptions!$D$36*G62*G63 | H68: =SUM(C68:G68)
A69: Total gross savings | B69: Rp B | C69: =SUM(C64:C68) | D69: =SUM(D64:D68) | E69: =SUM(E64:E68) | F69: =SUM(F64:F68) | G69: =SUM(G64:G68) | H69: =SUM(C69:G69)
A70: Investment (capex) | B70: Rp B | C70: =Assumptions!$D$37*Assumptions!B$44 | D70: =Assumptions!$D$37*Assumptions!C$44 | E70: =Assumptions!$D$37*Assumptions!D$44 | F70: =Assumptions!$D$37*Assumptions!E$44 | G70: =Assumptions!$D$37*Assumptions!F$44 | H70: =SUM(C70:G70)
A71: Cumulative investment | B71: Rp B | C71: =SUM($C70:C70) | D71: =SUM($C70:D70) | E71: =SUM($C70:E70) | F71: =SUM($C70:F70) | G71: =SUM($C70:G70)
A72: Running + training cost | B72: Rp B | C72: =C71*Assumptions!$D$38+Assumptions!$D$39 | D72: =D71*Assumptions!$D$38+Assumptions!$D$39 | E72: =E71*Assumptions!$D$38+Assumptions!$D$39 | F72: =F71*Assumptions!$D$38+Assumptions!$D$39 | G72: =G71*Assumptions!$D$38+Assumptions!$D$39 | H72: =SUM(C72:G72)
A73: Net cash flow | B73: Rp B | C73: =C69-C70-C72 | D73: =D69-D70-D72 | E73: =E69-E70-E72 | F73: =F69-F70-F72 | G73: =G69-G70-G72 | H73: =SUM(C73:G73)
A74: Discount factor | B74: x | C74: =1/(1+Assumptions!$B$9)^Assumptions!B$45 | D74: =1/(1+Assumptions!$B$9)^Assumptions!C$45 | E74: =1/(1+Assumptions!$B$9)^Assumptions!D$45 | F74: =1/(1+Assumptions!$B$9)^Assumptions!E$45 | G74: =1/(1+Assumptions!$B$9)^Assumptions!F$45
A75: Present value | B75: Rp B | C75: =C73*C74 | D75: =D73*D74 | E75: =E73*E74 | F75: =F73*F74 | G75: =G73*G74 | H75: =SUM(C75:G75)
A76: Cumulative net cash flow | B76: Rp B | C76: =SUM($C73:C73) | D76: =SUM($C73:D73) | E76: =SUM($C73:E73) | F76: =SUM($C73:F73) | G76: =SUM($C73:G73)
A78: Outputs
A79: NPV @ discount rate | B79: Rp B | C79: =SUM(C75:G75)
A80: IRR | B80: % | C80: =IFERROR(IRR(C73:G73),"n/a")
A81: Payback year (cumulative net turns positive) | B81: year | C81: =IF(G76<0,"Beyond 2030",2026+COUNTIF(C76:G76,"<0"))
A82: Full run-rate savings (2025 prices) | B82: Rp B/yr | C82: =Assumptions!$B$8*(Assumptions!$B$22*Assumptions!D32+Assumptions!$B$20*Assumptions!D33+Assumptions!$B$18*Assumptions!$B$14*Assumptions!D34*Assumptions!$B$28+Assumptions!$B$19*Assumptions!D35)+Assumptions!$B$26*Assumptions!$B$27*Assumptions!D36
A83: Run-rate savings as % of conversion cost | B83: % | C83: =C82/Assumptions!$B$8
A84: Implied conversion cost index | B84: index | C84: =Assumptions!$B$12*(1-C83)
A85: Share of gap to benchmark closed | B85: % | C85: =(Assumptions!$B$12-C84)/(Assumptions!$B$12-Assumptions!$B$13)
A86: NPV incl. remaining equipment value at end-2030 (book) | B86: Rp B | C86: =C79+SUMPRODUCT(C70:G70,(Assumptions!$B$45:$F$45-0.5)/Assumptions!$B$11)/(1+Assumptions!$B$9)^Assumptions!$B$11

Sheet Dashboard
A1: Financial summary for the deck (Rp billion)
A3: Metric | B3: Conservative | C3: Base | D3: Optimistic
A4: NPV (10%) | B4: =Model!C23 | C4: =Model!C51 | D4: =Model!C79
A5: IRR | B5: =Model!C24 | C5: =Model!C52 | D5: =Model!C80
A6: Payback year | B6: =Model!C25 | C6: =Model!C53 | D6: =Model!C81
A7: Gross savings in 2030 | B7: =Model!G13 | C7: =Model!G41 | D7: =Model!G69
A8: Full run-rate savings / yr | B8: =Model!C26 | C8: =Model!C54 | D8: =Model!C82
A9: Run-rate as % of conversion cost | B9: =Model!C27 | C9: =Model!C55 | D9: =Model!C83
A10: Implied cost index (today 106) | B10: =Model!C28 | C10: =Model!C56 | D10: =Model!C84
A11: Gap to new-player benchmark closed | B11: =Model!C29 | C11: =Model!C57 | D11: =Model!C85
A12: NPV incl. remaining equipment value | B12: =Model!C30 | C12: =Model!C58 | D12: =Model!C86
A13: Investment (Rp B) | B13: =Assumptions!B37 | C13: =Assumptions!C37 | D13: =Assumptions!D37
A14: Variant modification time (months, today 9) | B14: =Assumptions!B40 | C14: =Assumptions!C40 | D14: =Assumptions!D40
A15: Note: with pilot-light phasing the 2026 outflow is small, so IRR looks extreme. Lead with NPV and P(NPV>0) from the Simulation tab, not IRR.
A16: Base case savings by lever | B16: 2026 | C16: 2027 | D16: 2028 | E16: 2029 | F16: 2030
A17: Scrap | B17: =Model!C36 | C17: =Model!D36 | D17: =Model!E36 | E17: =Model!F36 | F17: =Model!G36
A18: Maintenance | B18: =Model!C37 | C18: =Model!D37 | D18: =Model!E37 | E18: =Model!F37 | F18: =Model!G37
A19: Operator NVA | B19: =Model!C38 | C19: =Model!D38 | D19: =Model!E38 | E19: =Model!F38 | F19: =Model!G38
A20: Energy | B20: =Model!C39 | C20: =Model!D39 | D20: =Model!E39 | E20: =Model!F39 | F20: =Model!G39
A21: Variant modification | B21: =Model!C40 | C21: =Model!D40 | D21: =Model!E40 | E21: =Model!F40 | F21: =Model!G40

Sheet Breakeven
A1: How much saving pays back the program?
A2: Simplified: investment at start, steady savings from year 1 growing with escalation, no running cost.
A4: Discount rate | B4: =Assumptions!B9
A5: Savings growth (escalation) | B5: =Assumptions!B10
A6: Years | B6: =Assumptions!B11
A7: Growing annuity factor (PV of Rp1 first-year saving) | B7: =(1-((1+B5)/(1+B4))^B6)/(B4-B5)
A8: Annual conversion cost (Rp B) | B8: =Assumptions!B8
A10: Investment (Rp B) | B10: Break-even first-year saving (Rp B) | C10: % of conversion cost | D10: Share of gap to benchmark that must close
A11: 40 | B11: =A11/$B$7 | C11: =B11/$B$8 | D11: =C11*Assumptions!$B$12/(Assumptions!$B$12-Assumptions!$B$13)
A12: 60 | B12: =A12/$B$7 | C12: =B12/$B$8 | D12: =C12*Assumptions!$B$12/(Assumptions!$B$12-Assumptions!$B$13)
A13: 80 | B13: =A13/$B$7 | C13: =B13/$B$8 | D13: =C13*Assumptions!$B$12/(Assumptions!$B$12-Assumptions!$B$13)
A14: 100 | B14: =A14/$B$7 | C14: =B14/$B$8 | D14: =C14*Assumptions!$B$12/(Assumptions!$B$12-Assumptions!$B$13)
A15: 120 | B15: =A15/$B$7 | C15: =B15/$B$8 | D15: =C15*Assumptions!$B$12/(Assumptions!$B$12-Assumptions!$B$13)
A17: Reading: if break-even needs only a small share of the gap closed, the case for investing is strong.
A19: NPV sensitivity grid (simplified): rows = investment, columns = first-year savings (Rp B)
A20: Invest \ Savings | B20: 10 | C20: 20 | D20: 30 | E20: 40 | F20: 50 | G20: 60
A21: 40 | B21: =B$20*$B$7-$A21 | C21: =C$20*$B$7-$A21 | D21: =D$20*$B$7-$A21 | E21: =E$20*$B$7-$A21 | F21: =F$20*$B$7-$A21 | G21: =G$20*$B$7-$A21
A22: 60 | B22: =B$20*$B$7-$A22 | C22: =C$20*$B$7-$A22 | D22: =D$20*$B$7-$A22 | E22: =E$20*$B$7-$A22 | F22: =F$20*$B$7-$A22 | G22: =G$20*$B$7-$A22
A23: 80 | B23: =B$20*$B$7-$A23 | C23: =C$20*$B$7-$A23 | D23: =D$20*$B$7-$A23 | E23: =E$20*$B$7-$A23 | F23: =F$20*$B$7-$A23 | G23: =G$20*$B$7-$A23
A24: 100 | B24: =B$20*$B$7-$A24 | C24: =C$20*$B$7-$A24 | D24: =D$20*$B$7-$A24 | E24: =E$20*$B$7-$A24 | F24: =F$20*$B$7-$A24 | G24: =G$20*$B$7-$A24
A25: 120 | B25: =B$20*$B$7-$A25 | C25: =C$20*$B$7-$A25 | D25: =D$20*$B$7-$A25 | E25: =E$20*$B$7-$A25 | F25: =F$20*$B$7-$A25 | G25: =G$20*$B$7-$A25

Sheet Capability
A1: Workforce capability & engineer time model (SQ3 / SQ4 workforce impact)
A2: Formulas only. Starting points from Exhibits 6A and 7; yellow cells are academy / knowledge assumptions to defend.
A4: Academy assumption | B4: Value | C4: Note
A5: Promotion rate L1 -> L2 per year | B5: 0.3 | C5: Share of L1 engineers reaching L2 each year via academy cohort
A6: Promotion rate L2 -> L3 per year | B6: 0.2 | C6: Needs project-based learning in the pilot
A7: Promotion rate L3 -> L4 per year | B7: 0.1 | C7: Expert level; partner / university collaboration
A8: Annual cut in routine-support share (pct points) | B8: 0.04 | C8: From knowledge base + citizen tools absorbing troubleshooting
A9: Floor for routine-support share | B9: 0.45 | C9: Some routine work always remains
A10: Engineer working hours per year | B10: 1800 | C10: Per engineer
A11: Engineers in production engineering team | B11: 30 | C11: Exhibit 7: N = 30 per field
A12: Annual rise in critical know-how documented (pct points) | B12: 0.1 | C12: Knowledge capture sprints with seniors
A13: Ramp-up months saved per +10 pts documented know-how | B13: 1.2 | C13: Assumption: tested in pilot cohort
A15: Software & AI (members per level) | B15: 2025 | C15: 2026 | D15: 2027 | E15: 2028 | F15: 2029 | G15: 2030
A16: Level 1 basic | B16: 20 | C16: =B16*(1-$B$5) | D16: =C16*(1-$B$5) | E16: =D16*(1-$B$5) | F16: =E16*(1-$B$5) | G16: =F16*(1-$B$5)
A17: Level 2 intermediate | B17: 8 | C17: =B17*(1-$B$6)+B16*$B$5 | D17: =C17*(1-$B$6)+C16*$B$5 | E17: =D17*(1-$B$6)+D16*$B$5 | F17: =E17*(1-$B$6)+E16*$B$5 | G17: =F17*(1-$B$6)+F16*$B$5
A18: Level 3 proficient | B18: 2 | C18: =B18*(1-$B$7)+B17*$B$6 | D18: =C18*(1-$B$7)+C17*$B$6 | E18: =D18*(1-$B$7)+D17*$B$6 | F18: =E18*(1-$B$7)+E17*$B$6 | G18: =F18*(1-$B$7)+F17*$B$6
A19: Level 4 expert | B19: 0 | C19: =B19+B18*$B$7 | D19: =C19+C18*$B$7 | E19: =D19+D18*$B$7 | F19: =E19+E18*$B$7 | G19: =F19+F18*$B$7
A20: Engineers at L3+ | B20: =B18+B19 | C20: =C18+C19 | D20: =D18+D19 | E20: =E18+E19 | F20: =F18+F19 | G20: =G18+G19
A22: Programming (members per level) | B22: 2025 | C22: 2026 | D22: 2027 | E22: 2028 | F22: 2029 | G22: 2030
A23: Level 1 basic | B23: 14 | C23: =B23*(1-$B$5) | D23: =C23*(1-$B$5) | E23: =D23*(1-$B$5) | F23: =E23*(1-$B$5) | G23: =F23*(1-$B$5)
A24: Level 2 intermediate | B24: 10 | C24: =B24*(1-$B$6)+B23*$B$5 | D24: =C24*(1-$B$6)+C23*$B$5 | E24: =D24*(1-$B$6)+D23*$B$5 | F24: =E24*(1-$B$6)+E23*$B$5 | G24: =F24*(1-$B$6)+F23*$B$5
A25: Level 3 proficient | B25: 5 | C25: =B25*(1-$B$7)+B24*$B$6 | D25: =C25*(1-$B$7)+C24*$B$6 | E25: =D25*(1-$B$7)+D24*$B$6 | F25: =E25*(1-$B$7)+E24*$B$6 | G25: =F25*(1-$B$7)+F24*$B$6
A26: Level 4 expert | B26: 1 | C26: =B26+B25*$B$7 | D26: =C26+C25*$B$7 | E26: =D26+D25*$B$7 | F26: =E26+E25*$B$7 | G26: =F26+F25*$B$7
A27: Engineers at L3+ | B27: =B25+B26 | C27: =C25+C26 | D27: =D25+D26 | E27: =E25+E26 | F27: =F25+F26 | G27: =G25+G26
A29: Engineer time & knowledge | B29: 2025 | C29: 2026 | D29: 2027 | E29: 2028 | F29: 2029 | G29: 2030
A30: Routine support share | B30: 0.65 | C30: =MAX($B$9,B30-$B$8) | D30: =MAX($B$9,C30-$B$8) | E30: =MAX($B$9,D30-$B$8) | F30: =MAX($B$9,E30-$B$8) | G30: =MAX($B$9,F30-$B$8)
A31: Improvement & development share | B31: =0.25+($B$30-B30) | C31: =0.25+($B$30-C30) | D31: =0.25+($B$30-D30) | E31: =0.25+($B$30-E30) | F31: =0.25+($B$30-F30) | G31: =0.25+($B$30-G30)
A32: Improvement hours (team / yr) | B32: =B31*$B$10*$B$11 | C32: =C31*$B$10*$B$11 | D32: =D31*$B$10*$B$11 | E32: =E31*$B$10*$B$11 | F32: =F31*$B$10*$B$11 | G32: =G31*$B$10*$B$11
A33: Extra improvement hours vs 2025 | B33: =B32-$B$32 | C33: =C32-$B$32 | D33: =D32-$B$32 | E33: =E32-$B$32 | F33: =F32-$B$32 | G33: =G32-$B$32
A34: Ideas per engineer (scales with improvement time) | B34: 2.4 | C34: =$B$34*C31/$B$31 | D34: =$B$34*D31/$B$31 | E34: =$B$34*E31/$B$31 | F34: =$B$34*F31/$B$31 | G34: =$B$34*G31/$B$31
A35: Critical know-how documented | B35: 0.33 | C35: =MIN(0.95,B35+$B$12) | D35: =MIN(0.95,C35+$B$12) | E35: =MIN(0.95,D35+$B$12) | F35: =MIN(0.95,E35+$B$12) | G35: =MIN(0.95,F35+$B$12)
A36: Months for new engineer to work independently | B36: 15 | C36: =MAX(6,$B$36-(C35-$B$35)*10*$B$13) | D36: =MAX(6,$B$36-(D35-$B$35)*10*$B$13) | E36: =MAX(6,$B$36-(E35-$B$35)*10*$B$13) | F36: =MAX(6,$B$36-(F35-$B$35)*10*$B$13) | G36: =MAX(6,$B$36-(G35-$B$35)*10*$B$13)
A38: Compare with KPI targets
A39: Software & AI engineers at L3+ in 2030 (feeds KPIs tab) | B39: =G20
A40: Programming engineers at L3+ in 2030 (feeds KPIs tab) | B40: =G27
A41: Engineer improvement share 2030 (feeds KPIs tab) | B41: =G31
A42: Extra improvement hours per year by 2030 | B42: =G33
A43: Reading: if the model misses a KPI target, either the target or the academy design must change. Keep the two consistent in the deck.

Sheet KPIs
A1: KPI tree: baseline from exhibits, targets are suggestions to debate
A3: Level | B3: KPI | C3: Baseline | D3: Pilot target (2027) | E3: Target 2030 | F3: Source of baseline | G3: Why judges care
A4: Outcome: cost | B4: Conversion cost index (2023=100) | C4: 106 | D4: 102 | E4: =Dashboard!C10 | F4: Exhibit 3 | G4: Headline competitiveness vs benchmark 89
A5: Outcome: quality | B5: Scrap index | C5: 108 | D5: 95 | E5: 75 | F5: Exhibit 4 (VERIFY) | G5: Direct cost + quality signal
A6: Outcome: quality | B6: Defects escaping downstream (index) | C6: 103 | D6: 90 | E6: 60 | F6: Exhibit 4 (VERIFY) | G6: Proves the closed loop works
A7: Outcome: flexibility | B7: Equipment modification time per variant (months) | C7: 9 | D7: 7 | E7: =Dashboard!C14 | F7: Exhibit 4 | G7: Multi-pathway readiness
A8: Driver: process | B8: Unplanned downtime (index) | C8: 111 | D8: 100 | E8: 75 | F8: Exhibit 4 | G8: Maintenance shift to predictive
A9: Driver: process | B9: Operator NVA time (% hours) | C9: 0.22 | D9: 0.19 | E9: 0.15 | F9: Exhibit 4 | G9: Productivity
A10: Driver: process | B10: Processes on common data/interface standard (%) | C10: 0 | D10: 0.15 | E10: 0.8 | F10: New KPI | G10: Measures integration, not gadgets
A11: Driver: people | B11: Engineer time on improvement (%) | C11: 0.25 | D11: 0.3 | E11: =Capability!G31 | F11: Exhibit 6A | G11: Talent not wasted
A12: Driver: people | B12: Improvement ideas per engineer per year | C12: 2.4 | D12: 3 | E12: =Capability!G34 | F12: Exhibit 6A | G12: Kaizen engine restarted
A13: Driver: people | B13: Ideas implemented (% submitted) | C13: 0.28 | D13: 0.35 | E13: 0.5 | F13: Exhibit 6A | G13: Ideas turn into value
A14: Driver: people | B14: Operators trained on data-driven tools (%) | C14: 0.18 | D14: 0.5 | E14: 0.9 | F14: Exhibit 6B | G14: Adoption
A15: Driver: people | B15: Operators overriding automated alerts (%) | C15: 0.31 | D15: 0.2 | E15: 0.1 | F15: Exhibit 6B | G15: Trust in the system
A16: Driver: knowledge | B16: Critical know-how documented & shared (%) | C16: 0.33 | D16: 0.5 | E16: =Capability!G35 | F16: Exhibit 6A | G16: Knowledge no longer in 1-2 heads
A17: Driver: knowledge | B17: Months for new engineer to work independently | C17: 15 | D17: 13 | E17: =Capability!G36 | F17: Exhibit 6A | G17: Knowledge transfer speed
A18: Driver: capability | B18: Engineers at Software & AI level 3+ (of 30) | C18: 2 | D18: 6 | E18: =Capability!B39 | F18: Exhibit 7 | G18: In-house capability built
A19: Driver: capability | B19: Engineers at Programming level 3+ (of 30) | C19: 6 | D19: 10 | E19: =Capability!B40 | F19: Exhibit 7 | G19: In-house capability built

Sheet Roadmap
A1: Roadmap template 2026-2030 (edit to match your chosen idea)
A3: Phase | B3: 0. Prepare (Q4 2026) | C3: 1. Pilot | D3: 2. Standardize | E3: 3. Roll out | F3: 4. Scale & sustain
A4: Quick wins (protect the ramp-up) | B4: Sealer closed loop on existing CCTV AI camera after Oct 2026 validation; digital andon for alerts; idea channel live | C4: First citizen-built tools in pilot; top-20 troubleshooting know-how captured; monthly savings tracked vs plan | D4: Copy proven quick wins to 2-3 areas | E4: Quick-win playbook in standard work | F4: Continuous kaizen pipeline
A5: Process & quality loop | B5: Map pilot area value stream; define stop/correct rules; baseline KPIs | C5: Closed-loop feedback live in pilot area (e.g. sealer -> inspection) | D5: Standard loop design + yokoten to 2-3 areas | E5: All vehicle processes Karawang I & II | F5: Extend to engine plants (Sunter, Karawang III)
A6: Data & equipment standard | B6: Draft common interface/data standard; inventory equipment generations | C6: Pilot area on the standard | D6: Standard mandatory for new/modified equipment | E6: Legacy retrofit by priority | F6: Variant change by configuration
A7: People & kaizen | B7: Idea channel launched; change champions per line | C7: Operators in pilot trained; first citizen-built tools | D7: Kaizen + data skills in standard training | E7: Plant-wide adoption; recognition system | F7: Self-sustaining improvement culture
A8: Knowledge | B8: Identify critical know-how held by 1-2 seniors | C8: Capture & validate top items for pilot area | D8: Knowledge base linked to standard work | E8: All critical processes covered | F8: Living knowledge updated through kaizen
A9: Capability (Exhibit 7) | B9: Skills assessment; academy design | C9: Cohort 1 (Software & AI L1 -> L2) | D9: Cohort 2 + first L3 engineers | E9: Internal trainers from L3 engineers | F9: Target L3+ count reached
A10: Technology building blocks | B10: AI camera validation completes (Oct 2026) | C10: Use validated building blocks in pilot | D10: Reusable components library | E10: Scale infrastructure | F10: Continuous upgrade
A11: Partners | B11: Decide build vs partner per component | C11: Partners for distinctive tech only | D11: Knowledge transfer clauses | E11: Reduce dependency | F11: Strategic partnerships
A12: Gate / go-no-go | B12: Pilot area + KPIs agreed | C12: Pilot KPIs met? | D12: Standard proven in 2+ areas? | E12: Rollout on budget? | F12: 2030 targets met
A13: Investment share | B13: =Assumptions!B44 | C13: =Assumptions!C44 | D13: =Assumptions!D44 | E13: =Assumptions!E44 | F13: =Assumptions!F44
A15: Years per phase: align to Assumptions timing row (2026 = prepare/pilot start, 2027 pilot, 2028 standardize, 2029 rollout, 2030 scale).
A16: Why quick wins matter: Simulation Test 2b, F: if savings arrive one year late, P(NPV>0) falls from ~85% to ~33%.

Sheet Risks
A1: Risk register (score = likelihood x impact, 1-5 each)
A3: Risk | B3: Likelihood | C3: Impact | D3: Score | E3: Mitigation built into the idea | F3: Early-warning KPI | G3: Evidence / test | H3: Owner
A4: Operators distrust or override AI alerts | B4: 4 | C4: 5 | D4: =B4*C4 | E4: Co-design alerts with team leaders; explain-why alerts; training before go-live; override reasons logged as kaizen input | F4: Alert override rate (31% today) | G4: Simulation: dismissals at 31% cut the scrap gain from ~85% to ~65% | H4: People lead
A5: Pilot adoption below plan | B5: 3 | C5: 5 | D5: =B5*C5 | E5: Pilot-light phasing; go/no-go gate end-2027 on adoption + scrap KPIs | F5: Adoption %, pilot KPI hit rate | G5: Simulation Test 2b: gate + pilot-light raises P(NPV>0) | H5: Program lead
A6: AI camera fails accuracy/durability validation (Oct 2026) | B6: 2 | C6: 4 | D6: =B6*C6 | E6: Loop design is sensor-agnostic; fall back to operator check + digital andon while model is retrained | F6: Validation accuracy vs threshold | G6: Case: validation target Oct 2026 | H6: Engineering
A7: Data integration harder than expected (legacy equipment) | B7: 4 | C7: 4 | D7: =B7*C7 | E7: Start with pilot area only; common interface standard for new equipment first; retrofit by priority | F7: % pilot equipment on standard | G7: Exhibit 5: no common interface today | H7: Engineering
A8: Engineers lack software/AI skills to build in-house | B8: 4 | C8: 4 | D8: =B8*C8 | E8: Academy cohorts; partner for first build with knowledge-transfer clause | F8: Engineers at L3+ (Capability tab) | G8: Exhibit 7: 2 of 30 at L3+ in Software & AI | H8: People lead
A9: Senior experts lack time to capture know-how | B9: 3 | C9: 3 | D9: =B9*C9 | E9: Protected capture sprints; recognition; AI-assisted interview transcripts validated by experts | F9: % critical know-how documented | G9: Exhibit 6A | H9: Knowledge lead
A10: Savings not converted to cash (freed time absorbed) | B10: 3 | C10: 3 | D10: =B10*C10 | E10: Redeploy freed time to kaizen with tracked outcomes; no-layoff pledge to protect trust | F10: Hours redeployed vs ideas implemented | G10: Assumptions: 50% cash realization | H10: Finance
A11: Savings ramp slower than plan (pilot results arrive late) | B11: 3 | C11: 5 | D11: =B11*C11 | E11: Start Phase 0 now on existing CCTV camera; pick quick wins for 2026-27; weekly pilot KPI review | F11: Pilot savings vs plan each quarter | G11: Simulation Test 2b, F: one-year delay cuts P(NPV>0) from ~85% to ~33% | H11: Program lead
A12: BEV volume ramps faster than plan (aggressive scenario) | B12: 2 | C12: 4 | D12: =B12*C12 | E12: Plug-and-produce standard lowers variant change cost; simulation-first preparation | F12: Months per variant change | G12: Exhibit 8 aggressive scenario: BEV 20% by 2030 | H12: Program lead
A13: Cybersecurity / data-governance issue from connected equipment | B13: 2 | C13: 4 | D13: =B13*C13 | E13: Segmented plant network; access governance in the data standard | F13: Security incidents | G13: Team judgement | H13: IT

Sheet QA_Bank
A1: Likely judge questions: answer outline, evidence, owner
A3: # | B3: Question | C3: Answer outline | D3: Evidence to cite | E3: Owner
A4: 1 | B4: Why is this not just buying an AI camera? | C4: Tech at end-of-line raises scrap; value comes from where the check sits, how fast feedback travels, and who acts | D4: Simulation Test 1 (scenario 2 vs 4) | E4: M2
A5: 2 | B5: What if operators don't trust the system? | C5: People design is in the idea: co-designed alerts, training first, overrides become kaizen input | D5: Exhibit 6B (31% override); dismissal chart in Simulation | E5: M1
A6: 3 | B6: Why this pilot area? | C6: Largest gap between processes, clear defect-escape story, AI camera building block ready Oct 2026 | D6: Exhibits 4, 5; gap heat map | E6: M2
A7: 4 | B7: How confident are you in the savings? | C7: Base NPV + Monte Carlo probability; gate protects downside; ranges below external benchmarks | D7: Dashboard, Simulation Test 2/2b, Assumptions col G | E7: M3
A8: 5 | B8: Which assumption hurts most if wrong? | C8: Name top tornado drivers and how the pilot tests each | D8: Simulation Test 3 | E8: M3
A9: 6 | B9: Why in-house instead of a vendor? | C9: Cheaper, flexible, connects to plant systems, builds capability; partner only for distinctive tech with knowledge transfer | D9: Case text on in-house strategy; Toyota insourcing (Toyota 2023) | E9: M2
A10: 7 | B10: Will people lose jobs? | C10: Freed time redeployed to kaizen and new pathways; cash conversion only 50% assumed | D10: Assumptions row 28; Capability tab | E10: M1
A11: 8 | B11: How does this help BEV / multi-pathway? | C11: Common interface + simulation-first preparation cut variant change months | D11: Dashboard months per variant; Exhibit 8; Siemens/Wipro PARI benchmark | E11: M2
A12: 9 | B12: What happens if the AI camera fails validation? | C12: Loop is sensor-agnostic: digital andon + operator check while retraining | D12: Risks tab | E12: M2
A13: 10 | B13: How do you capture senior know-how? | C13: Capture sprints, AI-assisted interviews validated by experts, linked to standard work | D13: Exhibit 6A; O-Beya precedent (Microsoft 2024) | E13: M1
A14: 11 | B14: How is this different from what Toyota Japan does? | C14: Adapted to TMMIN: integrates quality loop + data standard + knowledge in one system, gated for local budget | D14: Ideation refs | E14: M1
A15: 12 | B15: What do you need from TMMIN leadership now? | C15: Approve pilot area, Phase 0 budget, protected kaizen time, data standard ownership | D15: Roadmap tab | E15: M1
... A18: 15 | B18: Is Rp[x]B realistic within the Rp40-120B range? | C18: Bottom-up by phase; pilot-light spends 25% before gate | D18: Assumptions rows 37, 44 | E18: M3
